Workbook

Sheet Relação de NF's
A1: Area | B1: Documento | C1: Pacote | D1: Categoria | E1: Razão Social | F1: Tipo | G1: CNPJ/CPF | H1: Filial | I1: Valor Doc | J1: Emissão | K1: Referência | L1: Munícipio | M1: UF | N1: CFOP | O1: Atualizado Por | S1: Janeiro | T1: Fevereiro | U1: Março | V1: Abril | W1: Maio | X1: Junho | Y1: Julho | Z1: Agosto | AA1: Setembro | AB1: Outubro | AC1: Novembro | AD1: Dezembro
A2: =VLOOKUP($E2,Fornecedores!$A:$C,3,0) -> Frota | B2: AGMTZ-2883681 | C2: =IFERROR(VLOOKUP($E2,Fornecedores!$A:$E,4,0),"") -> OPE Merchandising | D2: =IFERROR(VLOOKUP($E2,Fornecedores!$A:$E,5,0),"") -> Locação | E2: LOCALIZA FLEET S/A | F2: FT | G2: 02.286.479/0001-08 | H2: 87 | I2: 34.5 | J2: 46006 | K2: 46028 | L2: BELO HORIZONTE | M2: MG | N2: 1556 | O2: GABRIEL.ALBINO | Q2: =SUM(R2:AD2)-I2 -> 0 | S2: =SUMIFS('Doc''s Pagos | Rodopar 108'!$J:$J,'Doc''s Pagos | Rodopar 108'!$A:$A,$B2&$E2&$F2&$J2,'Doc''s Pagos | Rodopar 108'!$B:$B,S$1)+SUMIFS('Doc Há Pagar | Rodopar 1015'!$J:$J,'Doc Há Pagar | Rodopar 1015'!$A:$A,$B2&$E2&$F2,'Doc Há Pagar | Rodopar 1015'!$B:$B,S$1) -> 34.5 | T2: =SUMIFS('Doc''s Pagos | Rodopar 108'!$J:$J,'Doc''s Pagos | Rodopar 108'!$A:$A,$B2&$E2&$F2&$J2,'Doc''s Pagos | Rodopar 108'!$B:$B,T$1)+SUMIFS('Doc Há Pagar | Rodopar 1015'!$J:$J,'Doc Há Pagar | Rodopar 1015'!$A:$A,$B2&$E2&$F2,'Doc Há Pagar | Rodopar 1015'!$B:$B,T$1) -> 0 | U2: =SUMIFS('Doc''s Pagos | Rodopar 108'!$J:$J,'Doc''s Pagos | Rodopar 108'!$A:$A,$B2&$E2&$F2&$J2,'Doc''s Pagos | Rodopar 108'!$B:$B,U$1)+SUMIFS('Doc Há Pagar | Rodopar 1015'!$J:$J,'Doc Há Pagar | Rodopar 1015'!$A:$A,$B2&$E2&$F2,'Doc Há Pagar | Rodopar 1015'!$B:$B,U$1) -> 0 | V2: =SUMIFS('Doc''s Pagos | Rodopar 108'!$J:$J,'Doc''s Pagos | Rodopar 108'!$A:$A,$B2&$E2&$F2&$J2,'Doc''s Pagos | Rodopar 108'!$B:$B,V$1)+SUMIFS('Doc Há Pagar | Rodopar 1015'!$J:$J,'Doc Há Pagar | Rodopar 1015'!$A:$A,$B2&$E2&$F2,'Doc Há Pagar | Rodopar 1015'!$B:$B,V$1) -> 0 | W2: =SUMIFS('Doc''s Pagos | Rodopar 108'!$J:$J,'Doc''s Pagos | Rodopar 108'!$A:$A,$B2&$E2&$F2&$J2,'Doc''s Pagos | Rodopar 108'!$B:$B,W$1)+SUMIFS('Doc Há Pagar | Rodopar 1015'!$J:$J,'Doc Há Pagar | Rodopar 1015'!$A:$A,$B2&$E2&$F2,'Doc Há Pagar | Rodopar 1015'!$B:$B,W$1) -> 0 | X2: =SUMIFS('Doc''s Pagos | Rodopar 108'!$J:$J,'Doc''s Pagos | Rodopar 108'!$A:$A,$B2&$E2&$F2&$J2,'Doc''s Pagos | Rodopar 108'!$B:$B,X$1)+SUMIFS('Doc Há Pagar | Rodopar 1015'!$J:$J,'Doc Há Pagar | Rodopar 1015'!$A:$A,$B2&$E2&$F2,'Doc Há Pagar | Rodopar 1015'!$B:$B,X$1) -> 0 | Y2: =SUMIFS('Doc''s Pagos | Rodopar 108'!$J:$J,'Doc''s Pagos | Rodopar 108'!$A:$A,$B2&$E2&$F2&$J2,'Doc''s Pagos | Rodopar 108'!$B:$B,Y$1)+SUMIFS('Doc Há Pagar | Rodopar 1015'!$J:$J,'Doc Há Pagar | Rodopar 1015'!$A:$A,$B2&$E2&$F2,'Doc Há Pagar | Rodopar 1015'!$B:$B,Y$1) -> 0 | Z2: =SUMIFS('Doc''s Pagos | Rodopar 108'!$J:$J,'Doc''s Pagos | Rodopar 108'!$A:$A,$B2&$E2&$F2&$J2,'Doc''s Pagos | Rodopar 108'!$B:$B,Z$1)+SUMIFS('Doc Há Pagar | Rodopar 1015'!$J:$J,'Doc Há Pagar | Rodopar 1015'!$A:$A,$B2&$E2&$F2,'Doc Há Pagar | Rodopar 1015'!$B:$B,Z$1) -> 0 | ... AD2: =SUMIFS('Doc''s Pagos | Rodopar 108'!$J:$J,'Doc''s Pagos | Rodopar 108'!$A:$A,$B2&$E2&$F2&$J2,'Doc''s Pagos | Rodopar 108'!$B:$B,AD$1)+SUMIFS('Doc Há Pagar | Rodopar 1015'!$J:$J,'Doc Há Pagar | Rodopar 1015'!$A:$A,$B2&$E2&$F2,'Doc Há Pagar | Rodopar 1015'!$B:$B,AD$1) -> 0
A3: =VLOOKUP($E3,Fornecedores!$A:$C,3,0) -> Frota | B3: 2631 | C3: =IFERROR(VLOOKUP($E3,Fornecedores!$A:$E,4,0),"") -> Manutenção | D3: =IFERROR(VLOOKUP($E3,Fornecedores!$A:$E,5,0),"") -> Frota Leve OPE | E3: MECANICA CRISTO REI LTDA | F3: NFE | G3: 71.299.614/0001-64 | H3: 87 | I3: 898 | J3: 46013 | K3: 46028 | L3: CONTAGEM | M3: MG | N3: 1556 | O3: GABRIEL.ALBINO | Q3: =SUM(R3:AD3)-I3 -> 0 | S3: =SUMIFS('Doc''s Pagos | Rodopar 108'!$J:$J,'Doc''s Pagos | Rodopar 108'!$A:$A,$B3&$E3&$F3&$J3,'Doc''s Pagos | Rodopar 108'!$B:$B,S$1)+SUMIFS('Doc Há Pagar | Rodopar 1015'!$J:$J,'Doc Há Pagar | Rodopar 1015'!$A:$A,$B3&$E3&$F3,'Doc Há Pagar | Rodopar 1015'!$B:$B,S$1) -> 898 | T3: =SUMIFS('Doc''s Pagos | Rodopar 108'!$J:$J,'Doc''s Pagos | Rodopar 108'!$A:$A,$B3&$E3&$F3&$J3,'Doc''s Pagos | Rodopar 108'!$B:$B,T$1)+SUMIFS('Doc Há Pagar | Rodopar 1015'!$J:$J,'Doc Há Pagar | Rodopar 1015'!$A:$A,$B3&$E3&$F3,'Doc Há Pagar | Rodopar 1015'!$B:$B,T$1) -> 0 | U3: =SUMIFS('Doc''s Pagos | Rodopar 108'!$J:$J,'Doc''s Pagos | Rodopar 108'!$A:$A,$B3&$E3&$F3&$J3,'Doc''s Pagos | Rodopar 108'!$B:$B,U$1)+SUMIFS('Doc Há Pagar | Rodopar 1015'!$J:$J,'Doc Há Pagar | Rodopar 1015'!$A:$A,$B3&$E3&$F3,'Doc Há Pagar | Rodopar 1015'!$B:$B,U$1) -> 0 | V3: =SUMIFS('Doc''s Pagos | Rodopar 108'!$J:$J,'Doc''s Pagos | Rodopar 108'!$A:$A,$B3&$E3&$F3&$J3,'Doc''s Pagos | Rodopar 108'!$B:$B,V$1)+SUMIFS('Doc Há Pagar | Rodopar 1015'!$J:$J,'Doc Há Pagar | Rodopar 1015'!$A:$A,$B3&$E3&$F3,'Doc Há Pagar | Rodopar 1015'!$B:$B,V$1) -> 0 | W3: =SUMIFS('Doc''s Pagos | Rodopar 108'!$J:$J,'Doc''s Pagos | Rodopar 108'!$A:$A,$B3&$E3&$F3&$J3,'Doc''s Pagos | Rodopar 108'!$B:$B,W$1)+SUMIFS('Doc Há Pagar | Rodopar 1015'!$J:$J,'Doc Há Pagar | Rodopar 1015'!$A:$A,$B3&$E3&$F3,'Doc Há Pagar | Rodopar 1015'!$B:$B,W$1) -> 0 | X3: =SUMIFS('Doc''s Pagos | Rodopar 108'!$J:$J,'Doc''s Pagos | Rodopar 108'!$A:$A,$B3&$E3&$F3&$J3,'Doc''s Pagos | Rodopar 108'!$B:$B,X$1)+SUMIFS('Doc Há Pagar | Rodopar 1015'!$J:$J,'Doc Há Pagar | Rodopar 1015'!$A:$A,$B3&$E3&$F3,'Doc Há Pagar | Rodopar 1015'!$B:$B,X$1) -> 0 | Y3: =SUMIFS('Doc''s Pagos | Rodopar 108'!$J:$J,'Doc''s Pagos | Rodopar 108'!$A:$A,$B3&$E3&$F3&$J3,'Doc''s Pagos | Rodopar 108'!$B:$B,Y$1)+SUMIFS('Doc Há Pagar | Rodopar 1015'!$J:$J,'Doc Há Pagar | Rodopar 1015'!$A:$A,$B3&$E3&$F3,'Doc Há Pagar | Rodopar 1015'!$B:$B,Y$1) -> 0 | Z3: =SUMIFS('Doc''s Pagos | Rodopar 108'!$J:$J,'Doc''s Pagos | Rodopar 108'!$A:$A,$B3&$E3&$F3&$J3,'Doc''s Pagos | Rodopar 108'!$B:$B,Z$1)+SUMIFS('Doc Há Pagar | Rodopar 1015'!$J:$J,'Doc Há Pagar | Rodopar 1015'!$A:$A,$B3&$E3&$F3,'Doc Há Pagar | Rodopar 1015'!$B:$B,Z$1) -> 0 | ... AD3: =SUMIFS('Doc''s Pagos | Rodopar 108'!$J:$J,'Doc''s Pagos | Rodopar 108'!$A:$A,$B3&$E3&$F3&$J3,'Doc''s Pagos | Rodopar 108'!$B:$B,AD$1)+SUMIFS('Doc Há Pagar | Rodopar 1015'!$J:$J,'Doc Há Pagar | Rodopar 1015'!$A:$A,$B3&$E3&$F3,'Doc Há Pagar | Rodopar 1015'!$B:$B,AD$1) -> 0
A4: =VLOOKUP($E4,Fornecedores!$A:$C,3,0) -> Frota | B4: 2632 | C4: =IFERROR(VLOOKUP($E4,Fornecedores!$A:$E,4,0),"") -> Manutenção | D4: =IFERROR(VLOOKUP($E4,Fornecedores!$A:$E,5,0),"") -> Frota Leve OPE | E4: MECANICA CRISTO REI LTDA | F4: NFE | G4: 71.299.614/0001-64 | H4: 87 | I4: 1338 | J4: 46013 | K4: 46028 | L4: CONTAGEM | M4: MG | N4: 1556 | O4: GABRIEL.ALBINO | Q4: =SUM(R4:AD4)-I4 -> 0 | S4: =SUMIFS('Doc''s Pagos | Rodopar 108'!$J:$J,'Doc''s Pagos | Rodopar 108'!$A:$A,$B4&$E4&$F4&$J4,'Doc''s Pagos | Rodopar 108'!$B:$B,S$1)+SUMIFS('Doc Há Pagar | Rodopar 1015'!$J:$J,'Doc Há Pagar | Rodopar 1015'!$A:$A,$B4&$E4&$F4,'Doc Há Pagar | Rodopar 1015'!$B:$B,S$1) -> 1338 | T4: =SUMIFS('Doc''s Pagos | Rodopar 108'!$J:$J,'Doc''s Pagos | Rodopar 108'!$A:$A,$B4&$E4&$F4&$J4,'Doc''s Pagos | Rodopar 108'!$B:$B,T$1)+SUMIFS('Doc Há Pagar | Rodopar 1015'!$J:$J,'Doc Há Pagar | Rodopar 1015'!$A:$A,$B4&$E4&$F4,'Doc Há Pagar | Rodopar 1015'!$B:$B,T$1) -> 0 | U4: =SUMIFS('Doc''s Pagos | Rodopar 108'!$J:$J,'Doc''s Pagos | Rodopar 108'!$A:$A,$B4&$E4&$F4&$J4,'Doc''s Pagos | Rodopar 108'!$B:$B,U$1)+SUMIFS('Doc Há Pagar | Rodopar 1015'!$J:$J,'Doc Há Pagar | Rodopar 1015'!$A:$A,$B4&$E4&$F4,'Doc Há Pagar | Rodopar 1015'!$B:$B,U$1) -> 0 | V4: =SUMIFS('Doc''s Pagos | Rodopar 108'!$J:$J,'Doc''s Pagos | Rodopar 108'!$A:$A,$B4&$E4&$F4&$J4,'Doc''s Pagos | Rodopar 108'!$B:$B,V$1)+SUMIFS('Doc Há Pagar | Rodopar 1015'!$J:$J,'Doc Há Pagar | Rodopar 1015'!$A:$A,$B4&$E4&$F4,'Doc Há Pagar | Rodopar 1015'!$B:$B,V$1) -> 0 | W4: =SUMIFS('Doc''s Pagos | Rodopar 108'!$J:$J,'Doc''s Pagos | Rodopar 108'!$A:$A,$B4&$E4&$F4&$J4,'Doc''s Pagos | Rodopar 108'!$B:$B,W$1)+SUMIFS('Doc Há Pagar | Rodopar 1015'!$J:$J,'Doc Há Pagar | Rodopar 1015'!$A:$A,$B4&$E4&$F4,'Doc Há Pagar | Rodopar 1015'!$B:$B,W$1) -> 0 | X4: =SUMIFS('Doc''s Pagos | Rodopar 108'!$J:$J,'Doc''s Pagos | Rodopar 108'!$A:$A,$B4&$E4&$F4&$J4,'Doc''s Pagos | Rodopar 108'!$B:$B,X$1)+SUMIFS('Doc Há Pagar | Rodopar 1015'!$J:$J,'Doc Há Pagar | Rodopar 1015'!$A:$A,$B4&$E4&$F4,'Doc Há Pagar | Rodopar 1015'!$B:$B,X$1) -> 0 | Y4: =SUMIFS('Doc''s Pagos | Rodopar 108'!$J:$J,'Doc''s Pagos | Rodopar 108'!$A:$A,$B4&$E4&$F4&$J4,'Doc''s Pagos | Rodopar 108'!$B:$B,Y$1)+SUMIFS('Doc Há Pagar | Rodopar 1015'!$J:$J,'Doc Há Pagar | Rodopar 1015'!$A:$A,$B4&$E4&$F4,'Doc Há Pagar | Rodopar 1015'!$B:$B,Y$1) -> 0 | Z4: =SUMIFS('Doc''s Pagos | Rodopar 108'!$J:$J,'Doc''s Pagos | Rodopar 108'!$A:$A,$B4&$E4&$F4&$J4,'Doc''s Pagos | Rodopar 108'!$B:$B,Z$1)+SUMIFS('Doc Há Pagar | Rodopar 1015'!$J:$J,'Doc Há Pagar | Rodopar 1015'!$A:$A,$B4&$E4&$F4,'Doc Há Pagar | Rodopar 1015'!$B:$B,Z$1) -> 0 | ... AD4: =SUMIFS('Doc''s Pagos | Rodopar 108'!$J:$J,'Doc''s Pagos | Rodopar 108'!$A:$A,$B4&$E4&$F4&$J4,'Doc''s Pagos | Rodopar 108'!$B:$B,AD$1)+SUMIFS('Doc Há Pagar | Rodopar 1015'!$J:$J,'Doc Há Pagar | Rodopar 1015'!$A:$A,$B4&$E4&$F4,'Doc Há Pagar | Rodopar 1015'!$B:$B,AD$1) -> 0
A5: =VLOOKUP($E5,Fornecedores!$A:$C,3,0) -> Frota | B5: 3780 | C5: =IFERROR(VLOOKUP($E5,Fornecedores!$A:$E,4,0),"") -> Manutenção | D5: =IFERROR(VLOOKUP($E5,Fornecedores!$A:$E,5,0),"") -> Frota Leve OPE | E5: MECANICA CRISTO REI LTDA | F5: NSE | G5: 71.299.614/0001-64 | H5: 87 | I5: 490 | J5: 46013 | K5: 46027 | L5: CONTAGEM | M5: MG | N5: 1556 | O5: GABRIEL.ALBINO | Q5: =SUM(R5:AD5)-I5 -> 0 | S5: =SUMIFS('Doc''s Pagos | Rodopar 108'!$J:$J,'Doc''s Pagos | Rodopar 108'!$A:$A,$B5&$E5&$F5&$J5,'Doc''s Pagos | Rodopar 108'!$B:$B,S$1)+SUMIFS('Doc Há Pagar | Rodopar 1015'!$J:$J,'Doc Há Pagar | Rodopar 1015'!$A:$A,$B5&$E5&$F5,'Doc Há Pagar | Rodopar 1015'!$B:$B,S$1) -> 490 | T5: =SUMIFS('Doc''s Pagos | Rodopar 108'!$J:$J,'Doc''s Pagos | Rodopar 108'!$A:$A,$B5&$E5&$F5&$J5,'Doc''s Pagos | Rodopar 108'!$B:$B,T$1)+SUMIFS('Doc Há Pagar | Rodopar 1015'!$J:$J,'Doc Há Pagar | Rodopar 1015'!$A:$A,$B5&$E5&$F5,'Doc Há Pagar | Rodopar 1015'!$B:$B,T$1) -> 0 | U5: =SUMIFS('Doc''s Pagos | Rodopar 108'!$J:$J,'Doc''s Pagos | Rodopar 108'!$A:$A,$B5&$E5&$F5&$J5,'Doc''s Pagos | Rodopar 108'!$B:$B,U$1)+SUMIFS('Doc Há Pagar | Rodopar 1015'!$J:$J,'Doc Há Pagar | Rodopar 1015'!$A:$A,$B5&$E5&$F5,'Doc Há Pagar | Rodopar 1015'!$B:$B,U$1) -> 0 | V5: =SUMIFS('Doc''s Pagos | Rodopar 108'!$J:$J,'Doc''s Pagos | Rodopar 108'!$A:$A,$B5&$E5&$F5&$J5,'Doc''s Pagos | Rodopar 108'!$B:$B,V$1)+SUMIFS('Doc Há Pagar | Rodopar 1015'!$J:$J,'Doc Há Pagar | Rodopar 1015'!$A:$A,$B5&$E5&$F5,'Doc Há Pagar | Rodopar 1015'!$B:$B,V$1) -> 0 | W5: =SUMIFS('Doc''s Pagos | Rodopar 108'!$J:$J,'Doc''s Pagos | Rodopar 108'!$A:$A,$B5&$E5&$F5&$J5,'Doc''s Pagos | Rodopar 108'!$B:$B,W$1)+SUMIFS('Doc Há Pagar | Rodopar 1015'!$J:$J,'Doc Há Pagar | Rodopar 1015'!$A:$A,$B5&$E5&$F5,'Doc Há Pagar | Rodopar 1015'!$B:$B,W$1) -> 0 | X5: =SUMIFS('Doc''s Pagos | Rodopar 108'!$J:$J,'Doc''s Pagos | Rodopar 108'!$A:$A,$B5&$E5&$F5&$J5,'Doc''s Pagos | Rodopar 108'!$B:$B,X$1)+SUMIFS('Doc Há Pagar | Rodopar 1015'!$J:$J,'Doc Há Pagar | Rodopar 1015'!$A:$A,$B5&$E5&$F5,'Doc Há Pagar | Rodopar 1015'!$B:$B,X$1) -> 0 | Y5: =SUMIFS('Doc''s Pagos | Rodopar 108'!$J:$J,'Doc''s Pagos | Rodopar 108'!$A:$A,$B5&$E5&$F5&$J5,'Doc''s Pagos | Rodopar 108'!$B:$B,Y$1)+SUMIFS('Doc Há Pagar | Rodopar 1015'!$J:$J,'Doc Há Pagar | Rodopar 1015'!$A:$A,$B5&$E5&$F5,'Doc Há Pagar | Rodopar 1015'!$B:$B,Y$1) -> 0 | Z5: =SUMIFS('Doc''s Pagos | Rodopar 108'!$J:$J,'Doc''s Pagos | Rodopar 108'!$A:$A,$B5&$E5&$F5&$J5,'Doc''s Pagos | Rodopar 108'!$B:$B,Z$1)+SUMIFS('Doc Há Pagar | Rodopar 1015'!$J:$J,'Doc Há Pagar | Rodopar 1015'!$A:$A,$B5&$E5&$F5,'Doc Há Pagar | Rodopar 1015'!$B:$B,Z$1) -> 0 | ... AD5: =SUMIFS('Doc''s Pagos | Rodopar 108'!$J:$J,'Doc''s Pagos | Rodopar 108'!$A:$A,$B5&$E5&$F5&$J5,'Doc''s Pagos | Rodopar 108'!$B:$B,AD$1)+SUMIFS('Doc Há Pagar | Rodopar 1015'!$J:$J,'Doc Há Pagar | Rodopar 1015'!$A:$A,$B5&$E5&$F5,'Doc Há Pagar | Rodopar 1015'!$B:$B,AD$1) -> 0
A6: =VLOOKUP($E6,Fornecedores!$A:$C,3,0) -> Frota | B6: 3781 | C6: =IFERROR(VLOOKUP($E6,Fornecedores!$A:$E,4,0),"") -> Manutenção | D6: =IFERROR(VLOOKUP($E6,Fornecedores!$A:$E,5,0),"") -> Frota Leve OPE | E6: MECANICA CRISTO REI LTDA | F6: NSE | G6: 71.299.614/0001-64 | H6: 87 | I6: 430 | J6: 46013 | K6: 46027 | L6: CONTAGEM | M6: MG | N6: 1556 | O6: GABRIEL.ALBINO | Q6: =SUM(R6:AD6)-I6 -> 0 | S6: =SUMIFS('Doc''s Pagos | Rodopar 108'!$J:$J,'Doc''s Pagos | Rodopar 108'!$A:$A,$B6&$E6&$F6&$J6,'Doc''s Pagos | Rodopar 108'!$B:$B,S$1)+SUMIFS('Doc Há Pagar | Rodopar 1015'!$J:$J,'Doc Há Pagar | Rodopar 1015'!$A:$A,$B6&$E6&$F6,'Doc Há Pagar | Rodopar 1015'!$B:$B,S$1) -> 430 | T6: =SUMIFS('Doc''s Pagos | Rodopar 108'!$J:$J,'Doc''s Pagos | Rodopar 108'!$A:$A,$B6&$E6&$F6&$J6,'Doc''s Pagos | Rodopar 108'!$B:$B,T$1)+SUMIFS('Doc Há Pagar | Rodopar 1015'!$J:$J,'Doc Há Pagar | Rodopar 1015'!$A:$A,$B6&$E6&$F6,'Doc Há Pagar | Rodopar 1015'!$B:$B,T$1) -> 0 | U6: =SUMIFS('Doc''s Pagos | Rodopar 108'!$J:$J,'Doc''s Pagos | Rodopar 108'!$A:$A,$B6&$E6&$F6&$J6,'Doc''s Pagos | Rodopar 108'!$B:$B,U$1)+SUMIFS('Doc Há Pagar | Rodopar 1015'!$J:$J,'Doc Há Pagar | Rodopar 1015'!$A:$A,$B6&$E6&$F6,'Doc Há Pagar | Rodopar 1015'!$B:$B,U$1) -> 0 | V6: =SUMIFS('Doc''s Pagos | Rodopar 108'!$J:$J,'Doc''s Pagos | Rodopar 108'!$A:$A,$B6&$E6&$F6&$J6,'Doc''s Pagos | Rodopar 108'!$B:$B,V$1)+SUMIFS('Doc Há Pagar | Rodopar 1015'!$J:$J,'Doc Há Pagar | Rodopar 1015'!$A:$A,$B6&$E6&$F6,'Doc Há Pagar | Rodopar 1015'!$B:$B,V$1) -> 0 | W6: =SUMIFS('Doc''s Pagos | Rodopar 108'!$J:$J,'Doc''s Pagos | Rodopar 108'!$A:$A,$B6&$E6&$F6&$J6,'Doc''s Pagos | Rodopar 108'!$B:$B,W$1)+SUMIFS('Doc Há Pagar | Rodopar 1015'!$J:$J,'Doc Há Pagar | Rodopar 1015'!$A:$A,$B6&$E6&$F6,'Doc Há Pagar | Rodopar 1015'!$B:$B,W$1) -> 0 | X6: =SUMIFS('Doc''s Pagos | Rodopar 108'!$J:$J,'Doc''s Pagos | Rodopar 108'!$A:$A,$B6&$E6&$F6&$J6,'Doc''s Pagos | Rodopar 108'!$B:$B,X$1)+SUMIFS('Doc Há Pagar | Rodopar 1015'!$J:$J,'Doc Há Pagar | Rodopar 1015'!$A:$A,$B6&$E6&$F6,'Doc Há Pagar | Rodopar 1015'!$B:$B,X$1) -> 0 | Y6: =SUMIFS('Doc''s Pagos | Rodopar 108'!$J:$J,'Doc''s Pagos | Rodopar 108'!$A:$A,$B6&$E6&$F6&$J6,'Doc''s Pagos | Rodopar 108'!$B:$B,Y$1)+SUMIFS('Doc Há Pagar | Rodopar 1015'!$J:$J,'Doc Há Pagar | Rodopar 1015'!$A:$A,$B6&$E6&$F6,'Doc Há Pagar | Rodopar 1015'!$B:$B,Y$1) -> 0 | Z6: =SUMIFS('Doc''s Pagos | Rodopar 108'!$J:$J,'Doc''s Pagos | Rodopar 108'!$A:$A,$B6&$E6&$F6&$J6,'Doc''s Pagos | Rodopar 108'!$B:$B,Z$1)+SUMIFS('Doc Há Pagar | Rodopar 1015'!$J:$J,'Doc Há Pagar | Rodopar 1015'!$A:$A,$B6&$E6&$F6,'Doc Há Pagar | Rodopar 1015'!$B:$B,Z$1) -> 0 | ... AD6: =SUMIFS('Doc''s Pagos | Rodopar 108'!$J:$J,'Doc''s Pagos | Rodopar 108'!$A:$A,$B6&$E6&$F6&$J6,'Doc''s Pagos | Rodopar 108'!$B:$B,AD$1)+SUMIFS('Doc Há Pagar | Rodopar 1015'!$J:$J,'Doc Há Pagar | Rodopar 1015'!$A:$A,$B6&$E6&$F6,'Doc Há Pagar | Rodopar 1015'!$B:$B,AD$1) -> 0
A7: =VLOOKUP($E7,Fornecedores!$A:$C,3,0) -> Frota | B7: 145 | C7: =IFERROR(VLOOKUP($E7,Fornecedores!$A:$E,4,0),"") -> Sinistro | D7: =IFERROR(VLOOKUP($E7,Fornecedores!$A:$E,5,0),"") -> Lanternagem | E7: CAMPOS VEICULOS LTDA - PRIME AUTO CENTER | F7: NSE | G7: 43.792.799/0001-09 | H7: 87 | I7: 1000 | J7: 46017 | K7: 46027 | L7: CONTAGEM | M7: MG | N7: 1556 | O7: GABRIEL.ALBINO | Q7: =SUM(R7:AD7)-I7 -> 0 | S7: =SUMIFS('Doc''s Pagos | Rodopar 108'!$J:$J,'Doc''s Pagos | Rodopar 108'!$A:$A,$B7&$E7&$F7&$J7,'Doc''s Pagos | Rodopar 108'!$B:$B,S$1)+SUMIFS('Doc Há Pagar | Rodopar 1015'!$J:$J,'Doc Há Pagar | Rodopar 1015'!$A:$A,$B7&$E7&$F7,'Doc Há Pagar | Rodopar 1015'!$B:$B,S$1) -> 1000 | T7: =SUMIFS('Doc''s Pagos | Rodopar 108'!$J:$J,'Doc''s Pagos | Rodopar 108'!$A:$A,$B7&$E7&$F7&$J7,'Doc''s Pagos | Rodopar 108'!$B:$B,T$1)+SUMIFS('Doc Há Pagar | Rodopar 1015'!$J:$J,'Doc Há Pagar | Rodopar 1015'!$A:$A,$B7&$E7&$F7,'Doc Há Pagar | Rodopar 1015'!$B:$B,T$1) -> 0 | U7: =SUMIFS('Doc''s Pagos | Rodopar 108'!$J:$J,'Doc''s Pagos | Rodopar 108'!$A:$A,$B7&$E7&$F7&$J7,'Doc''s Pagos | Rodopar 108'!$B:$B,U$1)+SUMIFS('Doc Há Pagar | Rodopar 1015'!$J:$J,'Doc Há Pagar | Rodopar 1015'!$A:$A,$B7&$E7&$F7,'Doc Há Pagar | Rodopar 1015'!$B:$B,U$1) -> 0 | V7: =SUMIFS('Doc''s Pagos | Rodopar 108'!$J:$J,'Doc''s Pagos | Rodopar 108'!$A:$A,$B7&$E7&$F7&$J7,'Doc''s Pagos | Rodopar 108'!$B:$B,V$1)+SUMIFS('Doc Há Pagar | Rodopar 1015'!$J:$J,'Doc Há Pagar | Rodopar 1015'!$A:$A,$B7&$E7&$F7,'Doc Há Pagar | Rodopar 1015'!$B:$B,V$1) -> 0 | W7: =SUMIFS('Doc''s Pagos | Rodopar 108'!$J:$J,'Doc''s Pagos | Rodopar 108'!$A:$A,$B7&$E7&$F7&$J7,'Doc''s Pagos | Rodopar 108'!$B:$B,W$1)+SUMIFS('Doc Há Pagar | Rodopar 1015'!$J:$J,'Doc Há Pagar | Rodopar 1015'!$A:$A,$B7&$E7&$F7,'Doc Há Pagar | Rodopar 1015'!$B:$B,W$1) -> 0 | X7: =SUMIFS('Doc''s Pagos | Rodopar 108'!$J:$J,'Doc''s Pagos | Rodopar 108'!$A:$A,$B7&$E7&$F7&$J7,'Doc''s Pagos | Rodopar 108'!$B:$B,X$1)+SUMIFS('Doc Há Pagar | Rodopar 1015'!$J:$J,'Doc Há Pagar | Rodopar 1015'!$A:$A,$B7&$E7&$F7,'Doc Há Pagar | Rodopar 1015'!$B:$B,X$1) -> 0 | Y7: =SUMIFS('Doc''s Pagos | Rodopar 108'!$J:$J,'Doc''s Pagos | Rodopar 108'!$A:$A,$B7&$E7&$F7&$J7,'Doc''s Pagos | Rodopar 108'!$B:$B,Y$1)+SUMIFS('Doc Há Pagar | Rodopar 1015'!$J:$J,'Doc Há Pagar | Rodopar 1015'!$A:$A,$B7&$E7&$F7,'Doc Há Pagar | Rodopar 1015'!$B:$B,Y$1) -> 0 | Z7: =SUMIFS('Doc''s Pagos | Rodopar 108'!$J:$J,'Doc''s Pagos | Rodopar 108'!$A:$A,$B7&$E7&$F7&$J7,'Doc''s Pagos | Rodopar 108'!$B:$B,Z$1)+SUMIFS('Doc Há Pagar | Rodopar 1015'!$J:$J,'Doc Há Pagar | Rodopar 1015'!$A:$A,$B7&$E7&$F7,'Doc Há Pagar | Rodopar 1015'!$B:$B,Z$1) -> 0 | ... AD7: =SUMIFS('Doc''s Pagos | Rodopar 108'!$J:$J,'Doc''s Pagos | Rodopar 108'!$A:$A,$B7&$E7&$F7&$J7,'Doc''s Pagos | Rodopar 108'!$B:$B,AD$1)+SUMIFS('Doc Há Pagar | Rodopar 1015'!$J:$J,'Doc Há Pagar | Rodopar 1015'!$A:$A,$B7&$E7&$F7,'Doc Há Pagar | Rodopar 1015'!$B:$B,AD$1) -> 0
A8: =VLOOKUP($E8,Fornecedores!$A:$C,3,0) -> Frota | B8: 2611814548 | C8: =IFERROR(VLOOKUP($E8,Fornecedores!$A:$E,4,0),"") -> Pedagios | D8: =IFERROR(VLOOKUP($E8,Fornecedores!$A:$E,5,0),"") -> Pedagios | E8: CENTRO DE GESTÃO DE MEIOS DE PAGTOS. S/A | F8: FT | G8: 04.088.208/0001-65 | H8: 87 | I8: 23342.83 | J8: 46025 | K8: 46029 | L8: OSASCO | M8: SP | N8: 2556 | O8: GABRIEL.ALBINO | Q8: =SUM(R8:AD8)-I8 -> 0 | S8: =SUMIFS('Doc''s Pagos | Rodopar 108'!$J:$J,'Doc''s Pagos | Rodopar 108'!$A:$A,$B8&$E8&$F8&$J8,'Doc''s Pagos | Rodopar 108'!$B:$B,S$1)+SUMIFS('Doc Há Pagar | Rodopar 1015'!$J:$J,'Doc Há Pagar | Rodopar 1015'!$A:$A,$B8&$E8&$F8,'Doc Há Pagar | Rodopar 1015'!$B:$B,S$1) -> 23342.83 | T8: =SUMIFS('Doc''s Pagos | Rodopar 108'!$J:$J,'Doc''s Pagos | Rodopar 108'!$A:$A,$B8&$E8&$F8&$J8,'Doc''s Pagos | Rodopar 108'!$B:$B,T$1)+SUMIFS('Doc Há Pagar | Rodopar 1015'!$J:$J,'Doc Há Pagar | Rodopar 1015'!$A:$A,$B8&$E8&$F8,'Doc Há Pagar | Rodopar 1015'!$B:$B,T$1) -> 0 | U8: =SUMIFS('Doc''s Pagos | Rodopar 108'!$J:$J,'Doc''s Pagos | Rodopar 108'!$A:$A,$B8&$E8&$F8&$J8,'Doc''s Pagos | Rodopar 108'!$B:$B,U$1)+SUMIFS('Doc Há Pagar | Rodopar 1015'!$J:$J,'Doc Há Pagar | Rodopar 1015'!$A:$A,$B8&$E8&$F8,'Doc Há Pagar | Rodopar 1015'!$B:$B,U$1) -> 0 | V8: =SUMIFS('Doc''s Pagos | Rodopar 108'!$J:$J,'Doc''s Pagos | Rodopar 108'!$A:$A,$B8&$E8&$F8&$J8,'Doc''s Pagos | Rodopar 108'!$B:$B,V$1)+SUMIFS('Doc Há Pagar | Rodopar 1015'!$J:$J,'Doc Há Pagar | Rodopar 1015'!$A:$A,$B8&$E8&$F8,'Doc Há Pagar | Rodopar 1015'!$B:$B,V$1) -> 0 | W8: =SUMIFS('Doc''s Pagos | Rodopar 108'!$J:$J,'Doc''s Pagos | Rodopar 108'!$A:$A,$B8&$E8&$F8&$J8,'Doc''s Pagos | Rodopar 108'!$B:$B,W$1)+SUMIFS('Doc Há Pagar | Rodopar 1015'!$J:$J,'Doc Há Pagar | Rodopar 1015'!$A:$A,$B8&$E8&$F8,'Doc Há Pagar | Rodopar 1015'!$B:$B,W$1) -> 0 | X8: =SUMIFS('Doc''s Pagos | Rodopar 108'!$J:$J,'Doc''s Pagos | Rodopar 108'!$A:$A,$B8&$E8&$F8&$J8,'Doc''s Pagos | Rodopar 108'!$B:$B,X$1)+SUMIFS('Doc Há Pagar | Rodopar 1015'!$J:$J,'Doc Há Pagar | Rodopar 1015'!$A:$A,$B8&$E8&$F8,'Doc Há Pagar | Rodopar 1015'!$B:$B,X$1) -> 0 | Y8: =SUMIFS('Doc''s Pagos | Rodopar 108'!$J:$J,'Doc''s Pagos | Rodopar 108'!$A:$A,$B8&$E8&$F8&$J8,'Doc''s Pagos | Rodopar 108'!$B:$B,Y$1)+SUMIFS('Doc Há Pagar | Rodopar 1015'!$J:$J,'Doc Há Pagar | Rodopar 1015'!$A:$A,$B8&$E8&$F8,'Doc Há Pagar | Rodopar 1015'!$B:$B,Y$1) -> 0 | Z8: =SUMIFS('Doc''s Pagos | Rodopar 108'!$J:$J,'Doc''s Pagos | Rodopar 108'!$A:$A,$B8&$E8&$F8&$J8,'Doc''s Pagos | Rodopar 108'!$B:$B,Z$1)+SUMIFS('Doc Há Pagar | Rodopar 1015'!$J:$J,'Doc Há Pagar | Rodopar 1015'!$A:$A,$B8&$E8&$F8,'Doc Há Pagar | Rodopar 1015'!$B:$B,Z$1) -> 0 | ... AD8: =SUMIFS('Doc''s Pagos | Rodopar 108'!$J:$J,'Doc''s Pagos | Rodopar 108'!$A:$A,$B8&$E8&$F8&$J8,'Doc''s Pagos | Rodopar 108'!$B:$B,AD$1)+SUMIFS('Doc Há Pagar | Rodopar 1015'!$J:$J,'Doc Há Pagar | Rodopar 1015'!$A:$A,$B8&$E8&$F8,'Doc Há Pagar | Rodopar 1015'!$B:$B,AD$1) -> 0
A9: =VLOOKUP($E9,Fornecedores!$A:$C,3,0) -> Frota | B9: 1420 | C9: =IFERROR(VLOOKUP($E9,Fornecedores!$A:$E,4,0),"") -> MTSR | D9: =IFERROR(VLOOKUP($E9,Fornecedores!$A:$E,5,0),"") -> Tecnologia | E9: AVANSAT TECNOLOGIAS E SERVS EM SEGURANCA LTDA | F9: FT | G9: 02.602.115/0001-81 | H9: 87 | I9: 59176.89 | J9: 46029 | K9: 46030 | L9: PORTO ALEGRE | M9: RS | N9: 2556 | O9: GABRIEL.ALBINO | Q9: =SUM(R9:AD9)-I9 -> 0 | S9: =SUMIFS('Doc''s Pagos | Rodopar 108'!$J:$J,'Doc''s Pagos | Rodopar 108'!$A:$A,$B9&$E9&$F9&$J9,'Doc''s Pagos | Rodopar 108'!$B:$B,S$1)+SUMIFS('Doc Há Pagar | Rodopar 1015'!$J:$J,'Doc Há Pagar | Rodopar 1015'!$A:$A,$B9&$E9&$F9,'Doc Há Pagar | Rodopar 1015'!$B:$B,S$1) -> 0 | T9: =SUMIFS('Doc''s Pagos | Rodopar 108'!$J:$J,'Doc''s Pagos | Rodopar 108'!$A:$A,$B9&$E9&$F9&$J9,'Doc''s Pagos | Rodopar 108'!$B:$B,T$1)+SUMIFS('Doc Há Pagar | Rodopar 1015'!$J:$J,'Doc Há Pagar | Rodopar 1015'!$A:$A,$B9&$E9&$F9,'Doc Há Pagar | Rodopar 1015'!$B:$B,T$1) -> 59176.89 | U9: =SUMIFS('Doc''s Pagos | Rodopar 108'!$J:$J,'Doc''s Pagos | Rodopar 108'!$A:$A,$B9&$E9&$F9&$J9,'Doc''s Pagos | Rodopar 108'!$B:$B,U$1)+SUMIFS('Doc Há Pagar | Rodopar 1015'!$J:$J,'Doc Há Pagar | Rodopar 1015'!$A:$A,$B9&$E9&$F9,'Doc Há Pagar | Rodopar 1015'!$B:$B,U$1) -> 0 | V9: =SUMIFS('Doc''s Pagos | Rodopar 108'!$J:$J,'Doc''s Pagos | Rodopar 108'!$A:$A,$B9&$E9&$F9&$J9,'Doc''s Pagos | Rodopar 108'!$B:$B,V$1)+SUMIFS('Doc Há Pagar | Rodopar 1015'!$J:$J,'Doc Há Pagar | Rodopar 1015'!$A:$A,$B9&$E9&$F9,'Doc Há Pagar | Rodopar 1015'!$B:$B,V$1) -> 0 | W9: =SUMIFS('Doc''s Pagos | Rodopar 108'!$J:$J,'Doc''s Pagos | Rodopar 108'!$A:$A,$B9&$E9&$F9&$J9,'Doc''s Pagos | Rodopar 108'!$B:$B,W$1)+SUMIFS('Doc Há Pagar | Rodopar 1015'!$J:$J,'Doc Há Pagar | Rodopar 1015'!$A:$A,$B9&$E9&$F9,'Doc Há Pagar | Rodopar 1015'!$B:$B,W$1) -> 0 | X9: =SUMIFS('Doc''s Pagos | Rodopar 108'!$J:$J,'Doc''s Pagos | Rodopar 108'!$A:$A,$B9&$E9&$F9&$J9,'Doc''s Pagos | Rodopar 108'!$B:$B,X$1)+SUMIFS('Doc Há Pagar | Rodopar 1015'!$J:$J,'Doc Há Pagar | Rodopar 1015'!$A:$A,$B9&$E9&$F9,'Doc Há Pagar | Rodopar 1015'!$B:$B,X$1) -> 0 | Y9: =SUMIFS('Doc''s Pagos | Rodopar 108'!$J:$J,'Doc''s Pagos | Rodopar 108'!$A:$A,$B9&$E9&$F9&$J9,'Doc''s Pagos | Rodopar 108'!$B:$B,Y$1)+SUMIFS('Doc Há Pagar | Rodopar 1015'!$J:$J,'Doc Há Pagar | Rodopar 1015'!$A:$A,$B9&$E9&$F9,'Doc Há Pagar | Rodopar 1015'!$B:$B,Y$1) -> 0 | Z9: =SUMIFS('Doc''s Pagos | Rodopar 108'!$J:$J,'Doc''s Pagos | Rodopar 108'!$A:$A,$B9&$E9&$F9&$J9,'Doc''s Pagos | Rodopar 108'!$B:$B,Z$1)+SUMIFS('Doc Há Pagar | Rodopar 1015'!$J:$J,'Doc Há Pagar | Rodopar 1015'!$A:$A,$B9&$E9&$F9,'Doc Há Pagar | Rodopar 1015'!$B:$B,Z$1) -> 0 | ... AD9: =SUMIFS('Doc''s Pagos | Rodopar 108'!$J:$J,'Doc''s Pagos | Rodopar 108'!$A:$A,$B9&$E9&$F9&$J9,'Doc''s Pagos | Rodopar 108'!$B:$B,AD$1)+SUMIFS('Doc Há Pagar | Rodopar 1015'!$J:$J,'Doc Há Pagar | Rodopar 1015'!$A:$A,$B9&$E9&$F9,'Doc Há Pagar | Rodopar 1015'!$B:$B,AD$1) -> 0
A10: =VLOOKUP($E10,Fornecedores!$A:$C,3,0) -> Frota | B10: 421 | C10: =IFERROR(VLOOKUP($E10,Fornecedores!$A:$E,4,0),"") -> MTSR | D10: =IFERROR(VLOOKUP($E10,Fornecedores!$A:$E,5,0),"") -> Tecnologia | E10: AVANSAT TECNOLOGIAS E SERVS EM SEGURANCA LTDA | F10: NSE | G10: 02.602.115/0001-81 | H10: 87 | I10: 11929.32 | J10: 46029 | K10: 46030 | L10: PORTO ALEGRE | M10: RS | N10: 2556 | O10: GABRIEL.ALBINO | Q10: =SUM(R10:AD10)-I10 -> 0 | S10: =SUMIFS('Doc''s Pagos | Rodopar 108'!$J:$J,'Doc''s Pagos | Rodopar 108'!$A:$A,$B10&$E10&$F10&$J10,'Doc''s Pagos | Rodopar 108'!$B:$B,S$1)+SUMIFS('Doc Há Pagar | Rodopar 1015'!$J:$J,'Doc Há Pagar | Rodopar 1015'!$A:$A,$B10&$E10&$F10,'Doc Há Pagar | Rodopar 1015'!$B:$B,S$1) -> 0 | T10: =SUMIFS('Doc''s Pagos | Rodopar 108'!$J:$J,'Doc''s Pagos | Rodopar 108'!$A:$A,$B10&$E10&$F10&$J10,'Doc''s Pagos | Rodopar 108'!$B:$B,T$1)+SUMIFS('Doc Há Pagar | Rodopar 1015'!$J:$J,'Doc Há Pagar | Rodopar 1015'!$A:$A,$B10&$E10&$F10,'Doc Há Pagar | Rodopar 1015'!$B:$B,T$1) -> 11929.32 | U10: =SUMIFS('Doc''s Pagos | Rodopar 108'!$J:$J,'Doc''s Pagos | Rodopar 108'!$A:$A,$B10&$E10&$F10&$J10,'Doc''s Pagos | Rodopar 108'!$B:$B,U$1)+SUMIFS('Doc Há Pagar | Rodopar 1015'!$J:$J,'Doc Há Pagar | Rodopar 1015'!$A:$A,$B10&$E10&$F10,'Doc Há Pagar | Rodopar 1015'!$B:$B,U$1) -> 0 | V10: =SUMIFS('Doc''s Pagos | Rodopar 108'!$J:$J,'Doc''s Pagos | Rodopar 108'!$A:$A,$B10&$E10&$F10&$J10,'Doc''s Pagos | Rodopar 108'!$B:$B,V$1)+SUMIFS('Doc Há Pagar | Rodopar 1015'!$J:$J,'Doc Há Pagar | Rodopar 1015'!$A:$A,$B10&$E10&$F10,'Doc Há Pagar | Rodopar 1015'!$B:$B,V$1) -> 0 | W10: =SUMIFS('Doc''s Pagos | Rodopar 108'!$J:$J,'Doc''s Pagos | Rodopar 108'!$A:$A,$B10&$E10&$F10&$J10,'Doc''s Pagos | Rodopar 108'!$B:$B,W$1)+SUMIFS('Doc Há Pagar | Rodopar 1015'!$J:$J,'Doc Há Pagar | Rodopar 1015'!$A:$A,$B10&$E10&$F10,'Doc Há Pagar | Rodopar 1015'!$B:$B,W$1) -> 0 | X10: =SUMIFS('Doc''s Pagos | Rodopar 108'!$J:$J,'Doc''s Pagos | Rodopar 108'!$A:$A,$B10&$E10&$F10&$J10,'Doc''s Pagos | Rodopar 108'!$B:$B,X$1)+SUMIFS('Doc Há Pagar | Rodopar 1015'!$J:$J,'Doc Há Pagar | Rodopar 1015'!$A:$A,$B10&$E10&$F10,'Doc Há Pagar | Rodopar 1015'!$B:$B,X$1) -> 0 | Y10: =SUMIFS('Doc''s Pagos | Rodopar 108'!$J:$J,'Doc''s Pagos | Rodopar 108'!$A:$A,$B10&$E10&$F10&$J10,'Doc''s Pagos | Rodopar 108'!$B:$B,Y$1)+SUMIFS('Doc Há Pagar | Rodopar 1015'!$J:$J,'Doc Há Pagar | Rodopar 1015'!$A:$A,$B10&$E10&$F10,'Doc Há Pagar | Rodopar 1015'!$B:$B,Y$1) -> 0 | Z10: =SUMIFS('Doc''s Pagos | Rodopar 108'!$J:$J,'Doc''s Pagos | Rodopar 108'!$A:$A,$B10&$E10&$F10&$J10,'Doc''s Pagos | Rodopar 108'!$B:$B,Z$1)+SUMIFS('Doc Há Pagar | Rodopar 1015'!$J:$J,'Doc Há Pagar | Rodopar 1015'!$A:$A,$B10&$E10&$F10,'Doc Há Pagar | Rodopar 1015'!$B:$B,Z$1) -> 0 | ... AD10: =SUMIFS('Doc''s Pagos | Rodopar 108'!$J:$J,'Doc''s Pagos | Rodopar 108'!$A:$A,$B10&$E10&$F10&$J10,'Doc''s Pagos | Rodopar 108'!$B:$B,AD$1)+SUMIFS('Doc Há Pagar | Rodopar 1015'!$J:$J,'Doc Há Pagar | Rodopar 1015'!$A:$A,$B10&$E10&$F10,'Doc Há Pagar | Rodopar 1015'!$B:$B,AD$1) -> 0
A11: =VLOOKUP($E11,Fornecedores!$A:$C,3,0) -> Frota | B11: 422 | C11: =IFERROR(VLOOKUP($E11,Fornecedores!$A:$E,4,0),"") -> MTSR | D11: =IFERROR(VLOOKUP($E11,Fornecedores!$A:$E,5,0),"") -> Tecnologia | E11: AVANSAT TECNOLOGIAS E SERVS EM SEGURANCA LTDA | F11: NSE | G11: 02.602.115/0001-81 | H11: 87 | I11: 9126.74 | J11: 46029 | K11: 46030 | L11: PORTO ALEGRE | M11: RS | N11: 2556 | O11: GABRIEL.ALBINO | Q11: =SUM(R11:AD11)-I11 -> 0 | S11: =SUMIFS('Doc''s Pagos | Rodopar 108'!$J:$J,'Doc''s Pagos | Rodopar 108'!$A:$A,$B11&$E11&$F11&$J11,'Doc''s Pagos | Rodopar 108'!$B:$B,S$1)+SUMIFS('Doc Há Pagar | Rodopar 1015'!$J:$J,'Doc Há Pagar | Rodopar 1015'!$A:$A,$B11&$E11&$F11,'Doc Há Pagar | Rodopar 1015'!$B:$B,S$1) -> 0 | T11: =SUMIFS('Doc''s Pagos | Rodopar 108'!$J:$J,'Doc''s Pagos | Rodopar 108'!$A:$A,$B11&$E11&$F11&$J11,'Doc''s Pagos | Rodopar 108'!$B:$B,T$1)+SUMIFS('Doc Há Pagar | Rodopar 1015'!$J:$J,'Doc Há Pagar | Rodopar 1015'!$A:$A,$B11&$E11&$F11,'Doc Há Pagar | Rodopar 1015'!$B:$B,T$1) -> 9126.74 | U11: =SUMIFS('Doc''s Pagos | Rodopar 108'!$J:$J,'Doc''s Pagos | Rodopar 108'!$A:$A,$B11&$E11&$F11&$J11,'Doc''s Pagos | Rodopar 108'!$B:$B,U$1)+SUMIFS('Doc Há Pagar | Rodopar 1015'!$J:$J,'Doc Há Pagar | Rodopar 1015'!$A:$A,$B11&$E11&$F11,'Doc Há Pagar | Rodopar 1015'!$B:$B,U$1) -> 0 | V11: =SUMIFS('Doc''s Pagos | Rodopar 108'!$J:$J,'Doc''s Pagos | Rodopar 108'!$A:$A,$B11&$E11&$F11&$J11,'Doc''s Pagos | Rodopar 108'!$B:$B,V$1)+SUMIFS('Doc Há Pagar | Rodopar 1015'!$J:$J,'Doc Há Pagar | Rodopar 1015'!$A:$A,$B11&$E11&$F11,'Doc Há Pagar | Rodopar 1015'!$B:$B,V$1) -> 0 | W11: =SUMIFS('Doc''s Pagos | Rodopar 108'!$J:$J,'Doc''s Pagos | Rodopar 108'!$A:$A,$B11&$E11&$F11&$J11,'Doc''s Pagos | Rodopar 108'!$B:$B,W$1)+SUMIFS('Doc Há Pagar | Rodopar 1015'!$J:$J,'Doc Há Pagar | Rodopar 1015'!$A:$A,$B11&$E11&$F11,'Doc Há Pagar | Rodopar 1015'!$B:$B,W$1) -> 0 | X11: =SUMIFS('Doc''s Pagos | Rodopar 108'!$J:$J,'Doc''s Pagos | Rodopar 108'!$A:$A,$B11&$E11&$F11&$J11,'Doc''s Pagos | Rodopar 108'!$B:$B,X$1)+SUMIFS('Doc Há Pagar | Rodopar 1015'!$J:$J,'Doc Há Pagar | Rodopar 1015'!$A:$A,$B11&$E11&$F11,'Doc Há Pagar | Rodopar 1015'!$B:$B,X$1) -> 0 | Y11: =SUMIFS('Doc''s Pagos | Rodopar 108'!$J:$J,'Doc''s Pagos | Rodopar 108'!$A:$A,$B11&$E11&$F11&$J11,'Doc''s Pagos | Rodopar 108'!$B:$B,Y$1)+SUMIFS('Doc Há Pagar | Rodopar 1015'!$J:$J,'Doc Há Pagar | Rodopar 1015'!$A:$A,$B11&$E11&$F11,'Doc Há Pagar | Rodopar 1015'!$B:$B,Y$1) -> 0 | Z11: =SUMIFS('Doc''s Pagos | Rodopar 108'!$J:$J,'Doc''s Pagos | Rodopar 108'!$A:$A,$B11&$E11&$F11&$J11,'Doc''s Pagos | Rodopar 108'!$B:$B,Z$1)+SUMIFS('Doc Há Pagar | Rodopar 1015'!$J:$J,'Doc Há Pagar | Rodopar 1015'!$A:$A,$B11&$E11&$F11,'Doc Há Pagar | Rodopar 1015'!$B:$B,Z$1) -> 0 | ... AD11: =SUMIFS('Doc''s Pagos | Rodopar 108'!$J:$J,'Doc''s Pagos | Rodopar 108'!$A:$A,$B11&$E11&$F11&$J11,'Doc''s Pagos | Rodopar 108'!$B:$B,AD$1)+SUMIFS('Doc Há Pagar | Rodopar 1015'!$J:$J,'Doc Há Pagar | Rodopar 1015'!$A:$A,$B11&$E11&$F11,'Doc Há Pagar | Rodopar 1015'!$B:$B,AD$1) -> 0
A12: =VLOOKUP($E12,Fornecedores!$A:$C,3,0) -> Frota | B12: 746021 | C12: =IFERROR(VLOOKUP($E12,Fornecedores!$A:$E,4,0),"") -> Telemetria | D12: =IFERROR(VLOOKUP($E12,Fornecedores!$A:$E,5,0),"") -> Telemetria | E12: SASCAR TECNOLOGIA E SEGURANÇA AUTOMOTICA S/A | F12: NSE | G12: 03.112.879/0001-51 | H12: 87 | I12: 357.45 | J12: 46030 | K12: 46031 | L12: SANTANA DE PARNAIBA | M12: SP | N12: 2556 | O12: GABRIEL.ALBINO | Q12: =SUM(R12:AD12)-I12 -> 0 | S12: =SUMIFS('Doc''s Pagos | Rodopar 108'!$J:$J,'Doc''s Pagos | Rodopar 108'!$A:$A,$B12&$E12&$F12&$J12,'Doc''s Pagos | Rodopar 108'!$B:$B,S$1)+SUMIFS('Doc Há Pagar | Rodopar 1015'!$J:$J,'Doc Há Pagar | Rodopar 1015'!$A:$A,$B12&$E12&$F12,'Doc Há Pagar | Rodopar 1015'!$B:$B,S$1) -> 0 | T12: =SUMIFS('Doc''s Pagos | Rodopar 108'!$J:$J,'Doc''s Pagos | Rodopar 108'!$A:$A,$B12&$E12&$F12&$J12,'Doc''s Pagos | Rodopar 108'!$B:$B,T$1)+SUMIFS('Doc Há Pagar | Rodopar 1015'!$J:$J,'Doc Há Pagar | Rodopar 1015'!$A:$A,$B12&$E12&$F12,'Doc Há Pagar | Rodopar 1015'!$B:$B,T$1) -> 357.45 | U12: =SUMIFS('Doc''s Pagos | Rodopar 108'!$J:$J,'Doc''s Pagos | Rodopar 108'!$A:$A,$B12&$E12&$F12&$J12,'Doc''s Pagos | Rodopar 108'!$B:$B,U$1)+SUMIFS('Doc Há Pagar | Rodopar 1015'!$J:$J,'Doc Há Pagar | Rodopar 1015'!$A:$A,$B12&$E12&$F12,'Doc Há Pagar | Rodopar 1015'!$B:$B,U$1) -> 0 | V12: =SUMIFS('Doc''s Pagos | Rodopar 108'!$J:$J,'Doc''s Pagos | Rodopar 108'!$A:$A,$B12&$E12&$F12&$J12,'Doc''s Pagos | Rodopar 108'!$B:$B,V$1)+SUMIFS('Doc Há Pagar | Rodopar 1015'!$J:$J,'Doc Há Pagar | Rodopar 1015'!$A:$A,$B12&$E12&$F12,'Doc Há Pagar | Rodopar 1015'!$B:$B,V$1) -> 0 | W12: =SUMIFS('Doc''s Pagos | Rodopar 108'!$J:$J,'Doc''s Pagos | Rodopar 108'!$A:$A,$B12&$E12&$F12&$J12,'Doc''s Pagos | Rodopar 108'!$B:$B,W$1)+SUMIFS('Doc Há Pagar | Rodopar 1015'!$J:$J,'Doc Há Pagar | Rodopar 1015'!$A:$A,$B12&$E12&$F12,'Doc Há Pagar | Rodopar 1015'!$B:$B,W$1) -> 0 | X12: =SUMIFS('Doc''s Pagos | Rodopar 108'!$J:$J,'Doc''s Pagos | Rodopar 108'!$A:$A,$B12&$E12&$F12&$J12,'Doc''s Pagos | Rodopar 108'!$B:$B,X$1)+SUMIFS('Doc Há Pagar | Rodopar 1015'!$J:$J,'Doc Há Pagar | Rodopar 1015'!$A:$A,$B12&$E12&$F12,'Doc Há Pagar | Rodopar 1015'!$B:$B,X$1) -> 0 | Y12: =SUMIFS('Doc''s Pagos | Rodopar 108'!$J:$J,'Doc''s Pagos | Rodopar 108'!$A:$A,$B12&$E12&$F12&$J12,'Doc''s Pagos | Rodopar 108'!$B:$B,Y$1)+SUMIFS('Doc Há Pagar | Rodopar 1015'!$J:$J,'Doc Há Pagar | Rodopar 1015'!$A:$A,$B12&$E12&$F12,'Doc Há Pagar | Rodopar 1015'!$B:$B,Y$1) -> 0 | Z12: =SUMIFS('Doc''s Pagos | Rodopar 108'!$J:$J,'Doc''s Pagos | Rodopar 108'!$A:$A,$B12&$E12&$F12&$J12,'Doc''s Pagos | Rodopar 108'!$B:$B,Z$1)+SUMIFS('Doc Há Pagar | Rodopar 1015'!$J:$J,'Doc Há Pagar | Rodopar 1015'!$A:$A,$B12&$E12&$F12,'Doc Há Pagar | Rodopar 1015'!$B:$B,Z$1) -> 0 | ... AD12: =SUMIFS('Doc''s Pagos | Rodopar 108'!$J:$J,'Doc''s Pagos | Rodopar 108'!$A:$A,$B12&$E12&$F12&$J12,'Doc''s Pagos | Rodopar 108'!$B:$B,AD$1)+SUMIFS('Doc Há Pagar | Rodopar 1015'!$J:$J,'Doc Há Pagar | Rodopar 1015'!$A:$A,$B12&$E12&$F12,'Doc Há Pagar | Rodopar 1015'!$B:$B,AD$1) -> 0
A13: =VLOOKUP($E13,Fornecedores!$A:$C,3,0) -> Frota | B13: AGMTZ-10840198 | C13: =IFERROR(VLOOKUP($E13,Fornecedores!$A:$E,4,0),"") -> OPE Merchandising | D13: =IFERROR(VLOOKUP($E13,Fornecedores!$A:$E,5,0),"") -> Locação | E13: LOCALIZA RENT A CAR SA | F13: FT | G13: 16.670.085/0001-55 | H13: 87 | I13: 588.97 | J13: 46031 | K13: 46035 | L13: BELO HORIZONTE | M13: MG | N13: 1556 | O13: GABRIEL.ALBINO | Q13: =SUM(R13:AD13)-I13 -> 0 | S13: =SUMIFS('Doc''s Pagos | Rodopar 108'!$J:$J,'Doc''s Pagos | Rodopar 108'!$A:$A,$B13&$E13&$F13&$J13,'Doc''s Pagos | Rodopar 108'!$B:$B,S$1)+SUMIFS('Doc Há Pagar | Rodopar 1015'!$J:$J,'Doc Há Pagar | Rodopar 1015'!$A:$A,$B13&$E13&$F13,'Doc Há Pagar | Rodopar 1015'!$B:$B,S$1) -> 588.97 | T13: =SUMIFS('Doc''s Pagos | Rodopar 108'!$J:$J,'Doc''s Pagos | Rodopar 108'!$A:$A,$B13&$E13&$F13&$J13,'Doc''s Pagos | Rodopar 108'!$B:$B,T$1)+SUMIFS('Doc Há Pagar | Rodopar 1015'!$J:$J,'Doc Há Pagar | Rodopar 1015'!$A:$A,$B13&$E13&$F13,'Doc Há Pagar | Rodopar 1015'!$B:$B,T$1) -> 0 | U13: =SUMIFS('Doc''s Pagos | Rodopar 108'!$J:$J,'Doc''s Pagos | Rodopar 108'!$A:$A,$B13&$E13&$F13&$J13,'Doc''s Pagos | Rodopar 108'!$B:$B,U$1)+SUMIFS('Doc Há Pagar | Rodopar 1015'!$J:$J,'Doc Há Pagar | Rodopar 1015'!$A:$A,$B13&$E13&$F13,'Doc Há Pagar | Rodopar 1015'!$B:$B,U$1) -> 0 | V13: =SUMIFS('Doc''s Pagos | Rodopar 108'!$J:$J,'Doc''s Pagos | Rodopar 108'!$A:$A,$B13&$E13&$F13&$J13,'Doc''s Pagos | Rodopar 108'!$B:$B,V$1)+SUMIFS('Doc Há Pagar | Rodopar 1015'!$J:$J,'Doc Há Pagar | Rodopar 1015'!$A:$A,$B13&$E13&$F13,'Doc Há Pagar | Rodopar 1015'!$B:$B,V$1) -> 0 | W13: =SUMIFS('Doc''s Pagos | Rodopar 108'!$J:$J,'Doc''s Pagos | Rodopar 108'!$A:$A,$B13&$E13&$F13&$J13,'Doc''s Pagos | Rodopar 108'!$B:$B,W$1)+SUMIFS('Doc Há Pagar | Rodopar 1015'!$J:$J,'Doc Há Pagar | Rodopar 1015'!$A:$A,$B13&$E13&$F13,'Doc Há Pagar | Rodopar 1015'!$B:$B,W$1) -> 0 | X13: =SUMIFS('Doc''s Pagos | Rodopar 108'!$J:$J,'Doc''s Pagos | Rodopar 108'!$A:$A,$B13&$E13&$F13&$J13,'Doc''s Pagos | Rodopar 108'!$B:$B,X$1)+SUMIFS('Doc Há Pagar | Rodopar 1015'!$J:$J,'Doc Há Pagar | Rodopar 1015'!$A:$A,$B13&$E13&$F13,'Doc Há Pagar | Rodopar 1015'!$B:$B,X$1) -> 0 | Y13: =SUMIFS('Doc''s Pagos | Rodopar 108'!$J:$J,'Doc''s Pagos | Rodopar 108'!$A:$A,$B13&$E13&$F13&$J13,'Doc''s Pagos | Rodopar 108'!$B:$B,Y$1)+SUMIFS('Doc Há Pagar | Rodopar 1015'!$J:$J,'Doc Há Pagar | Rodopar 1015'!$A:$A,$B13&$E13&$F13,'Doc Há Pagar | Rodopar 1015'!$B:$B,Y$1) -> 0 | Z13: =SUMIFS('Doc''s Pagos | Rodopar 108'!$J:$J,'Doc''s Pagos | Rodopar 108'!$A:$A,$B13&$E13&$F13&$J13,'Doc''s Pagos | Rodopar 108'!$B:$B,Z$1)+SUMIFS('Doc Há Pagar | Rodopar 1015'!$J:$J,'Doc Há Pagar | Rodopar 1015'!$A:$A,$B13&$E13&$F13,'Doc Há Pagar | Rodopar 1015'!$B:$B,Z$1) -> 0 | ... AD13: =SUMIFS('Doc''s Pagos | Rodopar 108'!$J:$J,'Doc''s Pagos | Rodopar 108'!$A:$A,$B13&$E13&$F13&$J13,'Doc''s Pagos | Rodopar 108'!$B:$B,AD$1)+SUMIFS('Doc Há Pagar | Rodopar 1015'!$J:$J,'Doc Há Pagar | Rodopar 1015'!$A:$A,$B13&$E13&$F13,'Doc Há Pagar | Rodopar 1015'!$B:$B,AD$1) -> 0
A14: =VLOOKUP($E14,Fornecedores!$A:$C,3,0) -> Frota | B14: 183264 | C14: =IFERROR(VLOOKUP($E14,Fornecedores!$A:$E,4,0),"") -> Manutenção | D14: =IFERROR(VLOOKUP($E14,Fornecedores!$A:$E,5,0),"") -> Vans | E14: MINAS MAQUINAS SA | JUIZ DE FORA | F14: NFE | G14: 21.549.423/0001-35 | H14: 87 | I14: 2526.91 | J14: 46031 | K14: 46035 | L14: JUIZ DE FORA | M14: MG | N14: 1556 | O14: GABRIEL.ALBINO | Q14: =SUM(R14:AD14)-I14 -> 0 | S14: =SUMIFS('Doc''s Pagos | Rodopar 108'!$J:$J,'Doc''s Pagos | Rodopar 108'!$A:$A,$B14&$E14&$F14&$J14,'Doc''s Pagos | Rodopar 108'!$B:$B,S$1)+SUMIFS('Doc Há Pagar | Rodopar 1015'!$J:$J,'Doc Há Pagar | Rodopar 1015'!$A:$A,$B14&$E14&$F14,'Doc Há Pagar | Rodopar 1015'!$B:$B,S$1) -> 0 | T14: =SUMIFS('Doc''s Pagos | Rodopar 108'!$J:$J,'Doc''s Pagos | Rodopar 108'!$A:$A,$B14&$E14&$F14&$J14,'Doc''s Pagos | Rodopar 108'!$B:$B,T$1)+SUMIFS('Doc Há Pagar | Rodopar 1015'!$J:$J,'Doc Há Pagar | Rodopar 1015'!$A:$A,$B14&$E14&$F14,'Doc Há Pagar | Rodopar 1015'!$B:$B,T$1) -> 2526.91 | U14: =SUMIFS('Doc''s Pagos | Rodopar 108'!$J:$J,'Doc''s Pagos | Rodopar 108'!$A:$A,$B14&$E14&$F14&$J14,'Doc''s Pagos | Rodopar 108'!$B:$B,U$1)+SUMIFS('Doc Há Pagar | Rodopar 1015'!$J:$J,'Doc Há Pagar | Rodopar 1015'!$A:$A,$B14&$E14&$F14,'Doc Há Pagar | Rodopar 1015'!$B:$B,U$1) -> 0 | V14: =SUMIFS('Doc''s Pagos | Rodopar 108'!$J:$J,'Doc''s Pagos | Rodopar 108'!$A:$A,$B14&$E14&$F14&$J14,'Doc''s Pagos | Rodopar 108'!$B:$B,V$1)+SUMIFS('Doc Há Pagar | Rodopar 1015'!$J:$J,'Doc Há Pagar | Rodopar 1015'!$A:$A,$B14&$E14&$F14,'Doc Há Pagar | Rodopar 1015'!$B:$B,V$1) -> 0 | W14: =SUMIFS('Doc''s Pagos | Rodopar 108'!$J:$J,'Doc''s Pagos | Rodopar 108'!$A:$A,$B14&$E14&$F14&$J14,'Doc''s Pagos | Rodopar 108'!$B:$B,W$1)+SUMIFS('Doc Há Pagar | Rodopar 1015'!$J:$J,'Doc Há Pagar | Rodopar 1015'!$A:$A,$B14&$E14&$F14,'Doc Há Pagar | Rodopar 1015'!$B:$B,W$1) -> 0 | X14: =SUMIFS('Doc''s Pagos | Rodopar 108'!$J:$J,'Doc''s Pagos | Rodopar 108'!$A:$A,$B14&$E14&$F14&$J14,'Doc''s Pagos | Rodopar 108'!$B:$B,X$1)+SUMIFS('Doc Há Pagar | Rodopar 1015'!$J:$J,'Doc Há Pagar | Rodopar 1015'!$A:$A,$B14&$E14&$F14,'Doc Há Pagar | Rodopar 1015'!$B:$B,X$1) -> 0 | Y14: =SUMIFS('Doc''s Pagos | Rodopar 108'!$J:$J,'Doc''s Pagos | Rodopar 108'!$A:$A,$B14&$E14&$F14&$J14,'Doc''s Pagos | Rodopar 108'!$B:$B,Y$1)+SUMIFS('Doc Há Pagar | Rodopar 1015'!$J:$J,'Doc Há Pagar | Rodopar 1015'!$A:$A,$B14&$E14&$F14,'Doc Há Pagar | Rodopar 1015'!$B:$B,Y$1) -> 0 | Z14: =SUMIFS('Doc''s Pagos | Rodopar 108'!$J:$J,'Doc''s Pagos | Rodopar 108'!$A:$A,$B14&$E14&$F14&$J14,'Doc''s Pagos | Rodopar 108'!$B:$B,Z$1)+SUMIFS('Doc Há Pagar | Rodopar 1015'!$J:$J,'Doc Há Pagar | Rodopar 1015'!$A:$A,$B14&$E14&$F14,'Doc Há Pagar | Rodopar 1015'!$B:$B,Z$1) -> 0 | ... AD14: =SUMIFS('Doc''s Pagos | Rodopar 108'!$J:$J,'Doc''s Pagos | Rodopar 108'!$A:$A,$B14&$E14&$F14&$J14,'Doc''s Pagos | Rodopar 108'!$B:$B,AD$1)+SUMIFS('Doc Há Pagar | Rodopar 1015'!$J:$J,'Doc Há Pagar | Rodopar 1015'!$A:$A,$B14&$E14&$F14,'Doc Há Pagar | Rodopar 1015'!$B:$B,AD$1) -> 0
A15: =VLOOKUP($E15,Fornecedores!$A:$C,3,0) -> Frota | B15: 6120 | C15: =IFERROR(VLOOKUP($E15,Fornecedores!$A:$E,4,0),"") -> Manutenção | D15: =IFERROR(VLOOKUP($E15,Fornecedores!$A:$E,5,0),"") -> Peças E Serviços | E15: LL BATERIAS E AUTO-ELETRICA LTDA | F15: NFE | G15: 12.118.555/0001-11 | H15: 87 | I15: 435 | J15: 46031 | K15: 46034 | L15: CONTAGEM | M15: MG | N15: 1556 | O15: GABRIEL.ALBINO | Q15: =SUM(R15:AD15)-I15 -> 0 | S15: =SUMIFS('Doc''s Pagos | Rodopar 108'!$J:$J,'Doc''s Pagos | Rodopar 108'!$A:$A,$B15&$E15&$F15&$J15,'Doc''s Pagos | Rodopar 108'!$B:$B,S$1)+SUMIFS('Doc Há Pagar | Rodopar 1015'!$J:$J,'Doc Há Pagar | Rodopar 1015'!$A:$A,$B15&$E15&$F15,'Doc Há Pagar | Rodopar 1015'!$B:$B,S$1) -> 0 | T15: =SUMIFS('Doc''s Pagos | Rodopar 108'!$J:$J,'Doc''s Pagos | Rodopar 108'!$A:$A,$B15&$E15&$F15&$J15,'Doc''s Pagos | Rodopar 108'!$B:$B,T$1)+SUMIFS('Doc Há Pagar | Rodopar 1015'!$J:$J,'Doc Há Pagar | Rodopar 1015'!$A:$A,$B15&$E15&$F15,'Doc Há Pagar | Rodopar 1015'!$B:$B,T$1) -> 435 | U15: =SUMIFS('Doc''s Pagos | Rodopar 108'!$J:$J,'Doc''s Pagos | Rodopar 108'!$A:$A,$B15&$E15&$F15&$J15,'Doc''s Pagos | Rodopar 108'!$B:$B,U$1)+SUMIFS('Doc Há Pagar | Rodopar 1015'!$J:$J,'Doc Há Pagar | Rodopar 1015'!$A:$A,$B15&$E15&$F15,'Doc Há Pagar | Rodopar 1015'!$B:$B,U$1) -> 0 | V15: =SUMIFS('Doc''s Pagos | Rodopar 108'!$J:$J,'Doc''s Pagos | Rodopar 108'!$A:$A,$B15&$E15&$F15&$J15,'Doc''s Pagos | Rodopar 108'!$B:$B,V$1)+SUMIFS('Doc Há Pagar | Rodopar 1015'!$J:$J,'Doc Há Pagar | Rodopar 1015'!$A:$A,$B15&$E15&$F15,'Doc Há Pagar | Rodopar 1015'!$B:$B,V$1) -> 0 | W15: =SUMIFS('Doc''s Pagos | Rodopar 108'!$J:$J,'Doc''s Pagos | Rodopar 108'!$A:$A,$B15&$E15&$F15&$J15,'Doc''s Pagos | Rodopar 108'!$B:$B,W$1)+SUMIFS('Doc Há Pagar | Rodopar 1015'!$J:$J,'Doc Há Pagar | Rodopar 1015'!$A:$A,$B15&$E15&$F15,'Doc Há Pagar | Rodopar 1015'!$B:$B,W$1) -> 0 | X15: =SUMIFS('Doc''s Pagos | Rodopar 108'!$J:$J,'Doc''s Pagos | Rodopar 108'!$A:$A,$B15&$E15&$F15&$J15,'Doc''s Pagos | Rodopar 108'!$B:$B,X$1)+SUMIFS('Doc Há Pagar | Rodopar 1015'!$J:$J,'Doc Há Pagar | Rodopar 1015'!$A:$A,$B15&$E15&$F15,'Doc Há Pagar | Rodopar 1015'!$B:$B,X$1) -> 0 | Y15: =SUMIFS('Doc''s Pagos | Rodopar 108'!$J:$J,'Doc''s Pagos | Rodopar 108'!$A:$A,$B15&$E15&$F15&$J15,'Doc''s Pagos | Rodopar 108'!$B:$B,Y$1)+SUMIFS('Doc Há Pagar | Rodopar 1015'!$J:$J,'Doc Há Pagar | Rodopar 1015'!$A:$A,$B15&$E15&$F15,'Doc Há Pagar | Rodopar 1015'!$B:$B,Y$1) -> 0 | Z15: =SUMIFS('Doc''s Pagos | Rodopar 108'!$J:$J,'Doc''s Pagos | Rodopar 108'!$A:$A,$B15&$E15&$F15&$J15,'Doc''s Pagos | Rodopar 108'!$B:$B,Z$1)+SUMIFS('Doc Há Pagar | Rodopar 1015'!$J:$J,'Doc Há Pagar | Rodopar 1015'!$A:$A,$B15&$E15&$F15,'Doc Há Pagar | Rodopar 1015'!$B:$B,Z$1) -> 0 | ... AD15: =SUMIFS('Doc''s Pagos | Rodopar 108'!$J:$J,'Doc''s Pagos | Rodopar 108'!$A:$A,$B15&$E15&$F15&$J15,'Doc''s Pagos | Rodopar 108'!$B:$B,AD$1)+SUMIFS('Doc Há Pagar | Rodopar 1015'!$J:$J,'Doc Há Pagar | Rodopar 1015'!$A:$A,$B15&$E15&$F15,'Doc Há Pagar | Rodopar 1015'!$B:$B,AD$1) -> 0
A16: =VLOOKUP($E16,Fornecedores!$A:$C,3,0) -> Frota | B16: 2805 | C16: =IFERROR(VLOOKUP($E16,Fornecedores!$A:$E,4,0),"") -> Pneus | D16: =IFERROR(VLOOKUP($E16,Fornecedores!$A:$E,5,0),"") -> Tecnologia | E16: OPENSYSTECH SERVICOS DE MANUTENCAO DE SISTEMAS LTDA | F16: NFS | G16: 23.756.723/0001-10 | H16: 87 | I16: 936.1 | J16: 46031 | K16: 46037 | L16: SAO PAULO | M16: SP | N16: 2949 | O16: JEFFERSON.LIRA | Q16: =SUM(R16:AD16)-I16 -> 0 | S16: =SUMIFS('Doc''s Pagos | Rodopar 108'!$J:$J,'Doc''s Pagos | Rodopar 108'!$A:$A,$B16&$E16&$F16&$J16,'Doc''s Pagos | Rodopar 108'!$B:$B,S$1)+SUMIFS('Doc Há Pagar | Rodopar 1015'!$J:$J,'Doc Há Pagar | Rodopar 1015'!$A:$A,$B16&$E16&$F16,'Doc Há Pagar | Rodopar 1015'!$B:$B,S$1) -> 0 | T16: =SUMIFS('Doc''s Pagos | Rodopar 108'!$J:$J,'Doc''s Pagos | Rodopar 108'!$A:$A,$B16&$E16&$F16&$J16,'Doc''s Pagos | Rodopar 108'!$B:$B,T$1)+SUMIFS('Doc Há Pagar | Rodopar 1015'!$J:$J,'Doc Há Pagar | Rodopar 1015'!$A:$A,$B16&$E16&$F16,'Doc Há Pagar | Rodopar 1015'!$B:$B,T$1) -> 936.1 | U16: =SUMIFS('Doc''s Pagos | Rodopar 108'!$J:$J,'Doc''s Pagos | Rodopar 108'!$A:$A,$B16&$E16&$F16&$J16,'Doc''s Pagos | Rodopar 108'!$B:$B,U$1)+SUMIFS('Doc Há Pagar | Rodopar 1015'!$J:$J,'Doc Há Pagar | Rodopar 1015'!$A:$A,$B16&$E16&$F16,'Doc Há Pagar | Rodopar 1015'!$B:$B,U$1) -> 0 | V16: =SUMIFS('Doc''s Pagos | Rodopar 108'!$J:$J,'Doc''s Pagos | Rodopar 108'!$A:$A,$B16&$E16&$F16&$J16,'Doc''s Pagos | Rodopar 108'!$B:$B,V$1)+SUMIFS('Doc Há Pagar | Rodopar 1015'!$J:$J,'Doc Há Pagar | Rodopar 1015'!$A:$A,$B16&$E16&$F16,'Doc Há Pagar | Rodopar 1015'!$B:$B,V$1) -> 0 | W16: =SUMIFS('Doc''s Pagos | Rodopar 108'!$J:$J,'Doc''s Pagos | Rodopar 108'!$A:$A,$B16&$E16&$F16&$J16,'Doc''s Pagos | Rodopar 108'!$B:$B,W$1)+SUMIFS('Doc Há Pagar | Rodopar 1015'!$J:$J,'Doc Há Pagar | Rodopar 1015'!$A:$A,$B16&$E16&$F16,'Doc Há Pagar | Rodopar 1015'!$B:$B,W$1) -> 0 | X16: =SUMIFS('Doc''s Pagos | Rodopar 108'!$J:$J,'Doc''s Pagos | Rodopar 108'!$A:$A,$B16&$E16&$F16&$J16,'Doc''s Pagos | Rodopar 108'!$B:$B,X$1)+SUMIFS('Doc Há Pagar | Rodopar 1015'!$J:$J,'Doc Há Pagar | Rodopar 1015'!$A:$A,$B16&$E16&$F16,'Doc Há Pagar | Rodopar 1015'!$B:$B,X$1) -> 0 | Y16: =SUMIFS('Doc''s Pagos | Rodopar 108'!$J:$J,'Doc''s Pagos | Rodopar 108'!$A:$A,$B16&$E16&$F16&$J16,'Doc''s Pagos | Rodopar 108'!$B:$B,Y$1)+SUMIFS('Doc Há Pagar | Rodopar 1015'!$J:$J,'Doc Há Pagar | Rodopar 1015'!$A:$A,$B16&$E16&$F16,'Doc Há Pagar | Rodopar 1015'!$B:$B,Y$1) -> 0 | Z16: =SUMIFS('Doc''s Pagos | Rodopar 108'!$J:$J,'Doc''s Pagos | Rodopar 108'!$A:$A,$B16&$E16&$F16&$J16,'Doc''s Pagos | Rodopar 108'!$B:$B,Z$1)+SUMIFS('Doc Há Pagar | Rodopar 1015'!$J:$J,'Doc Há Pagar | Rodopar 1015'!$A:$A,$B16&$E16&$F16,'Doc Há Pagar | Rodopar 1015'!$B:$B,Z$1) -> 0 | ... AD16: =SUMIFS('Doc''s Pagos | Rodopar 108'!$J:$J,'Doc''s Pagos | Rodopar 108'!$A:$A,$B16&$E16&$F16&$J16,'Doc''s Pagos | Rodopar 108'!$B:$B,AD$1)+SUMIFS('Doc Há Pagar | Rodopar 1015'!$J:$J,'Doc Há Pagar | Rodopar 1015'!$A:$A,$B16&$E16&$F16,'Doc Há Pagar | Rodopar 1015'!$B:$B,AD$1) -> 0
A17: =VLOOKUP($E17,Fornecedores!$A:$C,3,0) -> Frota | B17: 23645 | C17: =IFERROR(VLOOKUP($E17,Fornecedores!$A:$E,4,0),"") -> Manutenção | D17: =IFERROR(VLOOKUP($E17,Fornecedores!$A:$E,5,0),"") -> Vans | E17: MINAS MAQUINAS SA | JUIZ DE FORA | F17: NSE | G17: 21.549.423/0001-35 | H17: 87 | I17: 999 | J17: 46031 | K17: 46035 | L17: JUIZ DE FORA | M17: MG | N17: 1556 | O17: GABRIEL.ALBINO | Q17: =SUM(R17:AD17)-I17 -> 0 | S17: =SUMIFS('Doc''s Pagos | Rodopar 108'!$J:$J,'Doc''s Pagos | Rodopar 108'!$A:$A,$B17&$E17&$F17&$J17,'Doc''s Pagos | Rodopar 108'!$B:$B,S$1)+SUMIFS('Doc Há Pagar | Rodopar 1015'!$J:$J,'Doc Há Pagar | Rodopar 1015'!$A:$A,$B17&$E17&$F17,'Doc Há Pagar | Rodopar 1015'!$B:$B,S$1) -> 0 | T17: =SUMIFS('Doc''s Pagos | Rodopar 108'!$J:$J,'Doc''s Pagos | Rodopar 108'!$A:$A,$B17&$E17&$F17&$J17,'Doc''s Pagos | Rodopar 108'!$B:$B,T$1)+SUMIFS('Doc Há Pagar | Rodopar 1015'!$J:$J,'Doc Há Pagar | Rodopar 1015'!$A:$A,$B17&$E17&$F17,'Doc Há Pagar | Rodopar 1015'!$B:$B,T$1) -> 999 | U17: =SUMIFS('Doc''s Pagos | Rodopar 108'!$J:$J,'Doc''s Pagos | Rodopar 108'!$A:$A,$B17&$E17&$F17&$J17,'Doc''s Pagos | Rodopar 108'!$B:$B,U$1)+SUMIFS('Doc Há Pagar | Rodopar 1015'!$J:$J,'Doc Há Pagar | Rodopar 1015'!$A:$A,$B17&$E17&$F17,'Doc Há Pagar | Rodopar 1015'!$B:$B,U$1) -> 0 | V17: =SUMIFS('Doc''s Pagos | Rodopar 108'!$J:$J,'Doc''s Pagos | Rodopar 108'!$A:$A,$B17&$E17&$F17&$J17,'Doc''s Pagos | Rodopar 108'!$B:$B,V$1)+SUMIFS('Doc Há Pagar | Rodopar 1015'!$J:$J,'Doc Há Pagar | Rodopar 1015'!$A:$A,$B17&$E17&$F17,'Doc Há Pagar | Rodopar 1015'!$B:$B,V$1) -> 0 | W17: =SUMIFS('Doc''s Pagos | Rodopar 108'!$J:$J,'Doc''s Pagos | Rodopar 108'!$A:$A,$B17&$E17&$F17&$J17,'Doc''s Pagos | Rodopar 108'!$B:$B,W$1)+SUMIFS('Doc Há Pagar | Rodopar 1015'!$J:$J,'Doc Há Pagar | Rodopar 1015'!$A:$A,$B17&$E17&$F17,'Doc Há Pagar | Rodopar 1015'!$B:$B,W$1) -> 0 | X17: =SUMIFS('Doc''s Pagos | Rodopar 108'!$J:$J,'Doc''s Pagos | Rodopar 108'!$A:$A,$B17&$E17&$F17&$J17,'Doc''s Pagos | Rodopar 108'!$B:$B,X$1)+SUMIFS('Doc Há Pagar | Rodopar 1015'!$J:$J,'Doc Há Pagar | Rodopar 1015'!$A:$A,$B17&$E17&$F17,'Doc Há Pagar | Rodopar 1015'!$B:$B,X$1) -> 0 | Y17: =SUMIFS('Doc''s Pagos | Rodopar 108'!$J:$J,'Doc''s Pagos | Rodopar 108'!$A:$A,$B17&$E17&$F17&$J17,'Doc''s Pagos | Rodopar 108'!$B:$B,Y$1)+SUMIFS('Doc Há Pagar | Rodopar 1015'!$J:$J,'Doc Há Pagar | Rodopar 1015'!$A:$A,$B17&$E17&$F17,'Doc Há Pagar | Rodopar 1015'!$B:$B,Y$1) -> 0 | Z17: =SUMIFS('Doc''s Pagos | Rodopar 108'!$J:$J,'Doc''s Pagos | Rodopar 108'!$A:$A,$B17&$E17&$F17&$J17,'Doc''s Pagos | Rodopar 108'!$B:$B,Z$1)+SUMIFS('Doc Há Pagar | Rodopar 1015'!$J:$J,'Doc Há Pagar | Rodopar 1015'!$A:$A,$B17&$E17&$F17,'Doc Há Pagar | Rodopar 1015'!$B:$B,Z$1) -> 0 | ... AD17: =SUMIFS('Doc''s Pagos | Rodopar 108'!$J:$J,'Doc''s Pagos | Rodopar 108'!$A:$A,$B17&$E17&$F17&$J17,'Doc''s Pagos | Rodopar 108'!$B:$B,AD$1)+SUMIFS('Doc Há Pagar | Rodopar 1015'!$J:$J,'Doc Há Pagar | Rodopar 1015'!$A:$A,$B17&$E17&$F17,'Doc Há Pagar | Rodopar 1015'!$B:$B,AD$1) -> 0
A18: =VLOOKUP($E18,Fornecedores!$A:$C,3,0) -> Frota | B18: 326 | C18: =IFERROR(VLOOKUP($E18,Fornecedores!$A:$E,4,0),"") -> Lavagem | D18: =IFERROR(VLOOKUP($E18,Fornecedores!$A:$E,5,0),"") -> Lavagem | E18: LAURISNEIDE VIEIRA DA SILVA 02793491306 | F18: NSE | G18: 41.736.221/0001-00 | H18: 87 | I18: 360 | J18: 46031 | K18: 46031 | L18: UBERLANDIA | M18: MG | N18: 1556 | O18: GABRIEL.ALBINO | Q18: =SUM(R18:AD18)-I18 -> 0 | S18: =SUMIFS('Doc''s Pagos | Rodopar 108'!$J:$J,'Doc''s Pagos | Rodopar 108'!$A:$A,$B18&$E18&$F18&$J18,'Doc''s Pagos | Rodopar 108'!$B:$B,S$1)+SUMIFS('Doc Há Pagar | Rodopar 1015'!$J:$J,'Doc Há Pagar | Rodopar 1015'!$A:$A,$B18&$E18&$F18,'Doc Há Pagar | Rodopar 1015'!$B:$B,S$1) -> 0 | T18: =SUMIFS('Doc''s Pagos | Rodopar 108'!$J:$J,'Doc''s Pagos | Rodopar 108'!$A:$A,$B18&$E18&$F18&$J18,'Doc''s Pagos | Rodopar 108'!$B:$B,T$1)+SUMIFS('Doc Há Pagar | Rodopar 1015'!$J:$J,'Doc Há Pagar | Rodopar 1015'!$A:$A,$B18&$E18&$F18,'Doc Há Pagar | Rodopar 1015'!$B:$B,T$1) -> 360 | U18: =SUMIFS('Doc''s Pagos | Rodopar 108'!$J:$J,'Doc''s Pagos | Rodopar 108'!$A:$A,$B18&$E18&$F18&$J18,'Doc''s Pagos | Rodopar 108'!$B:$B,U$1)+SUMIFS('Doc Há Pagar | Rodopar 1015'!$J:$J,'Doc Há Pagar | Rodopar 1015'!$A:$A,$B18&$E18&$F18,'Doc Há Pagar | Rodopar 1015'!$B:$B,U$1) -> 0 | V18: =SUMIFS('Doc''s Pagos | Rodopar 108'!$J:$J,'Doc''s Pagos | Rodopar 108'!$A:$A,$B18&$E18&$F18&$J18,'Doc''s Pagos | Rodopar 108'!$B:$B,V$1)+SUMIFS('Doc Há Pagar | Rodopar 1015'!$J:$J,'Doc Há Pagar | Rodopar 1015'!$A:$A,$B18&$E18&$F18,'Doc Há Pagar | Rodopar 1015'!$B:$B,V$1) -> 0 | W18: =SUMIFS('Doc''s Pagos | Rodopar 108'!$J:$J,'Doc''s Pagos | Rodopar 108'!$A:$A,$B18&$E18&$F18&$J18,'Doc''s Pagos | Rodopar 108'!$B:$B,W$1)+SUMIFS('Doc Há Pagar | Rodopar 1015'!$J:$J,'Doc Há Pagar | Rodopar 1015'!$A:$A,$B18&$E18&$F18,'Doc Há Pagar | Rodopar 1015'!$B:$B,W$1) -> 0 | X18: =SUMIFS('Doc''s Pagos | Rodopar 108'!$J:$J,'Doc''s Pagos | Rodopar 108'!$A:$A,$B18&$E18&$F18&$J18,'Doc''s Pagos | Rodopar 108'!$B:$B,X$1)+SUMIFS('Doc Há Pagar | Rodopar 1015'!$J:$J,'Doc Há Pagar | Rodopar 1015'!$A:$A,$B18&$E18&$F18,'Doc Há Pagar | Rodopar 1015'!$B:$B,X$1) -> 0 | Y18: =SUMIFS('Doc''s Pagos | Rodopar 108'!$J:$J,'Doc''s Pagos | Rodopar 108'!$A:$A,$B18&$E18&$F18&$J18,'Doc''s Pagos | Rodopar 108'!$B:$B,Y$1)+SUMIFS('Doc Há Pagar | Rodopar 1015'!$J:$J,'Doc Há Pagar | Rodopar 1015'!$A:$A,$B18&$E18&$F18,'Doc Há Pagar | Rodopar 1015'!$B:$B,Y$1) -> 0 | Z18: =SUMIFS('Doc''s Pagos | Rodopar 108'!$J:$J,'Doc''s Pagos | Rodopar 108'!$A:$A,$B18&$E18&$F18&$J18,'Doc''s Pagos | Rodopar 108'!$B:$B,Z$1)+SUMIFS('Doc Há Pagar | Rodopar 1015'!$J:$J,'Doc Há Pagar | Rodopar 1015'!$A:$A,$B18&$E18&$F18,'Doc Há Pagar | Rodopar 1015'!$B:$B,Z$1) -> 0 | ... AD18: =SUMIFS('Doc''s Pagos | Rodopar 108'!$J:$J,'Doc''s Pagos | Rodopar 108'!$A:$A,$B18&$E18&$F18&$J18,'Doc''s Pagos | Rodopar 108'!$B:$B,AD$1)+SUMIFS('Doc Há Pagar | Rodopar 1015'!$J:$J,'Doc Há Pagar | Rodopar 1015'!$A:$A,$B18&$E18&$F18,'Doc Há Pagar | Rodopar 1015'!$B:$B,AD$1) -> 0
A19: =VLOOKUP($E19,Fornecedores!$A:$C,3,0) -> Frota | B19: 6 | C19: =IFERROR(VLOOKUP($E19,Fornecedores!$A:$E,4,0),"") -> Lavagem | D19: =IFERROR(VLOOKUP($E19,Fornecedores!$A:$E,5,0),"") -> Lavagem | E19: HIGOR RODNEY CIMINI DA COSTA | F19: NSE | G19: 29.524.404/0001-66 | H19: 87 | I19: 12450 | J19: 46031 | K19: 46034 | L19: CONTAGEM | M19: MG | N19: 1556 | O19: GABRIEL.ALBINO | Q19: =SUM(R19:AD19)-I19 -> 0 | S19: =SUMIFS('Doc''s Pagos | Rodopar 108'!$J:$J,'Doc''s Pagos | Rodopar 108'!$A:$A,$B19&$E19&$F19&$J19,'Doc''s Pagos | Rodopar 108'!$B:$B,S$1)+SUMIFS('Doc Há Pagar | Rodopar 1015'!$J:$J,'Doc Há Pagar | Rodopar 1015'!$A:$A,$B19&$E19&$F19,'Doc Há Pagar | Rodopar 1015'!$B:$B,S$1) -> 0 | T19: =SUMIFS('Doc''s Pagos | Rodopar 108'!$J:$J,'Doc''s Pagos | Rodopar 108'!$A:$A,$B19&$E19&$F19&$J19,'Doc''s Pagos | Rodopar 108'!$B:$B,T$1)+SUMIFS('Doc Há Pagar | Rodopar 1015'!$J:$J,'Doc Há Pagar | Rodopar 1015'!$A:$A,$B19&$E19&$F19,'Doc Há Pagar | Rodopar 1015'!$B:$B,T$1) -> 12450 | U19: =SUMIFS('Doc''s Pagos | Rodopar 108'!$J:$J,'Doc''s Pagos | Rodopar 108'!$A:$A,$B19&$E19&$F19&$J19,'Doc''s Pagos | Rodopar 108'!$B:$B,U$1)+SUMIFS('Doc Há Pagar | Rodopar 1015'!$J:$J,'Doc Há Pagar | Rodopar 1015'!$A:$A,$B19&$E19&$F19,'Doc Há Pagar | Rodopar 1015'!$B:$B,U$1) -> 0 | V19: =SUMIFS('Doc''s Pagos | Rodopar 108'!$J:$J,'Doc''s Pagos | Rodopar 108'!$A:$A,$B19&$E19&$F19&$J19,'Doc''s Pagos | Rodopar 108'!$B:$B,V$1)+SUMIFS('Doc Há Pagar | Rodopar 1015'!$J:$J,'Doc Há Pagar | Rodopar 1015'!$A:$A,$B19&$E19&$F19,'Doc Há Pagar | Rodopar 1015'!$B:$B,V$1) -> 0 | W19: =SUMIFS('Doc''s Pagos | Rodopar 108'!$J:$J,'Doc''s Pagos | Rodopar 108'!$A:$A,$B19&$E19&$F19&$J19,'Doc''s Pagos | Rodopar 108'!$B:$B,W$1)+SUMIFS('Doc Há Pagar | Rodopar 1015'!$J:$J,'Doc Há Pagar | Rodopar 1015'!$A:$A,$B19&$E19&$F19,'Doc Há Pagar | Rodopar 1015'!$B:$B,W$1) -> 0 | X19: =SUMIFS('Doc''s Pagos | Rodopar 108'!$J:$J,'Doc''s Pagos | Rodopar 108'!$A:$A,$B19&$E19&$F19&$J19,'Doc''s Pagos | Rodopar 108'!$B:$B,X$1)+SUMIFS('Doc Há Pagar | Rodopar 1015'!$J:$J,'Doc Há Pagar | Rodopar 1015'!$A:$A,$B19&$E19&$F19,'Doc Há Pagar | Rodopar 1015'!$B:$B,X$1) -> 0 | Y19: =SUMIFS('Doc''s Pagos | Rodopar 108'!$J:$J,'Doc''s Pagos | Rodopar 108'!$A:$A,$B19&$E19&$F19&$J19,'Doc''s Pagos | Rodopar 108'!$B:$B,Y$1)+SUMIFS('Doc Há Pagar | Rodopar 1015'!$J:$J,'Doc Há Pagar | Rodopar 1015'!$A:$A,$B19&$E19&$F19,'Doc Há Pagar | Rodopar 1015'!$B:$B,Y$1) -> 0 | Z19: =SUMIFS('Doc''s Pagos | Rodopar 108'!$J:$J,'Doc''s Pagos | Rodopar 108'!$A:$A,$B19&$E19&$F19&$J19,'Doc''s Pagos | Rodopar 108'!$B:$B,Z$1)+SUMIFS('Doc Há Pagar | Rodopar 1015'!$J:$J,'Doc Há Pagar | Rodopar 1015'!$A:$A,$B19&$E19&$F19,'Doc Há Pagar | Rodopar 1015'!$B:$B,Z$1) -> 0 | ... AD19: =SUMIFS('Doc''s Pagos | Rodopar 108'!$J:$J,'Doc''s Pagos | Rodopar 108'!$A:$A,$B19&$E19&$F19&$J19,'Doc''s Pagos | Rodopar 108'!$B:$B,AD$1)+SUMIFS('Doc Há Pagar | Rodopar 1015'!$J:$J,'Doc Há Pagar | Rodopar 1015'!$A:$A,$B19&$E19&$F19,'Doc Há Pagar | Rodopar 1015'!$B:$B,AD$1) -> 0
A20: =VLOOKUP($E20,Fornecedores!$A:$C,3,0) -> Frota | B20: 222247 | C20: =IFERROR(VLOOKUP($E20,Fornecedores!$A:$E,4,0),"") -> Manutenção | D20: =IFERROR(VLOOKUP($E20,Fornecedores!$A:$E,5,0),"") -> Peças E Serviços | E20: A C FARIAS COM. DE PEÇAS E SERVIÇOS. EIRELI EPP | F20: NFE | G20: 11.384.025/0001-52 | H20: 87 | I20: 1458 | J20: 46034 | K20: 46034 | L20: ANANINDEUA | M20: PA | N20: 2556 | O20: GABRIEL.ALBINO | Q20: =SUM(R20:AD20)-I20 -> 0 | S20: =SUMIFS('Doc''s Pagos | Rodopar 108'!$J:$J,'Doc''s Pagos | Rodopar 108'!$A:$A,$B20&$E20&$F20&$J20,'Doc''s Pagos | Rodopar 108'!$B:$B,S$1)+SUMIFS('Doc Há Pagar | Rodopar 1015'!$J:$J,'Doc Há Pagar | Rodopar 1015'!$A:$A,$B20&$E20&$F20,'Doc Há Pagar | Rodopar 1015'!$B:$B,S$1) -> 0 | T20: =SUMIFS('Doc''s Pagos | Rodopar 108'!$J:$J,'Doc''s Pagos | Rodopar 108'!$A:$A,$B20&$E20&$F20&$J20,'Doc''s Pagos | Rodopar 108'!$B:$B,T$1)+SUMIFS('Doc Há Pagar | Rodopar 1015'!$J:$J,'Doc Há Pagar | Rodopar 1015'!$A:$A,$B20&$E20&$F20,'Doc Há Pagar | Rodopar 1015'!$B:$B,T$1) -> 1458 | U20: =SUMIFS('Doc''s Pagos | Rodopar 108'!$J:$J,'Doc''s Pagos | Rodopar 108'!$A:$A,$B20&$E20&$F20&$J20,'Doc''s Pagos | Rodopar 108'!$B:$B,U$1)+SUMIFS('Doc Há Pagar | Rodopar 1015'!$J:$J,'Doc Há Pagar | Rodopar 1015'!$A:$A,$B20&$E20&$F20,'Doc Há Pagar | Rodopar 1015'!$B:$B,U$1) -> 0 | V20: =SUMIFS('Doc''s Pagos | Rodopar 108'!$J:$J,'Doc''s Pagos | Rodopar 108'!$A:$A,$B20&$E20&$F20&$J20,'Doc''s Pagos | Rodopar 108'!$B:$B,V$1)+SUMIFS('Doc Há Pagar | Rodopar 1015'!$J:$J,'Doc Há Pagar | Rodopar 1015'!$A:$A,$B20&$E20&$F20,'Doc Há Pagar | Rodopar 1015'!$B:$B,V$1) -> 0 | W20: =SUMIFS('Doc''s Pagos | Rodopar 108'!$J:$J,'Doc''s Pagos | Rodopar 108'!$A:$A,$B20&$E20&$F20&$J20,'Doc''s Pagos | Rodopar 108'!$B:$B,W$1)+SUMIFS('Doc Há Pagar | Rodopar 1015'!$J:$J,'Doc Há Pagar | Rodopar 1015'!$A:$A,$B20&$E20&$F20,'Doc Há Pagar | Rodopar 1015'!$B:$B,W$1) -> 0 | X20: =SUMIFS('Doc''s Pagos | Rodopar 108'!$J:$J,'Doc''s Pagos | Rodopar 108'!$A:$A,$B20&$E20&$F20&$J20,'Doc''s Pagos | Rodopar 108'!$B:$B,X$1)+SUMIFS('Doc Há Pagar | Rodopar 1015'!$J:$J,'Doc Há Pagar | Rodopar 1015'!$A:$A,$B20&$E20&$F20,'Doc Há Pagar | Rodopar 1015'!$B:$B,X$1) -> 0 | Y20: =SUMIFS('Doc''s Pagos | Rodopar 108'!$J:$J,'Doc''s Pagos | Rodopar 108'!$A:$A,$B20&$E20&$F20&$J20,'Doc''s Pagos | Rodopar 108'!$B:$B,Y$1)+SUMIFS('Doc Há Pagar | Rodopar 1015'!$J:$J,'Doc Há Pagar | Rodopar 1015'!$A:$A,$B20&$E20&$F20,'Doc Há Pagar | Rodopar 1015'!$B:$B,Y$1) -> 0 | Z20: =SUMIFS('Doc''s Pagos | Rodopar 108'!$J:$J,'Doc''s Pagos | Rodopar 108'!$A:$A,$B20&$E20&$F20&$J20,'Doc''s Pagos | Rodopar 108'!$B:$B,Z$1)+SUMIFS('Doc Há Pagar | Rodopar 1015'!$J:$J,'Doc Há Pagar | Rodopar 1015'!$A:$A,$B20&$E20&$F20,'Doc Há Pagar | Rodopar 1015'!$B:$B,Z$1) -> 0 | ... AD20: =SUMIFS('Doc''s Pagos | Rodopar 108'!$J:$J,'Doc''s Pagos | Rodopar 108'!$A:$A,$B20&$E20&$F20&$J20,'Doc''s Pagos | Rodopar 108'!$B:$B,AD$1)+SUMIFS('Doc Há Pagar | Rodopar 1015'!$J:$J,'Doc Há Pagar | Rodopar 1015'!$A:$A,$B20&$E20&$F20,'Doc Há Pagar | Rodopar 1015'!$B:$B,AD$1) -> 0
A21: =VLOOKUP($E21,Fornecedores!$A:$C,3,0) -> Frota | B21: 90 | C21: =IFERROR(VLOOKUP($E21,Fornecedores!$A:$E,4,0),"") -> Manutenção | D21: =IFERROR(VLOOKUP($E21,Fornecedores!$A:$E,5,0),"") -> Peças E Serviços | E21: ZAMBALDI AUTO CENTER LTDA | F21: NFE | G21: 55.012.105/0001-52 | H21: 87 | I21: 594.98 | J21: 46035 | K21: 46036 | L21: CONTAGEM | M21: MG | N21: 1556 | O21: GABRIEL.ALBINO | Q21: =SUM(R21:AD21)-I21 -> 0 | S21: =SUMIFS('Doc''s Pagos | Rodopar 108'!$J:$J,'Doc''s Pagos | Rodopar 108'!$A:$A,$B21&$E21&$F21&$J21,'Doc''s Pagos | Rodopar 108'!$B:$B,S$1)+SUMIFS('Doc Há Pagar | Rodopar 1015'!$J:$J,'Doc Há Pagar | Rodopar 1015'!$A:$A,$B21&$E21&$F21,'Doc Há Pagar | Rodopar 1015'!$B:$B,S$1) -> 0 | T21: =SUMIFS('Doc''s Pagos | Rodopar 108'!$J:$J,'Doc''s Pagos | Rodopar 108'!$A:$A,$B21&$E21&$F21&$J21,'Doc''s Pagos | Rodopar 108'!$B:$B,T$1)+SUMIFS('Doc Há Pagar | Rodopar 1015'!$J:$J,'Doc Há Pagar | Rodopar 1015'!$A:$A,$B21&$E21&$F21,'Doc Há Pagar | Rodopar 1015'!$B:$B,T$1) -> 594.98 | U21: =SUMIFS('Doc''s Pagos | Rodopar 108'!$J:$J,'Doc''s Pagos | Rodopar 108'!$A:$A,$B21&$E21&$F21&$J21,'Doc''s Pagos | Rodopar 108'!$B:$B,U$1)+SUMIFS('Doc Há Pagar | Rodopar 1015'!$J:$J,'Doc Há Pagar | Rodopar 1015'!$A:$A,$B21&$E21&$F21,'Doc Há Pagar | Rodopar 1015'!$B:$B,U$1) -> 0 | V21: =SUMIFS('Doc''s Pagos | Rodopar 108'!$J:$J,'Doc''s Pagos | Rodopar 108'!$A:$A,$B21&$E21&$F21&$J21,'Doc''s Pagos | Rodopar 108'!$B:$B,V$1)+SUMIFS('Doc Há Pagar | Rodopar 1015'!$J:$J,'Doc Há Pagar | Rodopar 1015'!$A:$A,$B21&$E21&$F21,'Doc Há Pagar | Rodopar 1015'!$B:$B,V$1) -> 0 | W21: =SUMIFS('Doc''s Pagos | Rodopar 108'!$J:$J,'Doc''s Pagos | Rodopar 108'!$A:$A,$B21&$E21&$F21&$J21,'Doc''s Pagos | Rodopar 108'!$B:$B,W$1)+SUMIFS('Doc Há Pagar | Rodopar 1015'!$J:$J,'Doc Há Pagar | Rodopar 1015'!$A:$A,$B21&$E21&$F21,'Doc Há Pagar | Rodopar 1015'!$B:$B,W$1) -> 0 | X21: =SUMIFS('Doc''s Pagos | Rodopar 108'!$J:$J,'Doc''s Pagos | Rodopar 108'!$A:$A,$B21&$E21&$F21&$J21,'Doc''s Pagos | Rodopar 108'!$B:$B,X$1)+SUMIFS('Doc Há Pagar | Rodopar 1015'!$J:$J,'Doc Há Pagar | Rodopar 1015'!$A:$A,$B21&$E21&$F21,'Doc Há Pagar | Rodopar 1015'!$B:$B,X$1) -> 0 | Y21: =SUMIFS('Doc''s Pagos | Rodopar 108'!$J:$J,'Doc''s Pagos | Rodopar 108'!$A:$A,$B21&$E21&$F21&$J21,'Doc''s Pagos | Rodopar 108'!$B:$B,Y$1)+SUMIFS('Doc Há Pagar | Rodopar 1015'!$J:$J,'Doc Há Pagar | Rodopar 1015'!$A:$A,$B21&$E21&$F21,'Doc Há Pagar | Rodopar 1015'!$B:$B,Y$1) -> 0 | Z21: =SUMIFS('Doc''s Pagos | Rodopar 108'!$J:$J,'Doc''s Pagos | Rodopar 108'!$A:$A,$B21&$E21&$F21&$J21,'Doc''s Pagos | Rodopar 108'!$B:$B,Z$1)+SUMIFS('Doc Há Pagar | Rodopar 1015'!$J:$J,'Doc Há Pagar | Rodopar 1015'!$A:$A,$B21&$E21&$F21,'Doc Há Pagar | Rodopar 1015'!$B:$B,Z$1) -> 0 | ... AD21: =SUMIFS('Doc''s Pagos | Rodopar 108'!$J:$J,'Doc''s Pagos | Rodopar 108'!$A:$A,$B21&$E21&$F21&$J21,'Doc''s Pagos | Rodopar 108'!$B:$B,AD$1)+SUMIFS('Doc Há Pagar | Rodopar 1015'!$J:$J,'Doc Há Pagar | Rodopar 1015'!$A:$A,$B21&$E21&$F21,'Doc Há Pagar | Rodopar 1015'!$B:$B,AD$1) -> 0
A22: =VLOOKUP($E22,Fornecedores!$A:$C,3,0) -> Frota | B22: 993983 | C22: =IFERROR(VLOOKUP($E22,Fornecedores!$A:$E,4,0),"") -> Manutenção | D22: =IFERROR(VLOOKUP($E22,Fornecedores!$A:$E,5,0),"") -> Caminhão | E22: TREVISO BETIM VEICULOS LTDA | F22: NFE | G22: 21.014.220/0001-44 | H22: 87 | I22: 1808.48 | J22: 46035 | K22: 46054 | L22: BETIM | M22: MG | N22: 1556 | O22: GABRIEL.ALBINO | Q22: =SUM(R22:AD22)-I22 -> 0 | S22: =SUMIFS('Doc''s Pagos | Rodopar 108'!$J:$J,'Doc''s Pagos | Rodopar 108'!$A:$A,$B22&$E22&$F22&$J22,'Doc''s Pagos | Rodopar 108'!$B:$B,S$1)+SUMIFS('Doc Há Pagar | Rodopar 1015'!$J:$J,'Doc Há Pagar | Rodopar 1015'!$A:$A,$B22&$E22&$F22,'Doc Há Pagar | Rodopar 1015'!$B:$B,S$1) -> 0 | T22: =SUMIFS('Doc''s Pagos | Rodopar 108'!$J:$J,'Doc''s Pagos | Rodopar 108'!$A:$A,$B22&$E22&$F22&$J22,'Doc''s Pagos | Rodopar 108'!$B:$B,T$1)+SUMIFS('Doc Há Pagar | Rodopar 1015'!$J:$J,'Doc Há Pagar | Rodopar 1015'!$A:$A,$B22&$E22&$F22,'Doc Há Pagar | Rodopar 1015'!$B:$B,T$1) -> 1808.48 | U22: =SUMIFS('Doc''s Pagos | Rodopar 108'!$J:$J,'Doc''s Pagos | Rodopar 108'!$A:$A,$B22&$E22&$F22&$J22,'Doc''s Pagos | Rodopar 108'!$B:$B,U$1)+SUMIFS('Doc Há Pagar | Rodopar 1015'!$J:$J,'Doc Há Pagar | Rodopar 1015'!$A:$A,$B22&$E22&$F22,'Doc Há Pagar | Rodopar 1015'!$B:$B,U$1) -> 0 | V22: =SUMIFS('Doc''s Pagos | Rodopar 108'!$J:$J,'Doc''s Pagos | Rodopar 108'!$A:$A,$B22&$E22&$F22&$J22,'Doc''s Pagos | Rodopar 108'!$B:$B,V$1)+SUMIFS('Doc Há Pagar | Rodopar 1015'!$J:$J,'Doc Há Pagar | Rodopar 1015'!$A:$A,$B22&$E22&$F22,'Doc Há Pagar | Rodopar 1015'!$B:$B,V$1) -> 0 | W22: =SUMIFS('Doc''s Pagos | Rodopar 108'!$J:$J,'Doc''s Pagos | Rodopar 108'!$A:$A,$B22&$E22&$F22&$J22,'Doc''s Pagos | Rodopar 108'!$B:$B,W$1)+SUMIFS('Doc Há Pagar | Rodopar 1015'!$J:$J,'Doc Há Pagar | Rodopar 1015'!$A:$A,$B22&$E22&$F22,'Doc Há Pagar | Rodopar 1015'!$B:$B,W$1) -> 0 | X22: =SUMIFS('Doc''s Pagos | Rodopar 108'!$J:$J,'Doc''s Pagos | Rodopar 108'!$A:$A,$B22&$E22&$F22&$J22,'Doc''s Pagos | Rodopar 108'!$B:$B,X$1)+SUMIFS('Doc Há Pagar | Rodopar 1015'!$J:$J,'Doc Há Pagar | Rodopar 1015'!$A:$A,$B22&$E22&$F22,'Doc Há Pagar | Rodopar 1015'!$B:$B,X$1) -> 0 | Y22: =SUMIFS('Doc''s Pagos | Rodopar 108'!$J:$J,'Doc''s Pagos | Rodopar 108'!$A:$A,$B22&$E22&$F22&$J22,'Doc''s Pagos | Rodopar 108'!$B:$B,Y$1)+SUMIFS('Doc Há Pagar | Rodopar 1015'!$J:$J,'Doc Há Pagar | Rodopar 1015'!$A:$A,$B22&$E22&$F22,'Doc Há Pagar | Rodopar 1015'!$B:$B,Y$1) -> 0 | Z22: =SUMIFS('Doc''s Pagos | Rodopar 108'!$J:$J,'Doc''s Pagos | Rodopar 108'!$A:$A,$B22&$E22&$F22&$J22,'Doc''s Pagos | Rodopar 108'!$B:$B,Z$1)+SUMIFS('Doc Há Pagar | Rodopar 1015'!$J:$J,'Doc Há Pagar | Rodopar 1015'!$A:$A,$B22&$E22&$F22,'Doc Há Pagar | Rodopar 1015'!$B:$B,Z$1) -> 0 | ... AD22: =SUMIFS('Doc''s Pagos | Rodopar 108'!$J:$J,'Doc''s Pagos | Rodopar 108'!$A:$A,$B22&$E22&$F22&$J22,'Doc''s Pagos | Rodopar 108'!$B:$B,AD$1)+SUMIFS('Doc Há Pagar | Rodopar 1015'!$J:$J,'Doc Há Pagar | Rodopar 1015'!$A:$A,$B22&$E22&$F22,'Doc Há Pagar | Rodopar 1015'!$B:$B,AD$1) -> 0
A23: =VLOOKUP($E23,Fornecedores!$A:$C,3,0) -> Frota | B23: 12 | C23: =IFERROR(VLOOKUP($E23,Fornecedores!$A:$E,4,0),"") -> Manutenção | D23: =IFERROR(VLOOKUP($E23,Fornecedores!$A:$E,5,0),"") -> Peças E Serviços | E23: ZAMBALDI AUTO CENTER LTDA | F23: NSE | G23: 55.012.105/0001-52 | H23: 87 | I23: 978 | J23: 46035 | K23: 46036 | L23: CONTAGEM | M23: MG | N23: 1556 | O23: GABRIEL.ALBINO | Q23: =SUM(R23:AD23)-I23 -> 0 | S23: =SUMIFS('Doc''s Pagos | Rodopar 108'!$J:$J,'Doc''s Pagos | Rodopar 108'!$A:$A,$B23&$E23&$F23&$J23,'Doc''s Pagos | Rodopar 108'!$B:$B,S$1)+SUMIFS('Doc Há Pagar | Rodopar 1015'!$J:$J,'Doc Há Pagar | Rodopar 1015'!$A:$A,$B23&$E23&$F23,'Doc Há Pagar | Rodopar 1015'!$B:$B,S$1) -> 0 | T23: =SUMIFS('Doc''s Pagos | Rodopar 108'!$J:$J,'Doc''s Pagos | Rodopar 108'!$A:$A,$B23&$E23&$F23&$J23,'Doc''s Pagos | Rodopar 108'!$B:$B,T$1)+SUMIFS('Doc Há Pagar | Rodopar 1015'!$J:$J,'Doc Há Pagar | Rodopar 1015'!$A:$A,$B23&$E23&$F23,'Doc Há Pagar | Rodopar 1015'!$B:$B,T$1) -> 978 | U23: =SUMIFS('Doc''s Pagos | Rodopar 108'!$J:$J,'Doc''s Pagos | Rodopar 108'!$A:$A,$B23&$E23&$F23&$J23,'Doc''s Pagos | Rodopar 108'!$B:$B,U$1)+SUMIFS('Doc Há Pagar | Rodopar 1015'!$J:$J,'Doc Há Pagar | Rodopar 1015'!$A:$A,$B23&$E23&$F23,'Doc Há Pagar | Rodopar 1015'!$B:$B,U$1) -> 0 | V23: =SUMIFS('Doc''s Pagos | Rodopar 108'!$J:$J,'Doc''s Pagos | Rodopar 108'!$A:$A,$B23&$E23&$F23&$J23,'Doc''s Pagos | Rodopar 108'!$B:$B,V$1)+SUMIFS('Doc Há Pagar | Rodopar 1015'!$J:$J,'Doc Há Pagar | Rodopar 1015'!$A:$A,$B23&$E23&$F23,'Doc Há Pagar | Rodopar 1015'!$B:$B,V$1) -> 0 | W23: =SUMIFS('Doc''s Pagos | Rodopar 108'!$J:$J,'Doc''s Pagos | Rodopar 108'!$A:$A,$B23&$E23&$F23&$J23,'Doc''s Pagos | Rodopar 108'!$B:$B,W$1)+SUMIFS('Doc Há Pagar | Rodopar 1015'!$J:$J,'Doc Há Pagar | Rodopar 1015'!$A:$A,$B23&$E23&$F23,'Doc Há Pagar | Rodopar 1015'!$B:$B,W$1) -> 0 | X23: =SUMIFS('Doc''s Pagos | Rodopar 108'!$J:$J,'Doc''s Pagos | Rodopar 108'!$A:$A,$B23&$E23&$F23&$J23,'Doc''s Pagos | Rodopar 108'!$B:$B,X$1)+SUMIFS('Doc Há Pagar | Rodopar 1015'!$J:$J,'Doc Há Pagar | Rodopar 1015'!$A:$A,$B23&$E23&$F23,'Doc Há Pagar | Rodopar 1015'!$B:$B,X$1) -> 0 | Y23: =SUMIFS('Doc''s Pagos | Rodopar 108'!$J:$J,'Doc''s Pagos | Rodopar 108'!$A:$A,$B23&$E23&$F23&$J23,'Doc''s Pagos | Rodopar 108'!$B:$B,Y$1)+SUMIFS('Doc Há Pagar | Rodopar 1015'!$J:$J,'Doc Há Pagar | Rodopar 1015'!$A:$A,$B23&$E23&$F23,'Doc Há Pagar | Rodopar 1015'!$B:$B,Y$1) -> 0 | Z23: =SUMIFS('Doc''s Pagos | Rodopar 108'!$J:$J,'Doc''s Pagos | Rodopar 108'!$A:$A,$B23&$E23&$F23&$J23,'Doc''s Pagos | Rodopar 108'!$B:$B,Z$1)+SUMIFS('Doc Há Pagar | Rodopar 1015'!$J:$J,'Doc Há Pagar | Rodopar 1015'!$A:$A,$B23&$E23&$F23,'Doc Há Pagar | Rodopar 1015'!$B:$B,Z$1) -> 0 | ... AD23: =SUMIFS('Doc''s Pagos | Rodopar 108'!$J:$J,'Doc''s Pagos | Rodopar 108'!$A:$A,$B23&$E23&$F23&$J23,'Doc''s Pagos | Rodopar 108'!$B:$B,AD$1)+SUMIFS('Doc Há Pagar | Rodopar 1015'!$J:$J,'Doc Há Pagar | Rodopar 1015'!$A:$A,$B23&$E23&$F23,'Doc Há Pagar | Rodopar 1015'!$B:$B,AD$1) -> 0
A24: =VLOOKUP($E24,Fornecedores!$A:$C,3,0) -> Frota | B24: 994241 | C24: =IFERROR(VLOOKUP($E24,Fornecedores!$A:$E,4,0),"") -> Manutenção | D24: =IFERROR(VLOOKUP($E24,Fornecedores!$A:$E,5,0),"") -> Caminhão | E24: TREVISO BETIM VEICULOS LTDA | F24: NFE | G24: 21.014.220/0001-44 | H24: 87 | I24: 1808.48 | J24: 46036 | K24: 46054 | L24: BETIM | M24: MG | N24: 1556 | O24: GABRIEL.ALBINO | Q24: =SUM(R24:AD24)-I24 -> 0 | S24: =SUMIFS('Doc''s Pagos | Rodopar 108'!$J:$J,'Doc''s Pagos | Rodopar 108'!$A:$A,$B24&$E24&$F24&$J24,'Doc''s Pagos | Rodopar 108'!$B:$B,S$1)+SUMIFS('Doc Há Pagar | Rodopar 1015'!$J:$J,'Doc Há Pagar | Rodopar 1015'!$A:$A,$B24&$E24&$F24,'Doc Há Pagar | Rodopar 1015'!$B:$B,S$1) -> 0 | T24: =SUMIFS('Doc''s Pagos | Rodopar 108'!$J:$J,'Doc''s Pagos | Rodopar 108'!$A:$A,$B24&$E24&$F24&$J24,'Doc''s Pagos | Rodopar 108'!$B:$B,T$1)+SUMIFS('Doc Há Pagar | Rodopar 1015'!$J:$J,'Doc Há Pagar | Rodopar 1015'!$A:$A,$B24&$E24&$F24,'Doc Há Pagar | Rodopar 1015'!$B:$B,T$1) -> 1808.48 | U24: =SUMIFS('Doc''s Pagos | Rodopar 108'!$J:$J,'Doc''s Pagos | Rodopar 108'!$A:$A,$B24&$E24&$F24&$J24,'Doc''s Pagos | Rodopar 108'!$B:$B,U$1)+SUMIFS('Doc Há Pagar | Rodopar 1015'!$J:$J,'Doc Há Pagar | Rodopar 1015'!$A:$A,$B24&$E24&$F24,'Doc Há Pagar | Rodopar 1015'!$B:$B,U$1) -> 0 | V24: =SUMIFS('Doc''s Pagos | Rodopar 108'!$J:$J,'Doc''s Pagos | Rodopar 108'!$A:$A,$B24&$E24&$F24&$J24,'Doc''s Pagos | Rodopar 108'!$B:$B,V$1)+SUMIFS('Doc Há Pagar | Rodopar 1015'!$J:$J,'Doc Há Pagar | Rodopar 1015'!$A:$A,$B24&$E24&$F24,'Doc Há Pagar | Rodopar 1015'!$B:$B,V$1) -> 0 | W24: =SUMIFS('Doc''s Pagos | Rodopar 108'!$J:$J,'Doc''s Pagos | Rodopar 108'!$A:$A,$B24&$E24&$F24&$J24,'Doc''s Pagos | Rodopar 108'!$B:$B,W$1)+SUMIFS('Doc Há Pagar | Rodopar 1015'!$J:$J,'Doc Há Pagar | Rodopar 1015'!$A:$A,$B24&$E24&$F24,'Doc Há Pagar | Rodopar 1015'!$B:$B,W$1) -> 0 | X24: =SUMIFS('Doc''s Pagos | Rodopar 108'!$J:$J,'Doc''s Pagos | Rodopar 108'!$A:$A,$B24&$E24&$F24&$J24,'Doc''s Pagos | Rodopar 108'!$B:$B,X$1)+SUMIFS('Doc Há Pagar | Rodopar 1015'!$J:$J,'Doc Há Pagar | Rodopar 1015'!$A:$A,$B24&$E24&$F24,'Doc Há Pagar | Rodopar 1015'!$B:$B,X$1) -> 0 | Y24: =SUMIFS('Doc''s Pagos | Rodopar 108'!$J:$J,'Doc''s Pagos | Rodopar 108'!$A:$A,$B24&$E24&$F24&$J24,'Doc''s Pagos | Rodopar 108'!$B:$B,Y$1)+SUMIFS('Doc Há Pagar | Rodopar 1015'!$J:$J,'Doc Há Pagar | Rodopar 1015'!$A:$A,$B24&$E24&$F24,'Doc Há Pagar | Rodopar 1015'!$B:$B,Y$1) -> 0 | Z24: =SUMIFS('Doc''s Pagos | Rodopar 108'!$J:$J,'Doc''s Pagos | Rodopar 108'!$A:$A,$B24&$E24&$F24&$J24,'Doc''s Pagos | Rodopar 108'!$B:$B,Z$1)+SUMIFS('Doc Há Pagar | Rodopar 1015'!$J:$J,'Doc Há Pagar | Rodopar 1015'!$A:$A,$B24&$E24&$F24,'Doc Há Pagar | Rodopar 1015'!$B:$B,Z$1) -> 0 | ... AD24: =SUMIFS('Doc''s Pagos | Rodopar 108'!$J:$J,'Doc''s Pagos | Rodopar 108'!$A:$A,$B24&$E24&$F24&$J24,'Doc''s Pagos | Rodopar 108'!$B:$B,AD$1)+SUMIFS('Doc Há Pagar | Rodopar 1015'!$J:$J,'Doc Há Pagar | Rodopar 1015'!$A:$A,$B24&$E24&$F24,'Doc Há Pagar | Rodopar 1015'!$B:$B,AD$1) -> 0
A25: =VLOOKUP($E25,Fornecedores!$A:$C,3,0) -> Frota | B25: 14 | C25: =IFERROR(VLOOKUP($E25,Fornecedores!$A:$E,4,0),"") -> Manutenção | D25: =IFERROR(VLOOKUP($E25,Fornecedores!$A:$E,5,0),"") -> Peças E Serviços | E25: ZAMBALDI AUTO CENTER LTDA | F25: NSE | G25: 55.012.105/0001-52 | H25: 87 | I25: 150 | J25: 46036 | K25: 46037 | L25: CONTAGEM | M25: MG | N25: 1556 | O25: GABRIEL.ALBINO | Q25: =SUM(R25:AD25)-I25 -> 0 | S25: =SUMIFS('Doc''s Pagos | Rodopar 108'!$J:$J,'Doc''s Pagos | Rodopar 108'!$A:$A,$B25&$E25&$F25&$J25,'Doc''s Pagos | Rodopar 108'!$B:$B,S$1)+SUMIFS('Doc Há Pagar | Rodopar 1015'!$J:$J,'Doc Há Pagar | Rodopar 1015'!$A:$A,$B25&$E25&$F25,'Doc Há Pagar | Rodopar 1015'!$B:$B,S$1) -> 0 | T25: =SUMIFS('Doc''s Pagos | Rodopar 108'!$J:$J,'Doc''s Pagos | Rodopar 108'!$A:$A,$B25&$E25&$F25&$J25,'Doc''s Pagos | Rodopar 108'!$B:$B,T$1)+SUMIFS('Doc Há Pagar | Rodopar 1015'!$J:$J,'Doc Há Pagar | Rodopar 1015'!$A:$A,$B25&$E25&$F25,'Doc Há Pagar | Rodopar 1015'!$B:$B,T$1) -> 150 | U25: =SUMIFS('Doc''s Pagos | Rodopar 108'!$J:$J,'Doc''s Pagos | Rodopar 108'!$A:$A,$B25&$E25&$F25&$J25,'Doc''s Pagos | Rodopar 108'!$B:$B,U$1)+SUMIFS('Doc Há Pagar | Rodopar 1015'!$J:$J,'Doc Há Pagar | Rodopar 1015'!$A:$A,$B25&$E25&$F25,'Doc Há Pagar | Rodopar 1015'!$B:$B,U$1) -> 0 | V25: =SUMIFS('Doc''s Pagos | Rodopar 108'!$J:$J,'Doc''s Pagos | Rodopar 108'!$A:$A,$B25&$E25&$F25&$J25,'Doc''s Pagos | Rodopar 108'!$B:$B,V$1)+SUMIFS('Doc Há Pagar | Rodopar 1015'!$J:$J,'Doc Há Pagar | Rodopar 1015'!$A:$A,$B25&$E25&$F25,'Doc Há Pagar | Rodopar 1015'!$B:$B,V$1) -> 0 | W25: =SUMIFS('Doc''s Pagos | Rodopar 108'!$J:$J,'Doc''s Pagos | Rodopar 108'!$A:$A,$B25&$E25&$F25&$J25,'Doc''s Pagos | Rodopar 108'!$B:$B,W$1)+SUMIFS('Doc Há Pagar | Rodopar 1015'!$J:$J,'Doc Há Pagar | Rodopar 1015'!$A:$A,$B25&$E25&$F25,'Doc Há Pagar | Rodopar 1015'!$B:$B,W$1) -> 0 | X25: =SUMIFS('Doc''s Pagos | Rodopar 108'!$J:$J,'Doc''s Pagos | Rodopar 108'!$A:$A,$B25&$E25&$F25&$J25,'Doc''s Pagos | Rodopar 108'!$B:$B,X$1)+SUMIFS('Doc Há Pagar | Rodopar 1015'!$J:$J,'Doc Há Pagar | Rodopar 1015'!$A:$A,$B25&$E25&$F25,'Doc Há Pagar | Rodopar 1015'!$B:$B,X$1) -> 0 | Y25: =SUMIFS('Doc''s Pagos | Rodopar 108'!$J:$J,'Doc''s Pagos | Rodopar 108'!$A:$A,$B25&$E25&$F25&$J25,'Doc''s Pagos | Rodopar 108'!$B:$B,Y$1)+SUMIFS('Doc Há Pagar | Rodopar 1015'!$J:$J,'Doc Há Pagar | Rodopar 1015'!$A:$A,$B25&$E25&$F25,'Doc Há Pagar | Rodopar 1015'!$B:$B,Y$1) -> 0 | Z25: =SUMIFS('Doc''s Pagos | Rodopar 108'!$J:$J,'Doc''s Pagos | Rodopar 108'!$A:$A,$B25&$E25&$F25&$J25,'Doc''s Pagos | Rodopar 108'!$B:$B,Z$1)+SUMIFS('Doc Há Pagar | Rodopar 1015'!$J:$J,'Doc Há Pagar | Rodopar 1015'!$A:$A,$B25&$E25&$F25,'Doc Há Pagar | Rodopar 1015'!$B:$B,Z$1) -> 0 | ... AD25: =SUMIFS('Doc''s Pagos | Rodopar 108'!$J:$J,'Doc''s Pagos | Rodopar 108'!$A:$A,$B25&$E25&$F25&$J25,'Doc''s Pagos | Rodopar 108'!$B:$B,AD$1)+SUMIFS('Doc Há Pagar | Rodopar 1015'!$J:$J,'Doc Há Pagar | Rodopar 1015'!$A:$A,$B25&$E25&$F25,'Doc Há Pagar | Rodopar 1015'!$B:$B,AD$1) -> 0
A26: =VLOOKUP($E26,Fornecedores!$A:$C,3,0) -> Frota | B26: AFMTZ-2993231 | C26: =IFERROR(VLOOKUP($E26,Fornecedores!$A:$E,4,0),"") -> OPE Merchandising | D26: =IFERROR(VLOOKUP($E26,Fornecedores!$A:$E,5,0),"") -> Locação | E26: LOCALIZA FLEET S/A | F26: FT | G26: 02.286.479/0001-08 | H26: 87 | I26: 38471.3 | J26: 46037 | K26: 46041 | L26: BELO HORIZONTE | M26: MG | N26: 1556 | O26: GABRIEL.ALBINO | Q26: =SUM(R26:AD26)-I26 -> 0 | S26: =SUMIFS('Doc''s Pagos | Rodopar 108'!$J:$J,'Doc''s Pagos | Rodopar 108'!$A:$A,$B26&$E26&$F26&$J26,'Doc''s Pagos | Rodopar 108'!$B:$B,S$1)+SUMIFS('Doc Há Pagar | Rodopar 1015'!$J:$J,'Doc Há Pagar | Rodopar 1015'!$A:$A,$B26&$E26&$F26,'Doc Há Pagar | Rodopar 1015'!$B:$B,S$1) -> 38471.3 | T26: =SUMIFS('Doc''s Pagos | Rodopar 108'!$J:$J,'Doc''s Pagos | Rodopar 108'!$A:$A,$B26&$E26&$F26&$J26,'Doc''s Pagos | Rodopar 108'!$B:$B,T$1)+SUMIFS('Doc Há Pagar | Rodopar 1015'!$J:$J,'Doc Há Pagar | Rodopar 1015'!$A:$A,$B26&$E26&$F26,'Doc Há Pagar | Rodopar 1015'!$B:$B,T$1) -> 0 | U26: =SUMIFS('Doc''s Pagos | Rodopar 108'!$J:$J,'Doc''s Pagos | Rodopar 108'!$A:$A,$B26&$E26&$F26&$J26,'Doc''s Pagos | Rodopar 108'!$B:$B,U$1)+SUMIFS('Doc Há Pagar | Rodopar 1015'!$J:$J,'Doc Há Pagar | Rodopar 1015'!$A:$A,$B26&$E26&$F26,'Doc Há Pagar | Rodopar 1015'!$B:$B,U$1) -> 0 | V26: =SUMIFS('Doc''s Pagos | Rodopar 108'!$J:$J,'Doc''s Pagos | Rodopar 108'!$A:$A,$B26&$E26&$F26&$J26,'Doc''s Pagos | Rodopar 108'!$B:$B,V$1)+SUMIFS('Doc Há Pagar | Rodopar 1015'!$J:$J,'Doc Há Pagar | Rodopar 1015'!$A:$A,$B26&$E26&$F26,'Doc Há Pagar | Rodopar 1015'!$B:$B,V$1) -> 0 | W26: =SUMIFS('Doc''s Pagos | Rodopar 108'!$J:$J,'Doc''s Pagos | Rodopar 108'!$A:$A,$B26&$E26&$F26&$J26,'Doc''s Pagos | Rodopar 108'!$B:$B,W$1)+SUMIFS('Doc Há Pagar | Rodopar 1015'!$J:$J,'Doc Há Pagar | Rodopar 1015'!$A:$A,$B26&$E26&$F26,'Doc Há Pagar | Rodopar 1015'!$B:$B,W$1) -> 0 | X26: =SUMIFS('Doc''s Pagos | Rodopar 108'!$J:$J,'Doc''s Pagos | Rodopar 108'!$A:$A,$B26&$E26&$F26&$J26,'Doc''s Pagos | Rodopar 108'!$B:$B,X$1)+SUMIFS('Doc Há Pagar | Rodopar 1015'!$J:$J,'Doc Há Pagar | Rodopar 1015'!$A:$A,$B26&$E26&$F26,'Doc Há Pagar | Rodopar 1015'!$B:$B,X$1) -> 0 | Y26: =SUMIFS('Doc''s Pagos | Rodopar 108'!$J:$J,'Doc''s Pagos | Rodopar 108'!$A:$A,$B26&$E26&$F26&$J26,'Doc''s Pagos | Rodopar 108'!$B:$B,Y$1)+SUMIFS('Doc Há Pagar | Rodopar 1015'!$J:$J,'Doc Há Pagar | Rodopar 1015'!$A:$A,$B26&$E26&$F26,'Doc Há Pagar | Rodopar 1015'!$B:$B,Y$1) -> 0 | Z26: =SUMIFS('Doc''s Pagos | Rodopar 108'!$J:$J,'Doc''s Pagos | Rodopar 108'!$A:$A,$B26&$E26&$F26&$J26,'Doc''s Pagos | Rodopar 108'!$B:$B,Z$1)+SUMIFS('Doc Há Pagar | Rodopar 1015'!$J:$J,'Doc Há Pagar | Rodopar 1015'!$A:$A,$B26&$E26&$F26,'Doc Há Pagar | Rodopar 1015'!$B:$B,Z$1) -> 0 | ... AD26: =SUMIFS('Doc''s Pagos | Rodopar 108'!$J:$J,'Doc''s Pagos | Rodopar 108'!$A:$A,$B26&$E26&$F26&$J26,'Doc''s Pagos | Rodopar 108'!$B:$B,AD$1)+SUMIFS('Doc Há Pagar | Rodopar 1015'!$J:$J,'Doc Há Pagar | Rodopar 1015'!$A:$A,$B26&$E26&$F26,'Doc Há Pagar | Rodopar 1015'!$B:$B,AD$1) -> 0
A27: =VLOOKUP($E27,Fornecedores!$A:$C,3,0) -> Frota | B27: AGMTZ-2948485 | C27: =IFERROR(VLOOKUP($E27,Fornecedores!$A:$E,4,0),"") -> OPE Merchandising | D27: =IFERROR(VLOOKUP($E27,Fornecedores!$A:$E,5,0),"") -> Locação | E27: LOCALIZA FLEET S/A | F27: FT | G27: 02.286.479/0001-08 | H27: 87 | I27: 978 | J27: 46037 | K27: 46064 | L27: BELO HORIZONTE | M27: MG | N27: 1556 | O27: GABRIEL.ALBINO | Q27: =SUM(R27:AD27)-I27 -> 0 | S27: =SUMIFS('Doc''s Pagos | Rodopar 108'!$J:$J,'Doc''s Pagos | Rodopar 108'!$A:$A,$B27&$E27&$F27&$J27,'Doc''s Pagos | Rodopar 108'!$B:$B,S$1)+SUMIFS('Doc Há Pagar | Rodopar 1015'!$J:$J,'Doc Há Pagar | Rodopar 1015'!$A:$A,$B27&$E27&$F27,'Doc Há Pagar | Rodopar 1015'!$B:$B,S$1) -> 0 | T27: =SUMIFS('Doc''s Pagos | Rodopar 108'!$J:$J,'Doc''s Pagos | Rodopar 108'!$A:$A,$B27&$E27&$F27&$J27,'Doc''s Pagos | Rodopar 108'!$B:$B,T$1)+SUMIFS('Doc Há Pagar | Rodopar 1015'!$J:$J,'Doc Há Pagar | Rodopar 1015'!$A:$A,$B27&$E27&$F27,'Doc Há Pagar | Rodopar 1015'!$B:$B,T$1) -> 978 | U27: =SUMIFS('Doc''s Pagos | Rodopar 108'!$J:$J,'Doc''s Pagos | Rodopar 108'!$A:$A,$B27&$E27&$F27&$J27,'Doc''s Pagos | Rodopar 108'!$B:$B,U$1)+SUMIFS('Doc Há Pagar | Rodopar 1015'!$J:$J,'Doc Há Pagar | Rodopar 1015'!$A:$A,$B27&$E27&$F27,'Doc Há Pagar | Rodopar 1015'!$B:$B,U$1) -> 0 | V27: =SUMIFS('Doc''s Pagos | Rodopar 108'!$J:$J,'Doc''s Pagos | Rodopar 108'!$A:$A,$B27&$E27&$F27&$J27,'Doc''s Pagos | Rodopar 108'!$B:$B,V$1)+SUMIFS('Doc Há Pagar | Rodopar 1015'!$J:$J,'Doc Há Pagar | Rodopar 1015'!$A:$A,$B27&$E27&$F27,'Doc Há Pagar | Rodopar 1015'!$B:$B,V$1) -> 0 | W27: =SUMIFS('Doc''s Pagos | Rodopar 108'!$J:$J,'Doc''s Pagos | Rodopar 108'!$A:$A,$B27&$E27&$F27&$J27,'Doc''s Pagos | Rodopar 108'!$B:$B,W$1)+SUMIFS('Doc Há Pagar | Rodopar 1015'!$J:$J,'Doc Há Pagar | Rodopar 1015'!$A:$A,$B27&$E27&$F27,'Doc Há Pagar | Rodopar 1015'!$B:$B,W$1) -> 0 | X27: =SUMIFS('Doc''s Pagos | Rodopar 108'!$J:$J,'Doc''s Pagos | Rodopar 108'!$A:$A,$B27&$E27&$F27&$J27,'Doc''s Pagos | Rodopar 108'!$B:$B,X$1)+SUMIFS('Doc Há Pagar | Rodopar 1015'!$J:$J,'Doc Há Pagar | Rodopar 1015'!$A:$A,$B27&$E27&$F27,'Doc Há Pagar | Rodopar 1015'!$B:$B,X$1) -> 0 | Y27: =SUMIFS('Doc''s Pagos | Rodopar 108'!$J:$J,'Doc''s Pagos | Rodopar 108'!$A:$A,$B27&$E27&$F27&$J27,'Doc''s Pagos | Rodopar 108'!$B:$B,Y$1)+SUMIFS('Doc Há Pagar | Rodopar 1015'!$J:$J,'Doc Há Pagar | Rodopar 1015'!$A:$A,$B27&$E27&$F27,'Doc Há Pagar | Rodopar 1015'!$B:$B,Y$1) -> 0 | Z27: =SUMIFS('Doc''s Pagos | Rodopar 108'!$J:$J,'Doc''s Pagos | Rodopar 108'!$A:$A,$B27&$E27&$F27&$J27,'Doc''s Pagos | Rodopar 108'!$B:$B,Z$1)+SUMIFS('Doc Há Pagar | Rodopar 1015'!$J:$J,'Doc Há Pagar | Rodopar 1015'!$A:$A,$B27&$E27&$F27,'Doc Há Pagar | Rodopar 1015'!$B:$B,Z$1) -> 0 | ... AD27: =SUMIFS('Doc''s Pagos | Rodopar 108'!$J:$J,'Doc''s Pagos | Rodopar 108'!$A:$A,$B27&$E27&$F27&$J27,'Doc''s Pagos | Rodopar 108'!$B:$B,AD$1)+SUMIFS('Doc Há Pagar | Rodopar 1015'!$J:$J,'Doc Há Pagar | Rodopar 1015'!$A:$A,$B27&$E27&$F27,'Doc Há Pagar | Rodopar 1015'!$B:$B,AD$1) -> 0
A28: =VLOOKUP($E28,Fornecedores!$A:$C,3,0) -> Frota | B28: 7447 | C28: =IFERROR(VLOOKUP($E28,Fornecedores!$A:$E,4,0),"") -> Documentação | D28: =IFERROR(VLOOKUP($E28,Fornecedores!$A:$E,5,0),"") -> Tacografos | E28: BETIM TACOGRAFO LTDA | F28: NFE | G28: 24.117.344/0001-43 | H28: 87 | I28: 390 | J28: 46038 | K28: 46041 | L28: BETIM | M28: MG | N28: 1556 | O28: GABRIEL.ALBINO | Q28: =SUM(R28:AD28)-I28 -> 0 | S28: =SUMIFS('Doc''s Pagos | Rodopar 108'!$J:$J,'Doc''s Pagos | Rodopar 108'!$A:$A,$B28&$E28&$F28&$J28,'Doc''s Pagos | Rodopar 108'!$B:$B,S$1)+SUMIFS('Doc Há Pagar | Rodopar 1015'!$J:$J,'Doc Há Pagar | Rodopar 1015'!$A:$A,$B28&$E28&$F28,'Doc Há Pagar | Rodopar 1015'!$B:$B,S$1) -> 390 | T28: =SUMIFS('Doc''s Pagos | Rodopar 108'!$J:$J,'Doc''s Pagos | Rodopar 108'!$A:$A,$B28&$E28&$F28&$J28,'Doc''s Pagos | Rodopar 108'!$B:$B,T$1)+SUMIFS('Doc Há Pagar | Rodopar 1015'!$J:$J,'Doc Há Pagar | Rodopar 1015'!$A:$A,$B28&$E28&$F28,'Doc Há Pagar | Rodopar 1015'!$B:$B,T$1) -> 0 | U28: =SUMIFS('Doc''s Pagos | Rodopar 108'!$J:$J,'Doc''s Pagos | Rodopar 108'!$A:$A,$B28&$E28&$F28&$J28,'Doc''s Pagos | Rodopar 108'!$B:$B,U$1)+SUMIFS('Doc Há Pagar | Rodopar 1015'!$J:$J,'Doc Há Pagar | Rodopar 1015'!$A:$A,$B28&$E28&$F28,'Doc Há Pagar | Rodopar 1015'!$B:$B,U$1) -> 0 | V28: =SUMIFS('Doc''s Pagos | Rodopar 108'!$J:$J,'Doc''s Pagos | Rodopar 108'!$A:$A,$B28&$E28&$F28&$J28,'Doc''s Pagos | Rodopar 108'!$B:$B,V$1)+SUMIFS('Doc Há Pagar | Rodopar 1015'!$J:$J,'Doc Há Pagar | Rodopar 1015'!$A:$A,$B28&$E28&$F28,'Doc Há Pagar | Rodopar 1015'!$B:$B,V$1) -> 0 | W28: =SUMIFS('Doc''s Pagos | Rodopar 108'!$J:$J,'Doc''s Pagos | Rodopar 108'!$A:$A,$B28&$E28&$F28&$J28,'Doc''s Pagos | Rodopar 108'!$B:$B,W$1)+SUMIFS('Doc Há Pagar | Rodopar 1015'!$J:$J,'Doc Há Pagar | Rodopar 1015'!$A:$A,$B28&$E28&$F28,'Doc Há Pagar | Rodopar 1015'!$B:$B,W$1) -> 0 | X28: =SUMIFS('Doc''s Pagos | Rodopar 108'!$J:$J,'Doc''s Pagos | Rodopar 108'!$A:$A,$B28&$E28&$F28&$J28,'Doc''s Pagos | Rodopar 108'!$B:$B,X$1)+SUMIFS('Doc Há Pagar | Rodopar 1015'!$J:$J,'Doc Há Pagar | Rodopar 1015'!$A:$A,$B28&$E28&$F28,'Doc Há Pagar | Rodopar 1015'!$B:$B,X$1) -> 0 | Y28: =SUMIFS('Doc''s Pagos | Rodopar 108'!$J:$J,'Doc''s Pagos | Rodopar 108'!$A:$A,$B28&$E28&$F28&$J28,'Doc''s Pagos | Rodopar 108'!$B:$B,Y$1)+SUMIFS('Doc Há Pagar | Rodopar 1015'!$J:$J,'Doc Há Pagar | Rodopar 1015'!$A:$A,$B28&$E28&$F28,'Doc Há Pagar | Rodopar 1015'!$B:$B,Y$1) -> 0 | Z28: =SUMIFS('Doc''s Pagos | Rodopar 108'!$J:$J,'Doc''s Pagos | Rodopar 108'!$A:$A,$B28&$E28&$F28&$J28,'Doc''s Pagos | Rodopar 108'!$B:$B,Z$1)+SUMIFS('Doc Há Pagar | Rodopar 1015'!$J:$J,'Doc Há Pagar | Rodopar 1015'!$A:$A,$B28&$E28&$F28,'Doc Há Pagar | Rodopar 1015'!$B:$B,Z$1) -> 0 | ... AD28: =SUMIFS('Doc''s Pagos | Rodopar 108'!$J:$J,'Doc''s Pagos | Rodopar 108'!$A:$A,$B28&$E28&$F28&$J28,'Doc''s Pagos | Rodopar 108'!$B:$B,AD$1)+SUMIFS('Doc Há Pagar | Rodopar 1015'!$J:$J,'Doc Há Pagar | Rodopar 1015'!$A:$A,$B28&$E28&$F28,'Doc Há Pagar | Rodopar 1015'!$B:$B,AD$1) -> 0
A29: =VLOOKUP($E29,Fornecedores!$A:$C,3,0) -> Frota | B29: 1449758 | C29: =IFERROR(VLOOKUP($E29,Fornecedores!$A:$E,4,0),"") -> MTSR | D29: =IFERROR(VLOOKUP($E29,Fornecedores!$A:$E,5,0),"") -> Tecnologia | E29: TRUCKS COM. E TEC. DE RASTREAD. COMUNICAÇÕES LTDA | F29: NSE | G29: 27.755.427/0007-41 | H29: 87 | I29: 1479.18 | J29: 46039 | K29: 46041 | L29: IBIPORA | M29: PR | N29: 2556 | O29: GABRIEL.ALBINO | Q29: =SUM(R29:AD29)-I29 -> 0 | S29: =SUMIFS('Doc''s Pagos | Rodopar 108'!$J:$J,'Doc''s Pagos | Rodopar 108'!$A:$A,$B29&$E29&$F29&$J29,'Doc''s Pagos | Rodopar 108'!$B:$B,S$1)+SUMIFS('Doc Há Pagar | Rodopar 1015'!$J:$J,'Doc Há Pagar | Rodopar 1015'!$A:$A,$B29&$E29&$F29,'Doc Há Pagar | Rodopar 1015'!$B:$B,S$1) -> 0 | T29: =SUMIFS('Doc''s Pagos | Rodopar 108'!$J:$J,'Doc''s Pagos | Rodopar 108'!$A:$A,$B29&$E29&$F29&$J29,'Doc''s Pagos | Rodopar 108'!$B:$B,T$1)+SUMIFS('Doc Há Pagar | Rodopar 1015'!$J:$J,'Doc Há Pagar | Rodopar 1015'!$A:$A,$B29&$E29&$F29,'Doc Há Pagar | Rodopar 1015'!$B:$B,T$1) -> 1479.18 | U29: =SUMIFS('Doc''s Pagos | Rodopar 108'!$J:$J,'Doc''s Pagos | Rodopar 108'!$A:$A,$B29&$E29&$F29&$J29,'Doc''s Pagos | Rodopar 108'!$B:$B,U$1)+SUMIFS('Doc Há Pagar | Rodopar 1015'!$J:$J,'Doc Há Pagar | Rodopar 1015'!$A:$A,$B29&$E29&$F29,'Doc Há Pagar | Rodopar 1015'!$B:$B,U$1) -> 0 | V29: =SUMIFS('Doc''s Pagos | Rodopar 108'!$J:$J,'Doc''s Pagos | Rodopar 108'!$A:$A,$B29&$E29&$F29&$J29,'Doc''s Pagos | Rodopar 108'!$B:$B,V$1)+SUMIFS('Doc Há Pagar | Rodopar 1015'!$J:$J,'Doc Há Pagar | Rodopar 1015'!$A:$A,$B29&$E29&$F29,'Doc Há Pagar | Rodopar 1015'!$B:$B,V$1) -> 0 | W29: =SUMIFS('Doc''s Pagos | Rodopar 108'!$J:$J,'Doc''s Pagos | Rodopar 108'!$A:$A,$B29&$E29&$F29&$J29,'Doc''s Pagos | Rodopar 108'!$B:$B,W$1)+SUMIFS('Doc Há Pagar | Rodopar 1015'!$J:$J,'Doc Há Pagar | Rodopar 1015'!$A:$A,$B29&$E29&$F29,'Doc Há Pagar | Rodopar 1015'!$B:$B,W$1) -> 0 | X29: =SUMIFS('Doc''s Pagos | Rodopar 108'!$J:$J,'Doc''s Pagos | Rodopar 108'!$A:$A,$B29&$E29&$F29&$J29,'Doc''s Pagos | Rodopar 108'!$B:$B,X$1)+SUMIFS('Doc Há Pagar | Rodopar 1015'!$J:$J,'Doc Há Pagar | Rodopar 1015'!$A:$A,$B29&$E29&$F29,'Doc Há Pagar | Rodopar 1015'!$B:$B,X$1) -> 0 | Y29: =SUMIFS('Doc''s Pagos | Rodopar 108'!$J:$J,'Doc''s Pagos | Rodopar 108'!$A:$A,$B29&$E29&$F29&$J29,'Doc''s Pagos | Rodopar 108'!$B:$B,Y$1)+SUMIFS('Doc Há Pagar | Rodopar 1015'!$J:$J,'Doc Há Pagar | Rodopar 1015'!$A:$A,$B29&$E29&$F29,'Doc Há Pagar | Rodopar 1015'!$B:$B,Y$1) -> 0 | Z29: =SUMIFS('Doc''s Pagos | Rodopar 108'!$J:$J,'Doc''s Pagos | Rodopar 108'!$A:$A,$B29&$E29&$F29&$J29,'Doc''s Pagos | Rodopar 108'!$B:$B,Z$1)+SUMIFS('Doc Há Pagar | Rodopar 1015'!$J:$J,'Doc Há Pagar | Rodopar 1015'!$A:$A,$B29&$E29&$F29,'Doc Há Pagar | Rodopar 1015'!$B:$B,Z$1) -> 0 | ... AD29: =SUMIFS('Doc''s Pagos | Rodopar 108'!$J:$J,'Doc''s Pagos | Rodopar 108'!$A:$A,$B29&$E29&$F29&$J29,'Doc''s Pagos | Rodopar 108'!$B:$B,AD$1)+SUMIFS('Doc Há Pagar | Rodopar 1015'!$J:$J,'Doc Há Pagar | Rodopar 1015'!$A:$A,$B29&$E29&$F29,'Doc Há Pagar | Rodopar 1015'!$B:$B,AD$1) -> 0
A30: =VLOOKUP($E30,Fornecedores!$A:$C,3,0) -> Frota | B30: 3125842 | C30: =IFERROR(VLOOKUP($E30,Fornecedores!$A:$E,4,0),"") -> MTSR | D30: =IFERROR(VLOOKUP($E30,Fornecedores!$A:$E,5,0),"") -> Tecnologia | E30: TRUCKS CONTROL - SERVIÇOS DE LOGISTICA LTDA | F30: NSE | G30: 09.110.913/0027-74 | H30: 87 | I30: 8365.89 | J30: 46039 | K30: 46041 | L30: IBIPORA | M30: PR | N30: 2556 | O30: GABRIEL.ALBINO | Q30: =SUM(R30:AD30)-I30 -> 0 | S30: =SUMIFS('Doc''s Pagos | Rodopar 108'!$J:$J,'Doc''s Pagos | Rodopar 108'!$A:$A,$B30&$E30&$F30&$J30,'Doc''s Pagos | Rodopar 108'!$B:$B,S$1)+SUMIFS('Doc Há Pagar | Rodopar 1015'!$J:$J,'Doc Há Pagar | Rodopar 1015'!$A:$A,$B30&$E30&$F30,'Doc Há Pagar | Rodopar 1015'!$B:$B,S$1) -> 0 | T30: =SUMIFS('Doc''s Pagos | Rodopar 108'!$J:$J,'Doc''s Pagos | Rodopar 108'!$A:$A,$B30&$E30&$F30&$J30,'Doc''s Pagos | Rodopar 108'!$B:$B,T$1)+SUMIFS('Doc Há Pagar | Rodopar 1015'!$J:$J,'Doc Há Pagar | Rodopar 1015'!$A:$A,$B30&$E30&$F30,'Doc Há Pagar | Rodopar 1015'!$B:$B,T$1) -> 8365.89 | U30: =SUMIFS('Doc''s Pagos | Rodopar 108'!$J:$J,'Doc''s Pagos | Rodopar 108'!$A:$A,$B30&$E30&$F30&$J30,'Doc''s Pagos | Rodopar 108'!$B:$B,U$1)+SUMIFS('Doc Há Pagar | Rodopar 1015'!$J:$J,'Doc Há Pagar | Rodopar 1015'!$A:$A,$B30&$E30&$F30,'Doc Há Pagar | Rodopar 1015'!$B:$B,U$1) -> 0 | V30: =SUMIFS('Doc''s Pagos | Rodopar 108'!$J:$J,'Doc''s Pagos | Rodopar 108'!$A:$A,$B30&$E30&$F30&$J30,'Doc''s Pagos | Rodopar 108'!$B:$B,V$1)+SUMIFS('Doc Há Pagar | Rodopar 1015'!$J:$J,'Doc Há Pagar | Rodopar 1015'!$A:$A,$B30&$E30&$F30,'Doc Há Pagar | Rodopar 1015'!$B:$B,V$1) -> 0 | W30: =SUMIFS('Doc''s Pagos | Rodopar 108'!$J:$J,'Doc''s Pagos | Rodopar 108'!$A:$A,$B30&$E30&$F30&$J30,'Doc''s Pagos | Rodopar 108'!$B:$B,W$1)+SUMIFS('Doc Há Pagar | Rodopar 1015'!$J:$J,'Doc Há Pagar | Rodopar 1015'!$A:$A,$B30&$E30&$F30,'Doc Há Pagar | Rodopar 1015'!$B:$B,W$1) -> 0 | X30: =SUMIFS('Doc''s Pagos | Rodopar 108'!$J:$J,'Doc''s Pagos | Rodopar 108'!$A:$A,$B30&$E30&$F30&$J30,'Doc''s Pagos | Rodopar 108'!$B:$B,X$1)+SUMIFS('Doc Há Pagar | Rodopar 1015'!$J:$J,'Doc Há Pagar | Rodopar 1015'!$A:$A,$B30&$E30&$F30,'Doc Há Pagar | Rodopar 1015'!$B:$B,X$1) -> 0 | Y30: =SUMIFS('Doc''s Pagos | Rodopar 108'!$J:$J,'Doc''s Pagos | Rodopar 108'!$A:$A,$B30&$E30&$F30&$J30,'Doc''s Pagos | Rodopar 108'!$B:$B,Y$1)+SUMIFS('Doc Há Pagar | Rodopar 1015'!$J:$J,'Doc Há Pagar | Rodopar 1015'!$A:$A,$B30&$E30&$F30,'Doc Há Pagar | Rodopar 1015'!$B:$B,Y$1) -> 0 | Z30: =SUMIFS('Doc''s Pagos | Rodopar 108'!$J:$J,'Doc''s Pagos | Rodopar 108'!$A:$A,$B30&$E30&$F30&$J30,'Doc''s Pagos | Rodopar 108'!$B:$B,Z$1)+SUMIFS('Doc Há Pagar | Rodopar 1015'!$J:$J,'Doc Há Pagar | Rodopar 1015'!$A:$A,$B30&$E30&$F30,'Doc Há Pagar | Rodopar 1015'!$B:$B,Z$1) -> 0 | ... AD30: =SUMIFS('Doc''s Pagos | Rodopar 108'!$J:$J,'Doc''s Pagos | Rodopar 108'!$A:$A,$B30&$E30&$F30&$J30,'Doc''s Pagos | Rodopar 108'!$B:$B,AD$1)+SUMIFS('Doc Há Pagar | Rodopar 1015'!$J:$J,'Doc Há Pagar | Rodopar 1015'!$A:$A,$B30&$E30&$F30,'Doc Há Pagar | Rodopar 1015'!$B:$B,AD$1) -> 0
A31: =VLOOKUP($E31,Fornecedores!$A:$C,3,0) -> Frota | B31: 994920 | C31: =IFERROR(VLOOKUP($E31,Fornecedores!$A:$E,4,0),"") -> Manutenção | D31: =IFERROR(VLOOKUP($E31,Fornecedores!$A:$E,5,0),"") -> Caminhão | E31: TREVISO BETIM VEICULOS LTDA | F31: NFE | G31: 21.014.220/0001-44 | H31: 87 | I31: 1808.48 | J31: 46041 | K31: 46054 | L31: BETIM | M31: MG | N31: 1556 | O31: GABRIEL.ALBINO | Q31: =SUM(R31:AD31)-I31 -> 0 | S31: =SUMIFS('Doc''s Pagos | Rodopar 108'!$J:$J,'Doc''s Pagos | Rodopar 108'!$A:$A,$B31&$E31&$F31&$J31,'Doc''s Pagos | Rodopar 108'!$B:$B,S$1)+SUMIFS('Doc Há Pagar | Rodopar 1015'!$J:$J,'Doc Há Pagar | Rodopar 1015'!$A:$A,$B31&$E31&$F31,'Doc Há Pagar | Rodopar 1015'!$B:$B,S$1) -> 0 | T31: =SUMIFS('Doc''s Pagos | Rodopar 108'!$J:$J,'Doc''s Pagos | Rodopar 108'!$A:$A,$B31&$E31&$F31&$J31,'Doc''s Pagos | Rodopar 108'!$B:$B,T$1)+SUMIFS('Doc Há Pagar | Rodopar 1015'!$J:$J,'Doc Há Pagar | Rodopar 1015'!$A:$A,$B31&$E31&$F31,'Doc Há Pagar | Rodopar 1015'!$B:$B,T$1) -> 1808.48 | U31: =SUMIFS('Doc''s Pagos | Rodopar 108'!$J:$J,'Doc''s Pagos | Rodopar 108'!$A:$A,$B31&$E31&$F31&$J31,'Doc''s Pagos | Rodopar 108'!$B:$B,U$1)+SUMIFS('Doc Há Pagar | Rodopar 1015'!$J:$J,'Doc Há Pagar | Rodopar 1015'!$A:$A,$B31&$E31&$F31,'Doc Há Pagar | Rodopar 1015'!$B:$B,U$1) -> 0 | V31: =SUMIFS('Doc''s Pagos | Rodopar 108'!$J:$J,'Doc''s Pagos | Rodopar 108'!$A:$A,$B31&$E31&$F31&$J31,'Doc''s Pagos | Rodopar 108'!$B:$B,V$1)+SUMIFS('Doc Há Pagar | Rodopar 1015'!$J:$J,'Doc Há Pagar | Rodopar 1015'!$A:$A,$B31&$E31&$F31,'Doc Há Pagar | Rodopar 1015'!$B:$B,V$1) -> 0 | W31: =SUMIFS('Doc''s Pagos | Rodopar 108'!$J:$J,'Doc''s Pagos | Rodopar 108'!$A:$A,$B31&$E31&$F31&$J31,'Doc''s Pagos | Rodopar 108'!$B:$B,W$1)+SUMIFS('Doc Há Pagar | Rodopar 1015'!$J:$J,'Doc Há Pagar | Rodopar 1015'!$A:$A,$B31&$E31&$F31,'Doc Há Pagar | Rodopar 1015'!$B:$B,W$1) -> 0 | X31: =SUMIFS('Doc''s Pagos | Rodopar 108'!$J:$J,'Doc''s Pagos | Rodopar 108'!$A:$A,$B31&$E31&$F31&$J31,'Doc''s Pagos | Rodopar 108'!$B:$B,X$1)+SUMIFS('Doc Há Pagar | Rodopar 1015'!$J:$J,'Doc Há Pagar | Rodopar 1015'!$A:$A,$B31&$E31&$F31,'Doc Há Pagar | Rodopar 1015'!$B:$B,X$1) -> 0 | Y31: =SUMIFS('Doc''s Pagos | Rodopar 108'!$J:$J,'Doc''s Pagos | Rodopar 108'!$A:$A,$B31&$E31&$F31&$J31,'Doc''s Pagos | Rodopar 108'!$B:$B,Y$1)+SUMIFS('Doc Há Pagar | Rodopar 1015'!$J:$J,'Doc Há Pagar | Rodopar 1015'!$A:$A,$B31&$E31&$F31,'Doc Há Pagar | Rodopar 1015'!$B:$B,Y$1) -> 0 | Z31: =SUMIFS('Doc''s Pagos | Rodopar 108'!$J:$J,'Doc''s Pagos | Rodopar 108'!$A:$A,$B31&$E31&$F31&$J31,'Doc''s Pagos | Rodopar 108'!$B:$B,Z$1)+SUMIFS('Doc Há Pagar | Rodopar 1015'!$J:$J,'Doc Há Pagar | Rodopar 1015'!$A:$A,$B31&$E31&$F31,'Doc Há Pagar | Rodopar 1015'!$B:$B,Z$1) -> 0 | ... AD31: =SUMIFS('Doc''s Pagos | Rodopar 108'!$J:$J,'Doc''s Pagos | Rodopar 108'!$A:$A,$B31&$E31&$F31&$J31,'Doc''s Pagos | Rodopar 108'!$B:$B,AD$1)+SUMIFS('Doc Há Pagar | Rodopar 1015'!$J:$J,'Doc Há Pagar | Rodopar 1015'!$A:$A,$B31&$E31&$F31,'Doc Há Pagar | Rodopar 1015'!$B:$B,AD$1) -> 0
A32: =VLOOKUP($E32,Fornecedores!$A:$C,3,0) -> Frota | B32: 45651 | C32: =IFERROR(VLOOKUP($E32,Fornecedores!$A:$E,4,0),"") -> Sinistro | D32: =IFERROR(VLOOKUP($E32,Fornecedores!$A:$E,5,0),"") -> Parabrisa | E32: CENTRAL DOS PARA-BRISAS LTDA | F32: NFE | G32: 20.590.353/0001-04 | H32: 87 | I32: 1120 | J32: 46042 | K32: 46044 | L32: BETIM | M32: MG | N32: 1556 | O32: GABRIEL.ALBINO | Q32: =SUM(R32:AD32)-I32 -> 0 | S32: =SUMIFS('Doc''s Pagos | Rodopar 108'!$J:$J,'Doc''s Pagos | Rodopar 108'!$A:$A,$B32&$E32&$F32&$J32,'Doc''s Pagos | Rodopar 108'!$B:$B,S$1)+SUMIFS('Doc Há Pagar | Rodopar 1015'!$J:$J,'Doc Há Pagar | Rodopar 1015'!$A:$A,$B32&$E32&$F32,'Doc Há Pagar | Rodopar 1015'!$B:$B,S$1) -> 0 | T32: =SUMIFS('Doc''s Pagos | Rodopar 108'!$J:$J,'Doc''s Pagos | Rodopar 108'!$A:$A,$B32&$E32&$F32&$J32,'Doc''s Pagos | Rodopar 108'!$B:$B,T$1)+SUMIFS('Doc Há Pagar | Rodopar 1015'!$J:$J,'Doc Há Pagar | Rodopar 1015'!$A:$A,$B32&$E32&$F32,'Doc Há Pagar | Rodopar 1015'!$B:$B,T$1) -> 1120 | U32: =SUMIFS('Doc''s Pagos | Rodopar 108'!$J:$J,'Doc''s Pagos | Rodopar 108'!$A:$A,$B32&$E32&$F32&$J32,'Doc''s Pagos | Rodopar 108'!$B:$B,U$1)+SUMIFS('Doc Há Pagar | Rodopar 1015'!$J:$J,'Doc Há Pagar | Rodopar 1015'!$A:$A,$B32&$E32&$F32,'Doc Há Pagar | Rodopar 1015'!$B:$B,U$1) -> 0 | V32: =SUMIFS('Doc''s Pagos | Rodopar 108'!$J:$J,'Doc''s Pagos | Rodopar 108'!$A:$A,$B32&$E32&$F32&$J32,'Doc''s Pagos | Rodopar 108'!$B:$B,V$1)+SUMIFS('Doc Há Pagar | Rodopar 1015'!$J:$J,'Doc Há Pagar | Rodopar 1015'!$A:$A,$B32&$E32&$F32,'Doc Há Pagar | Rodopar 1015'!$B:$B,V$1) -> 0 | W32: =SUMIFS('Doc''s Pagos | Rodopar 108'!$J:$J,'Doc''s Pagos | Rodopar 108'!$A:$A,$B32&$E32&$F32&$J32,'Doc''s Pagos | Rodopar 108'!$B:$B,W$1)+SUMIFS('Doc Há Pagar | Rodopar 1015'!$J:$J,'Doc Há Pagar | Rodopar 1015'!$A:$A,$B32&$E32&$F32,'Doc Há Pagar | Rodopar 1015'!$B:$B,W$1) -> 0 | X32: =SUMIFS('Doc''s Pagos | Rodopar 108'!$J:$J,'Doc''s Pagos | Rodopar 108'!$A:$A,$B32&$E32&$F32&$J32,'Doc''s Pagos | Rodopar 108'!$B:$B,X$1)+SUMIFS('Doc Há Pagar | Rodopar 1015'!$J:$J,'Doc Há Pagar | Rodopar 1015'!$A:$A,$B32&$E32&$F32,'Doc Há Pagar | Rodopar 1015'!$B:$B,X$1) -> 0 | Y32: =SUMIFS('Doc''s Pagos | Rodopar 108'!$J:$J,'Doc''s Pagos | Rodopar 108'!$A:$A,$B32&$E32&$F32&$J32,'Doc''s Pagos | Rodopar 108'!$B:$B,Y$1)+SUMIFS('Doc Há Pagar | Rodopar 1015'!$J:$J,'Doc Há Pagar | Rodopar 1015'!$A:$A,$B32&$E32&$F32,'Doc Há Pagar | Rodopar 1015'!$B:$B,Y$1) -> 0 | Z32: =SUMIFS('Doc''s Pagos | Rodopar 108'!$J:$J,'Doc''s Pagos | Rodopar 108'!$A:$A,$B32&$E32&$F32&$J32,'Doc''s Pagos | Rodopar 108'!$B:$B,Z$1)+SUMIFS('Doc Há Pagar | Rodopar 1015'!$J:$J,'Doc Há Pagar | Rodopar 1015'!$A:$A,$B32&$E32&$F32,'Doc Há Pagar | Rodopar 1015'!$B:$B,Z$1) -> 0 | ... AD32: =SUMIFS('Doc''s Pagos | Rodopar 108'!$J:$J,'Doc''s Pagos | Rodopar 108'!$A:$A,$B32&$E32&$F32&$J32,'Doc''s Pagos | Rodopar 108'!$B:$B,AD$1)+SUMIFS('Doc Há Pagar | Rodopar 1015'!$J:$J,'Doc Há Pagar | Rodopar 1015'!$A:$A,$B32&$E32&$F32,'Doc Há Pagar | Rodopar 1015'!$B:$B,AD$1) -> 0
A33: =VLOOKUP($E33,Fornecedores!$A:$C,3,0) -> Frota | B33: 92 | C33: =IFERROR(VLOOKUP($E33,Fornecedores!$A:$E,4,0),"") -> Manutenção | D33: =IFERROR(VLOOKUP($E33,Fornecedores!$A:$E,5,0),"") -> Peças E Serviços | E33: ZAMBALDI AUTO CENTER LTDA | F33: NFE | G33: 55.012.105/0001-52 | H33: 87 | I33: 1484.98 | J33: 46042 | K33: 46042 | L33: CONTAGEM | M33: MG | N33: 1556 | O33: GABRIEL.ALBINO | Q33: =SUM(R33:AD33)-I33 -> 0 | S33: =SUMIFS('Doc''s Pagos | Rodopar 108'!$J:$J,'Doc''s Pagos | Rodopar 108'!$A:$A,$B33&$E33&$F33&$J33,'Doc''s Pagos | Rodopar 108'!$B:$B,S$1)+SUMIFS('Doc Há Pagar | Rodopar 1015'!$J:$J,'Doc Há Pagar | Rodopar 1015'!$A:$A,$B33&$E33&$F33,'Doc Há Pagar | Rodopar 1015'!$B:$B,S$1) -> 0 | T33: =SUMIFS('Doc''s Pagos | Rodopar 108'!$J:$J,'Doc''s Pagos | Rodopar 108'!$A:$A,$B33&$E33&$F33&$J33,'Doc''s Pagos | Rodopar 108'!$B:$B,T$1)+SUMIFS('Doc Há Pagar | Rodopar 1015'!$J:$J,'Doc Há Pagar | Rodopar 1015'!$A:$A,$B33&$E33&$F33,'Doc Há Pagar | Rodopar 1015'!$B:$B,T$1) -> 1484.98 | U33: =SUMIFS('Doc''s Pagos | Rodopar 108'!$J:$J,'Doc''s Pagos | Rodopar 108'!$A:$A,$B33&$E33&$F33&$J33,'Doc''s Pagos | Rodopar 108'!$B:$B,U$1)+SUMIFS('Doc Há Pagar | Rodopar 1015'!$J:$J,'Doc Há Pagar | Rodopar 1015'!$A:$A,$B33&$E33&$F33,'Doc Há Pagar | Rodopar 1015'!$B:$B,U$1) -> 0 | V33: =SUMIFS('Doc''s Pagos | Rodopar 108'!$J:$J,'Doc''s Pagos | Rodopar 108'!$A:$A,$B33&$E33&$F33&$J33,'Doc''s Pagos | Rodopar 108'!$B:$B,V$1)+SUMIFS('Doc Há Pagar | Rodopar 1015'!$J:$J,'Doc Há Pagar | Rodopar 1015'!$A:$A,$B33&$E33&$F33,'Doc Há Pagar | Rodopar 1015'!$B:$B,V$1) -> 0 | W33: =SUMIFS('Doc''s Pagos | Rodopar 108'!$J:$J,'Doc''s Pagos | Rodopar 108'!$A:$A,$B33&$E33&$F33&$J33,'Doc''s Pagos | Rodopar 108'!$B:$B,W$1)+SUMIFS('Doc Há Pagar | Rodopar 1015'!$J:$J,'Doc Há Pagar | Rodopar 1015'!$A:$A,$B33&$E33&$F33,'Doc Há Pagar | Rodopar 1015'!$B:$B,W$1) -> 0 | X33: =SUMIFS('Doc''s Pagos | Rodopar 108'!$J:$J,'Doc''s Pagos | Rodopar 108'!$A:$A,$B33&$E33&$F33&$J33,'Doc''s Pagos | Rodopar 108'!$B:$B,X$1)+SUMIFS('Doc Há Pagar | Rodopar 1015'!$J:$J,'Doc Há Pagar | Rodopar 1015'!$A:$A,$B33&$E33&$F33,'Doc Há Pagar | Rodopar 1015'!$B:$B,X$1) -> 0 | Y33: =SUMIFS('Doc''s Pagos | Rodopar 108'!$J:$J,'Doc''s Pagos | Rodopar 108'!$A:$A,$B33&$E33&$F33&$J33,'Doc''s Pagos | Rodopar 108'!$B:$B,Y$1)+SUMIFS('Doc Há Pagar | Rodopar 1015'!$J:$J,'Doc Há Pagar | Rodopar 1015'!$A:$A,$B33&$E33&$F33,'Doc Há Pagar | Rodopar 1015'!$B:$B,Y$1) -> 0 | Z33: =SUMIFS('Doc''s Pagos | Rodopar 108'!$J:$J,'Doc''s Pagos | Rodopar 108'!$A:$A,$B33&$E33&$F33&$J33,'Doc''s Pagos | Rodopar 108'!$B:$B,Z$1)+SUMIFS('Doc Há Pagar | Rodopar 1015'!$J:$J,'Doc Há Pagar | Rodopar 1015'!$A:$A,$B33&$E33&$F33,'Doc Há Pagar | Rodopar 1015'!$B:$B,Z$1) -> 0 | ... AD33: =SUMIFS('Doc''s Pagos | Rodopar 108'!$J:$J,'Doc''s Pagos | Rodopar 108'!$A:$A,$B33&$E33&$F33&$J33,'Doc''s Pagos | Rodopar 108'!$B:$B,AD$1)+SUMIFS('Doc Há Pagar | Rodopar 1015'!$J:$J,'Doc Há Pagar | Rodopar 1015'!$A:$A,$B33&$E33&$F33,'Doc Há Pagar | Rodopar 1015'!$B:$B,AD$1) -> 0
A34: =VLOOKUP($E34,Fornecedores!$A:$C,3,0) -> Frota | B34: 27381 | C34: =IFERROR(VLOOKUP($E34,Fornecedores!$A:$E,4,0),"") -> Manutenção | D34: =IFERROR(VLOOKUP($E34,Fornecedores!$A:$E,5,0),"") -> Contrato | E34: MERCEDES-BENZ CARS & VANS BRASIL LTDA | F34: NSE | G34: 31.715.616/0005-04 | H34: 87 | I34: 52824.78 | J34: 46043 | K34: 46044 | L34: LIMEIRA | M34: SP | N34: 2949 | O34: dayane.vicente | Q34: =SUM(R34:AD34)-I34 -> 0 | S34: =SUMIFS('Doc''s Pagos | Rodopar 108'!$J:$J,'Doc''s Pagos | Rodopar 108'!$A:$A,$B34&$E34&$F34&$J34,'Doc''s Pagos | Rodopar 108'!$B:$B,S$1)+SUMIFS('Doc Há Pagar | Rodopar 1015'!$J:$J,'Doc Há Pagar | Rodopar 1015'!$A:$A,$B34&$E34&$F34,'Doc Há Pagar | Rodopar 1015'!$B:$B,S$1) -> 0 | T34: =SUMIFS('Doc''s Pagos | Rodopar 108'!$J:$J,'Doc''s Pagos | Rodopar 108'!$A:$A,$B34&$E34&$F34&$J34,'Doc''s Pagos | Rodopar 108'!$B:$B,T$1)+SUMIFS('Doc Há Pagar | Rodopar 1015'!$J:$J,'Doc Há Pagar | Rodopar 1015'!$A:$A,$B34&$E34&$F34,'Doc Há Pagar | Rodopar 1015'!$B:$B,T$1) -> 52824.78 | U34: =SUMIFS('Doc''s Pagos | Rodopar 108'!$J:$J,'Doc''s Pagos | Rodopar 108'!$A:$A,$B34&$E34&$F34&$J34,'Doc''s Pagos | Rodopar 108'!$B:$B,U$1)+SUMIFS('Doc Há Pagar | Rodopar 1015'!$J:$J,'Doc Há Pagar | Rodopar 1015'!$A:$A,$B34&$E34&$F34,'Doc Há Pagar | Rodopar 1015'!$B:$B,U$1) -> 0 | V34: =SUMIFS('Doc''s Pagos | Rodopar 108'!$J:$J,'Doc''s Pagos | Rodopar 108'!$A:$A,$B34&$E34&$F34&$J34,'Doc''s Pagos | Rodopar 108'!$B:$B,V$1)+SUMIFS('Doc Há Pagar | Rodopar 1015'!$J:$J,'Doc Há Pagar | Rodopar 1015'!$A:$A,$B34&$E34&$F34,'Doc Há Pagar | Rodopar 1015'!$B:$B,V$1) -> 0 | W34: =SUMIFS('Doc''s Pagos | Rodopar 108'!$J:$J,'Doc''s Pagos | Rodopar 108'!$A:$A,$B34&$E34&$F34&$J34,'Doc''s Pagos | Rodopar 108'!$B:$B,W$1)+SUMIFS('Doc Há Pagar | Rodopar 1015'!$J:$J,'Doc Há Pagar | Rodopar 1015'!$A:$A,$B34&$E34&$F34,'Doc Há Pagar | Rodopar 1015'!$B:$B,W$1) -> 0 | X34: =SUMIFS('Doc''s Pagos | Rodopar 108'!$J:$J,'Doc''s Pagos | Rodopar 108'!$A:$A,$B34&$E34&$F34&$J34,'Doc''s Pagos | Rodopar 108'!$B:$B,X$1)+SUMIFS('Doc Há Pagar | Rodopar 1015'!$J:$J,'Doc Há Pagar | Rodopar 1015'!$A:$A,$B34&$E34&$F34,'Doc Há Pagar | Rodopar 1015'!$B:$B,X$1) -> 0 | Y34: =SUMIFS('Doc''s Pagos | Rodopar 108'!$J:$J,'Doc''s Pagos | Rodopar 108'!$A:$A,$B34&$E34&$F34&$J34,'Doc''s Pagos | Rodopar 108'!$B:$B,Y$1)+SUMIFS('Doc Há Pagar | Rodopar 1015'!$J:$J,'Doc Há Pagar | Rodopar 1015'!$A:$A,$B34&$E34&$F34,'Doc Há Pagar | Rodopar 1015'!$B:$B,Y$1) -> 0 | Z34: =SUMIFS('Doc''s Pagos | Rodopar 108'!$J:$J,'Doc''s Pagos | Rodopar 108'!$A:$A,$B34&$E34&$F34&$J34,'Doc''s Pagos | Rodopar 108'!$B:$B,Z$1)+SUMIFS('Doc Há Pagar | Rodopar 1015'!$J:$J,'Doc Há Pagar | Rodopar 1015'!$A:$A,$B34&$E34&$F34,'Doc Há Pagar | Rodopar 1015'!$B:$B,Z$1) -> 0 | ... AD34: =SUMIFS('Doc''s Pagos | Rodopar 108'!$J:$J,'Doc''s Pagos | Rodopar 108'!$A:$A,$B34&$E34&$F34&$J34,'Doc''s Pagos | Rodopar 108'!$B:$B,AD$1)+SUMIFS('Doc Há Pagar | Rodopar 1015'!$J:$J,'Doc Há Pagar | Rodopar 1015'!$A:$A,$B34&$E34&$F34,'Doc Há Pagar | Rodopar 1015'!$B:$B,AD$1) -> 0
A35: =VLOOKUP($E35,Fornecedores!$A:$C,3,0) -> Frota | B35: 64 | C35: =IFERROR(VLOOKUP($E35,Fornecedores!$A:$E,4,0),"") -> Sinistro | D35: =IFERROR(VLOOKUP($E35,Fornecedores!$A:$E,5,0),"") -> Guincho | E35: MYRELLE ALVES RIBEIRO | F35: NSE | G35: 34.872.658/0001-05 | H35: 87 | I35: 4800 | J35: 46043 | K35: 46044 | L35: UBERLANDIA | M35: MG | N35: 1556 | O35: GABRIEL.ALBINO | Q35: =SUM(R35:AD35)-I35 -> 0 | S35: =SUMIFS('Doc''s Pagos | Rodopar 108'!$J:$J,'Doc''s Pagos | Rodopar 108'!$A:$A,$B35&$E35&$F35&$J35,'Doc''s Pagos | Rodopar 108'!$B:$B,S$1)+SUMIFS('Doc Há Pagar | Rodopar 1015'!$J:$J,'Doc Há Pagar | Rodopar 1015'!$A:$A,$B35&$E35&$F35,'Doc Há Pagar | Rodopar 1015'!$B:$B,S$1) -> 4800 | T35: =SUMIFS('Doc''s Pagos | Rodopar 108'!$J:$J,'Doc''s Pagos | Rodopar 108'!$A:$A,$B35&$E35&$F35&$J35,'Doc''s Pagos | Rodopar 108'!$B:$B,T$1)+SUMIFS('Doc Há Pagar | Rodopar 1015'!$J:$J,'Doc Há Pagar | Rodopar 1015'!$A:$A,$B35&$E35&$F35,'Doc Há Pagar | Rodopar 1015'!$B:$B,T$1) -> 0 | U35: =SUMIFS('Doc''s Pagos | Rodopar 108'!$J:$J,'Doc''s Pagos | Rodopar 108'!$A:$A,$B35&$E35&$F35&$J35,'Doc''s Pagos | Rodopar 108'!$B:$B,U$1)+SUMIFS('Doc Há Pagar | Rodopar 1015'!$J:$J,'Doc Há Pagar | Rodopar 1015'!$A:$A,$B35&$E35&$F35,'Doc Há Pagar | Rodopar 1015'!$B:$B,U$1) -> 0 | V35: =SUMIFS('Doc''s Pagos | Rodopar 108'!$J:$J,'Doc''s Pagos | Rodopar 108'!$A:$A,$B35&$E35&$F35&$J35,'Doc''s Pagos | Rodopar 108'!$B:$B,V$1)+SUMIFS('Doc Há Pagar | Rodopar 1015'!$J:$J,'Doc Há Pagar | Rodopar 1015'!$A:$A,$B35&$E35&$F35,'Doc Há Pagar | Rodopar 1015'!$B:$B,V$1) -> 0 | W35: =SUMIFS('Doc''s Pagos | Rodopar 108'!$J:$J,'Doc''s Pagos | Rodopar 108'!$A:$A,$B35&$E35&$F35&$J35,'Doc''s Pagos | Rodopar 108'!$B:$B,W$1)+SUMIFS('Doc Há Pagar | Rodopar 1015'!$J:$J,'Doc Há Pagar | Rodopar 1015'!$A:$A,$B35&$E35&$F35,'Doc Há Pagar | Rodopar 1015'!$B:$B,W$1) -> 0 | X35: =SUMIFS('Doc''s Pagos | Rodopar 108'!$J:$J,'Doc''s Pagos | Rodopar 108'!$A:$A,$B35&$E35&$F35&$J35,'Doc''s Pagos | Rodopar 108'!$B:$B,X$1)+SUMIFS('Doc Há Pagar | Rodopar 1015'!$J:$J,'Doc Há Pagar | Rodopar 1015'!$A:$A,$B35&$E35&$F35,'Doc Há Pagar | Rodopar 1015'!$B:$B,X$1) -> 0 | Y35: =SUMIFS('Doc''s Pagos | Rodopar 108'!$J:$J,'Doc''s Pagos | Rodopar 108'!$A:$A,$B35&$E35&$F35&$J35,'Doc''s Pagos | Rodopar 108'!$B:$B,Y$1)+SUMIFS('Doc Há Pagar | Rodopar 1015'!$J:$J,'Doc Há Pagar | Rodopar 1015'!$A:$A,$B35&$E35&$F35,'Doc Há Pagar | Rodopar 1015'!$B:$B,Y$1) -> 0 | Z35: =SUMIFS('Doc''s Pagos | Rodopar 108'!$J:$J,'Doc''s Pagos | Rodopar 108'!$A:$A,$B35&$E35&$F35&$J35,'Doc''s Pagos | Rodopar 108'!$B:$B,Z$1)+SUMIFS('Doc Há Pagar | Rodopar 1015'!$J:$J,'Doc Há Pagar | Rodopar 1015'!$A:$A,$B35&$E35&$F35,'Doc Há Pagar | Rodopar 1015'!$B:$B,Z$1) -> 0 | ... AD35: =SUMIFS('Doc''s Pagos | Rodopar 108'!$J:$J,'Doc''s Pagos | Rodopar 108'!$A:$A,$B35&$E35&$F35&$J35,'Doc''s Pagos | Rodopar 108'!$B:$B,AD$1)+SUMIFS('Doc Há Pagar | Rodopar 1015'!$J:$J,'Doc Há Pagar | Rodopar 1015'!$A:$A,$B35&$E35&$F35,'Doc Há Pagar | Rodopar 1015'!$B:$B,AD$1) -> 0
A36: =VLOOKUP($E36,Fornecedores!$A:$C,3,0) -> Frota | B36: 2163849 | C36: =IFERROR(VLOOKUP($E36,Fornecedores!$A:$E,4,0),"") -> Manutenção | D36: =IFERROR(VLOOKUP($E36,Fornecedores!$A:$E,5,0),"") -> Peças E Serviços | E36: Cpx Distribuidora S.A. | F36: NFE | G36: 10.158.356/0001-01 | H36: 87 | I36: 9260.01 | J36: 46044 | K36: 46051 | L36: ITAJAI | M36: SC | N36: 2556 | O36: dayane.vicente | Q36: =SUM(R36:AD36)-I36 -> 0 | S36: =SUMIFS('Doc''s Pagos | Rodopar 108'!$J:$J,'Doc''s Pagos | Rodopar 108'!$A:$A,$B36&$E36&$F36&$J36,'Doc''s Pagos | Rodopar 108'!$B:$B,S$1)+SUMIFS('Doc Há Pagar | Rodopar 1015'!$J:$J,'Doc Há Pagar | Rodopar 1015'!$A:$A,$B36&$E36&$F36,'Doc Há Pagar | Rodopar 1015'!$B:$B,S$1) -> 0 | T36: =SUMIFS('Doc''s Pagos | Rodopar 108'!$J:$J,'Doc''s Pagos | Rodopar 108'!$A:$A,$B36&$E36&$F36&$J36,'Doc''s Pagos | Rodopar 108'!$B:$B,T$1)+SUMIFS('Doc Há Pagar | Rodopar 1015'!$J:$J,'Doc Há Pagar | Rodopar 1015'!$A:$A,$B36&$E36&$F36,'Doc Há Pagar | Rodopar 1015'!$B:$B,T$1) -> 1542.72 | U36: =SUMIFS('Doc''s Pagos | Rodopar 108'!$J:$J,'Doc''s Pagos | Rodopar 108'!$A:$A,$B36&$E36&$F36&$J36,'Doc''s Pagos | Rodopar 108'!$B:$B,U$1)+SUMIFS('Doc Há Pagar | Rodopar 1015'!$J:$J,'Doc Há Pagar | Rodopar 1015'!$A:$A,$B36&$E36&$F36,'Doc Há Pagar | Rodopar 1015'!$B:$B,U$1) -> 1542.72 | V36: =SUMIFS('Doc''s Pagos | Rodopar 108'!$J:$J,'Doc''s Pagos | Rodopar 108'!$A:$A,$B36&$E36&$F36&$J36,'Doc''s Pagos | Rodopar 108'!$B:$B,V$1)+SUMIFS('Doc Há Pagar | Rodopar 1015'!$J:$J,'Doc Há Pagar | Rodopar 1015'!$A:$A,$B36&$E36&$F36,'Doc Há Pagar | Rodopar 1015'!$B:$B,V$1) -> 1542.72 | W36: =SUMIFS('Doc''s Pagos | Rodopar 108'!$J:$J,'Doc''s Pagos | Rodopar 108'!$A:$A,$B36&$E36&$F36&$J36,'Doc''s Pagos | Rodopar 108'!$B:$B,W$1)+SUMIFS('Doc Há Pagar | Rodopar 1015'!$J:$J,'Doc Há Pagar | Rodopar 1015'!$A:$A,$B36&$E36&$F36,'Doc Há Pagar | Rodopar 1015'!$B:$B,W$1) -> 1542.72 | X36: =SUMIFS('Doc''s Pagos | Rodopar 108'!$J:$J,'Doc''s Pagos | Rodopar 108'!$A:$A,$B36&$E36&$F36&$J36,'Doc''s Pagos | Rodopar 108'!$B:$B,X$1)+SUMIFS('Doc Há Pagar | Rodopar 1015'!$J:$J,'Doc Há Pagar | Rodopar 1015'!$A:$A,$B36&$E36&$F36,'Doc Há Pagar | Rodopar 1015'!$B:$B,X$1) -> 1542.72 | Y36: =SUMIFS('Doc''s Pagos | Rodopar 108'!$J:$J,'Doc''s Pagos | Rodopar 108'!$A:$A,$B36&$E36&$F36&$J36,'Doc''s Pagos | Rodopar 108'!$B:$B,Y$1)+SUMIFS('Doc Há Pagar | Rodopar 1015'!$J:$J,'Doc Há Pagar | Rodopar 1015'!$A:$A,$B36&$E36&$F36,'Doc Há Pagar | Rodopar 1015'!$B:$B,Y$1) -> 1546.41 | Z36: =SUMIFS('Doc''s Pagos | Rodopar 108'!$J:$J,'Doc''s Pagos | Rodopar 108'!$A:$A,$B36&$E36&$F36&$J36,'Doc''s Pagos | Rodopar 108'!$B:$B,Z$1)+SUMIFS('Doc Há Pagar | Rodopar 1015'!$J:$J,'Doc Há Pagar | Rodopar 1015'!$A:$A,$B36&$E36&$F36,'Doc Há Pagar | Rodopar 1015'!$B:$B,Z$1) -> 0 | ... AD36: =SUMIFS('Doc''s Pagos | Rodopar 108'!$J:$J,'Doc''s Pagos | Rodopar 108'!$A:$A,$B36&$E36&$F36&$J36,'Doc''s Pagos | Rodopar 108'!$B:$B,AD$1)+SUMIFS('Doc Há Pagar | Rodopar 1015'!$J:$J,'Doc Há Pagar | Rodopar 1015'!$A:$A,$B36&$E36&$F36,'Doc Há Pagar | Rodopar 1015'!$B:$B,AD$1) -> 0
A37: =VLOOKUP($E37,Fornecedores!$A:$C,3,0) -> Frota | B37: 98 | C37: =IFERROR(VLOOKUP($E37,Fornecedores!$A:$E,4,0),"") -> Manutenção | D37: =IFERROR(VLOOKUP($E37,Fornecedores!$A:$E,5,0),"") -> Peças E Serviços | E37: ZAMBALDI AUTO CENTER LTDA | F37: NFE | G37: 55.012.105/0001-52 | H37: 87 | I37: 322 | J37: 46044 | K37: 46048 | L37: CONTAGEM | M37: MG | N37: 1556 | O37: GABRIEL.ALBINO | Q37: =SUM(R37:AD37)-I37 -> 0 | S37: =SUMIFS('Doc''s Pagos | Rodopar 108'!$J:$J,'Doc''s Pagos | Rodopar 108'!$A:$A,$B37&$E37&$F37&$J37,'Doc''s Pagos | Rodopar 108'!$B:$B,S$1)+SUMIFS('Doc Há Pagar | Rodopar 1015'!$J:$J,'Doc Há Pagar | Rodopar 1015'!$A:$A,$B37&$E37&$F37,'Doc Há Pagar | Rodopar 1015'!$B:$B,S$1) -> 0 | T37: =SUMIFS('Doc''s Pagos | Rodopar 108'!$J:$J,'Doc''s Pagos | Rodopar 108'!$A:$A,$B37&$E37&$F37&$J37,'Doc''s Pagos | Rodopar 108'!$B:$B,T$1)+SUMIFS('Doc Há Pagar | Rodopar 1015'!$J:$J,'Doc Há Pagar | Rodopar 1015'!$A:$A,$B37&$E37&$F37,'Doc Há Pagar | Rodopar 1015'!$B:$B,T$1) -> 322 | U37: =SUMIFS('Doc''s Pagos | Rodopar 108'!$J:$J,'Doc''s Pagos | Rodopar 108'!$A:$A,$B37&$E37&$F37&$J37,'Doc''s Pagos | Rodopar 108'!$B:$B,U$1)+SUMIFS('Doc Há Pagar | Rodopar 1015'!$J:$J,'Doc Há Pagar | Rodopar 1015'!$A:$A,$B37&$E37&$F37,'Doc Há Pagar | Rodopar 1015'!$B:$B,U$1) -> 0 | V37: =SUMIFS('Doc''s Pagos | Rodopar 108'!$J:$J,'Doc''s Pagos | Rodopar 108'!$A:$A,$B37&$E37&$F37&$J37,'Doc''s Pagos | Rodopar 108'!$B:$B,V$1)+SUMIFS('Doc Há Pagar | Rodopar 1015'!$J:$J,'Doc Há Pagar | Rodopar 1015'!$A:$A,$B37&$E37&$F37,'Doc Há Pagar | Rodopar 1015'!$B:$B,V$1) -> 0 | W37: =SUMIFS('Doc''s Pagos | Rodopar 108'!$J:$J,'Doc''s Pagos | Rodopar 108'!$A:$A,$B37&$E37&$F37&$J37,'Doc''s Pagos | Rodopar 108'!$B:$B,W$1)+SUMIFS('Doc Há Pagar | Rodopar 1015'!$J:$J,'Doc Há Pagar | Rodopar 1015'!$A:$A,$B37&$E37&$F37,'Doc Há Pagar | Rodopar 1015'!$B:$B,W$1) -> 0 | X37: =SUMIFS('Doc''s Pagos | Rodopar 108'!$J:$J,'Doc''s Pagos | Rodopar 108'!$A:$A,$B37&$E37&$F37&$J37,'Doc''s Pagos | Rodopar 108'!$B:$B,X$1)+SUMIFS('Doc Há Pagar | Rodopar 1015'!$J:$J,'Doc Há Pagar | Rodopar 1015'!$A:$A,$B37&$E37&$F37,'Doc Há Pagar | Rodopar 1015'!$B:$B,X$1) -> 0 | Y37: =SUMIFS('Doc''s Pagos | Rodopar 108'!$J:$J,'Doc''s Pagos | Rodopar 108'!$A:$A,$B37&$E37&$F37&$J37,'Doc''s Pagos | Rodopar 108'!$B:$B,Y$1)+SUMIFS('Doc Há Pagar | Rodopar 1015'!$J:$J,'Doc Há Pagar | Rodopar 1015'!$A:$A,$B37&$E37&$F37,'Doc Há Pagar | Rodopar 1015'!$B:$B,Y$1) -> 0 | Z37: =SUMIFS('Doc''s Pagos | Rodopar 108'!$J:$J,'Doc''s Pagos | Rodopar 108'!$A:$A,$B37&$E37&$F37&$J37,'Doc''s Pagos | Rodopar 108'!$B:$B,Z$1)+SUMIFS('Doc Há Pagar | Rodopar 1015'!$J:$J,'Doc Há Pagar | Rodopar 1015'!$A:$A,$B37&$E37&$F37,'Doc Há Pagar | Rodopar 1015'!$B:$B,Z$1) -> 0 | ... AD37: =SUMIFS('Doc''s Pagos | Rodopar 108'!$J:$J,'Doc''s Pagos | Rodopar 108'!$A:$A,$B37&$E37&$F37&$J37,'Doc''s Pagos | Rodopar 108'!$B:$B,AD$1)+SUMIFS('Doc Há Pagar | Rodopar 1015'!$J:$J,'Doc Há Pagar | Rodopar 1015'!$A:$A,$B37&$E37&$F37,'Doc Há Pagar | Rodopar 1015'!$B:$B,AD$1) -> 0
A38: =VLOOKUP($E38,Fornecedores!$A:$C,3,0) -> Frota | B38: 19 | C38: =IFERROR(VLOOKUP($E38,Fornecedores!$A:$E,4,0),"") -> Manutenção | D38: =IFERROR(VLOOKUP($E38,Fornecedores!$A:$E,5,0),"") -> Peças E Serviços | E38: ZAMBALDI AUTO CENTER LTDA | F38: NSE | G38: 55.012.105/0001-52 | H38: 87 | I38: 120 | J38: 46044 | K38: 46048 | L38: CONTAGEM | M38: MG | N38: 1556 | O38: GABRIEL.ALBINO | Q38: =SUM(R38:AD38)-I38 -> 0 | S38: =SUMIFS('Doc''s Pagos | Rodopar 108'!$J:$J,'Doc''s Pagos | Rodopar 108'!$A:$A,$B38&$E38&$F38&$J38,'Doc''s Pagos | Rodopar 108'!$B:$B,S$1)+SUMIFS('Doc Há Pagar | Rodopar 1015'!$J:$J,'Doc Há Pagar | Rodopar 1015'!$A:$A,$B38&$E38&$F38,'Doc Há Pagar | Rodopar 1015'!$B:$B,S$1) -> 0 | T38: =SUMIFS('Doc''s Pagos | Rodopar 108'!$J:$J,'Doc''s Pagos | Rodopar 108'!$A:$A,$B38&$E38&$F38&$J38,'Doc''s Pagos | Rodopar 108'!$B:$B,T$1)+SUMIFS('Doc Há Pagar | Rodopar 1015'!$J:$J,'Doc Há Pagar | Rodopar 1015'!$A:$A,$B38&$E38&$F38,'Doc Há Pagar | Rodopar 1015'!$B:$B,T$1) -> 120 | U38: =SUMIFS('Doc''s Pagos | Rodopar 108'!$J:$J,'Doc''s Pagos | Rodopar 108'!$A:$A,$B38&$E38&$F38&$J38,'Doc''s Pagos | Rodopar 108'!$B:$B,U$1)+SUMIFS('Doc Há Pagar | Rodopar 1015'!$J:$J,'Doc Há Pagar | Rodopar 1015'!$A:$A,$B38&$E38&$F38,'Doc Há Pagar | Rodopar 1015'!$B:$B,U$1) -> 0 | V38: =SUMIFS('Doc''s Pagos | Rodopar 108'!$J:$J,'Doc''s Pagos | Rodopar 108'!$A:$A,$B38&$E38&$F38&$J38,'Doc''s Pagos | Rodopar 108'!$B:$B,V$1)+SUMIFS('Doc Há Pagar | Rodopar 1015'!$J:$J,'Doc Há Pagar | Rodopar 1015'!$A:$A,$B38&$E38&$F38,'Doc Há Pagar | Rodopar 1015'!$B:$B,V$1) -> 0 | W38: =SUMIFS('Doc''s Pagos | Rodopar 108'!$J:$J,'Doc''s Pagos | Rodopar 108'!$A:$A,$B38&$E38&$F38&$J38,'Doc''s Pagos | Rodopar 108'!$B:$B,W$1)+SUMIFS('Doc Há Pagar | Rodopar 1015'!$J:$J,'Doc Há Pagar | Rodopar 1015'!$A:$A,$B38&$E38&$F38,'Doc Há Pagar | Rodopar 1015'!$B:$B,W$1) -> 0 | X38: =SUMIFS('Doc''s Pagos | Rodopar 108'!$J:$J,'Doc''s Pagos | Rodopar 108'!$A:$A,$B38&$E38&$F38&$J38,'Doc''s Pagos | Rodopar 108'!$B:$B,X$1)+SUMIFS('Doc Há Pagar | Rodopar 1015'!$J:$J,'Doc Há Pagar | Rodopar 1015'!$A:$A,$B38&$E38&$F38,'Doc Há Pagar | Rodopar 1015'!$B:$B,X$1) -> 0 | Y38: =SUMIFS('Doc''s Pagos | Rodopar 108'!$J:$J,'Doc''s Pagos | Rodopar 108'!$A:$A,$B38&$E38&$F38&$J38,'Doc''s Pagos | Rodopar 108'!$B:$B,Y$1)+SUMIFS('Doc Há Pagar | Rodopar 1015'!$J:$J,'Doc Há Pagar | Rodopar 1015'!$A:$A,$B38&$E38&$F38,'Doc Há Pagar | Rodopar 1015'!$B:$B,Y$1) -> 0 | Z38: =SUMIFS('Doc''s Pagos | Rodopar 108'!$J:$J,'Doc''s Pagos | Rodopar 108'!$A:$A,$B38&$E38&$F38&$J38,'Doc''s Pagos | Rodopar 108'!$B:$B,Z$1)+SUMIFS('Doc Há Pagar | Rodopar 1015'!$J:$J,'Doc Há Pagar | Rodopar 1015'!$A:$A,$B38&$E38&$F38,'Doc Há Pagar | Rodopar 1015'!$B:$B,Z$1) -> 0 | ... AD38: =SUMIFS('Doc''s Pagos | Rodopar 108'!$J:$J,'Doc''s Pagos | Rodopar 108'!$A:$A,$B38&$E38&$F38&$J38,'Doc''s Pagos | Rodopar 108'!$B:$B,AD$1)+SUMIFS('Doc Há Pagar | Rodopar 1015'!$J:$J,'Doc Há Pagar | Rodopar 1015'!$A:$A,$B38&$E38&$F38,'Doc Há Pagar | Rodopar 1015'!$B:$B,AD$1) -> 0
A39: =VLOOKUP($E39,Fornecedores!$A:$C,3,0) -> Frota | B39: 996217 | C39: =IFERROR(VLOOKUP($E39,Fornecedores!$A:$E,4,0),"") -> Manutenção | D39: =IFERROR(VLOOKUP($E39,Fornecedores!$A:$E,5,0),"") -> Caminhão | E39: TREVISO BETIM VEICULOS LTDA | F39: NFE | G39: 21.014.220/0001-44 | H39: 87 | I39: 1748.52 | J39: 46048 | K39: 46051 | L39: BETIM | M39: MG | N39: 1556 | O39: GABRIEL.ALBINO | Q39: =SUM(R39:AD39)-I39 -> 0 | S39: =SUMIFS('Doc''s Pagos | Rodopar 108'!$J:$J,'Doc''s Pagos | Rodopar 108'!$A:$A,$B39&$E39&$F39&$J39,'Doc''s Pagos | Rodopar 108'!$B:$B,S$1)+SUMIFS('Doc Há Pagar | Rodopar 1015'!$J:$J,'Doc Há Pagar | Rodopar 1015'!$A:$A,$B39&$E39&$F39,'Doc Há Pagar | Rodopar 1015'!$B:$B,S$1) -> 0 | T39: =SUMIFS('Doc''s Pagos | Rodopar 108'!$J:$J,'Doc''s Pagos | Rodopar 108'!$A:$A,$B39&$E39&$F39&$J39,'Doc''s Pagos | Rodopar 108'!$B:$B,T$1)+SUMIFS('Doc Há Pagar | Rodopar 1015'!$J:$J,'Doc Há Pagar | Rodopar 1015'!$A:$A,$B39&$E39&$F39,'Doc Há Pagar | Rodopar 1015'!$B:$B,T$1) -> 1748.52 | U39: =SUMIFS('Doc''s Pagos | Rodopar 108'!$J:$J,'Doc''s Pagos | Rodopar 108'!$A:$A,$B39&$E39&$F39&$J39,'Doc''s Pagos | Rodopar 108'!$B:$B,U$1)+SUMIFS('Doc Há Pagar | Rodopar 1015'!$J:$J,'Doc Há Pagar | Rodopar 1015'!$A:$A,$B39&$E39&$F39,'Doc Há Pagar | Rodopar 1015'!$B:$B,U$1) -> 0 | V39: =SUMIFS('Doc''s Pagos | Rodopar 108'!$J:$J,'Doc''s Pagos | Rodopar 108'!$A:$A,$B39&$E39&$F39&$J39,'Doc''s Pagos | Rodopar 108'!$B:$B,V$1)+SUMIFS('Doc Há Pagar | Rodopar 1015'!$J:$J,'Doc Há Pagar | Rodopar 1015'!$A:$A,$B39&$E39&$F39,'Doc Há Pagar | Rodopar 1015'!$B:$B,V$1) -> 0 | W39: =SUMIFS('Doc''s Pagos | Rodopar 108'!$J:$J,'Doc''s Pagos | Rodopar 108'!$A:$A,$B39&$E39&$F39&$J39,'Doc''s Pagos | Rodopar 108'!$B:$B,W$1)+SUMIFS('Doc Há Pagar | Rodopar 1015'!$J:$J,'Doc Há Pagar | Rodopar 1015'!$A:$A,$B39&$E39&$F39,'Doc Há Pagar | Rodopar 1015'!$B:$B,W$1) -> 0 | X39: =SUMIFS('Doc''s Pagos | Rodopar 108'!$J:$J,'Doc''s Pagos | Rodopar 108'!$A:$A,$B39&$E39&$F39&$J39,'Doc''s Pagos | Rodopar 108'!$B:$B,X$1)+SUMIFS('Doc Há Pagar | Rodopar 1015'!$J:$J,'Doc Há Pagar | Rodopar 1015'!$A:$A,$B39&$E39&$F39,'Doc Há Pagar | Rodopar 1015'!$B:$B,X$1) -> 0 | Y39: =SUMIFS('Doc''s Pagos | Rodopar 108'!$J:$J,'Doc''s Pagos | Rodopar 108'!$A:$A,$B39&$E39&$F39&$J39,'Doc''s Pagos | Rodopar 108'!$B:$B,Y$1)+SUMIFS('Doc Há Pagar | Rodopar 1015'!$J:$J,'Doc Há Pagar | Rodopar 1015'!$A:$A,$B39&$E39&$F39,'Doc Há Pagar | Rodopar 1015'!$B:$B,Y$1) -> 0 | Z39: =SUMIFS('Doc''s Pagos | Rodopar 108'!$J:$J,'Doc''s Pagos | Rodopar 108'!$A:$A,$B39&$E39&$F39&$J39,'Doc''s Pagos | Rodopar 108'!$B:$B,Z$1)+SUMIFS('Doc Há Pagar | Rodopar 1015'!$J:$J,'Doc Há Pagar | Rodopar 1015'!$A:$A,$B39&$E39&$F39,'Doc Há Pagar | Rodopar 1015'!$B:$B,Z$1) -> 0 | ... AD39: =SUMIFS('Doc''s Pagos | Rodopar 108'!$J:$J,'Doc''s Pagos | Rodopar 108'!$A:$A,$B39&$E39&$F39&$J39,'Doc''s Pagos | Rodopar 108'!$B:$B,AD$1)+SUMIFS('Doc Há Pagar | Rodopar 1015'!$J:$J,'Doc Há Pagar | Rodopar 1015'!$A:$A,$B39&$E39&$F39,'Doc Há Pagar | Rodopar 1015'!$B:$B,AD$1) -> 0
... A67: =VLOOKUP($E67,Fornecedores!$A:$C,3,0) -> Frota | B67: 368 | C67: =IFERROR(VLOOKUP($E67,Fornecedores!$A:$E,4,0),"") -> Sinistro | D67: =IFERROR(VLOOKUP($E67,Fornecedores!$A:$E,5,0),"") -> Lanternagem | E67: EXXCELENCIA CONSULTORIA EM SOLUCOES EMPRESARIAIS LTDA | F67: NSE | G67: 13.937.011/0001-44 | H67: 87 | I67: 3150 | J67: 46065 | K67: 46065 | L67: BELO HORIZONTE | M67: MG | N67: 1556 | O67: RAYANE.AMORIM | Q67: =SUM(R67:AD67)-I67 -> 0 | S67: =SUMIFS('Doc''s Pagos | Rodopar 108'!$J:$J,'Doc''s Pagos | Rodopar 108'!$A:$A,$B67&$E67&$F67&$J67,'Doc''s Pagos | Rodopar 108'!$B:$B,S$1)+SUMIFS('Doc Há Pagar | Rodopar 1015'!$J:$J,'Doc Há Pagar | Rodopar 1015'!$A:$A,$B67&$E67&$F67,'Doc Há Pagar | Rodopar 1015'!$B:$B,S$1) -> 0 | T67: =SUMIFS('Doc''s Pagos | Rodopar 108'!$J:$J,'Doc''s Pagos | Rodopar 108'!$A:$A,$B67&$E67&$F67&$J67,'Doc''s Pagos | Rodopar 108'!$B:$B,T$1)+SUMIFS('Doc Há Pagar | Rodopar 1015'!$J:$J,'Doc Há Pagar | Rodopar 1015'!$A:$A,$B67&$E67&$F67,'Doc Há Pagar | Rodopar 1015'!$B:$B,T$1) -> 0 | U67: =SUMIFS('Doc''s Pagos | Rodopar 108'!$J:$J,'Doc''s Pagos | Rodopar 108'!$A:$A,$B67&$E67&$F67&$J67,'Doc''s Pagos | Rodopar 108'!$B:$B,U$1)+SUMIFS('Doc Há Pagar | Rodopar 1015'!$J:$J,'Doc Há Pagar | Rodopar 1015'!$A:$A,$B67&$E67&$F67,'Doc Há Pagar | Rodopar 1015'!$B:$B,U$1) -> 3150 | V67: =SUMIFS('Doc''s Pagos | Rodopar 108'!$J:$J,'Doc''s Pagos | Rodopar 108'!$A:$A,$B67&$E67&$F67&$J67,'Doc''s Pagos | Rodopar 108'!$B:$B,V$1)+SUMIFS('Doc Há Pagar | Rodopar 1015'!$J:$J,'Doc Há Pagar | Rodopar 1015'!$A:$A,$B67&$E67&$F67,'Doc Há Pagar | Rodopar 1015'!$B:$B,V$1) -> 0 | W67: =SUMIFS('Doc''s Pagos | Rodopar 108'!$J:$J,'Doc''s Pagos | Rodopar 108'!$A:$A,$B67&$E67&$F67&$J67,'Doc''s Pagos | Rodopar 108'!$B:$B,W$1)+SUMIFS('Doc Há Pagar | Rodopar 1015'!$J:$J,'Doc Há Pagar | Rodopar 1015'!$A:$A,$B67&$E67&$F67,'Doc Há Pagar | Rodopar 1015'!$B:$B,W$1) -> 0 | X67: =SUMIFS('Doc''s Pagos | Rodopar 108'!$J:$J,'Doc''s Pagos | Rodopar 108'!$A:$A,$B67&$E67&$F67&$J67,'Doc''s Pagos | Rodopar 108'!$B:$B,X$1)+SUMIFS('Doc Há Pagar | Rodopar 1015'!$J:$J,'Doc Há Pagar | Rodopar 1015'!$A:$A,$B67&$E67&$F67,'Doc Há Pagar | Rodopar 1015'!$B:$B,X$1) -> 0 | Y67: =SUMIFS('Doc''s Pagos | Rodopar 108'!$J:$J,'Doc''s Pagos | Rodopar 108'!$A:$A,$B67&$E67&$F67&$J67,'Doc''s Pagos | Rodopar 108'!$B:$B,Y$1)+SUMIFS('Doc Há Pagar | Rodopar 1015'!$J:$J,'Doc Há Pagar | Rodopar 1015'!$A:$A,$B67&$E67&$F67,'Doc Há Pagar | Rodopar 1015'!$B:$B,Y$1) -> 0 | Z67: =SUMIFS('Doc''s Pagos | Rodopar 108'!$J:$J,'Doc''s Pagos | Rodopar 108'!$A:$A,$B67&$E67&$F67&$J67,'Doc''s Pagos | Rodopar 108'!$B:$B,Z$1)+SUMIFS('Doc Há Pagar | Rodopar 1015'!$J:$J,'Doc Há Pagar | Rodopar 1015'!$A:$A,$B67&$E67&$F67,'Doc Há Pagar | Rodopar 1015'!$B:$B,Z$1) -> 0 | ... AD67: =SUMIFS('Doc''s Pagos | Rodopar 108'!$J:$J,'Doc''s Pagos | Rodopar 108'!$A:$A,$B67&$E67&$F67&$J67,'Doc''s Pagos | Rodopar 108'!$B:$B,AD$1)+SUMIFS('Doc Há Pagar | Rodopar 1015'!$J:$J,'Doc Há Pagar | Rodopar 1015'!$A:$A,$B67&$E67&$F67,'Doc Há Pagar | Rodopar 1015'!$B:$B,AD$1) -> 0
A68: =VLOOKUP($E68,Fornecedores!$A:$C,3,0) -> Frota | B68: AFMTZ-3075578 | C68: =IFERROR(VLOOKUP($E68,Fornecedores!$A:$E,4,0),"") -> OPE Merchandising | D68: =IFERROR(VLOOKUP($E68,Fornecedores!$A:$E,5,0),"") -> Locação | E68: LOCALIZA FLEET S/A | F68: FT | G68: 02.286.479/0001-08 | H68: 87 | I68: 38471.3 | J68: 46066 | K68: 46072 | L68: BELO HORIZONTE | M68: MG | N68: 1556 | O68: GABRIEL.ALBINO | Q68: =SUM(R68:AD68)-I68 -> 0 | S68: =SUMIFS('Doc''s Pagos | Rodopar 108'!$J:$J,'Doc''s Pagos | Rodopar 108'!$A:$A,$B68&$E68&$F68&$J68,'Doc''s Pagos | Rodopar 108'!$B:$B,S$1)+SUMIFS('Doc Há Pagar | Rodopar 1015'!$J:$J,'Doc Há Pagar | Rodopar 1015'!$A:$A,$B68&$E68&$F68,'Doc Há Pagar | Rodopar 1015'!$B:$B,S$1) -> 0 | T68: =SUMIFS('Doc''s Pagos | Rodopar 108'!$J:$J,'Doc''s Pagos | Rodopar 108'!$A:$A,$B68&$E68&$F68&$J68,'Doc''s Pagos | Rodopar 108'!$B:$B,T$1)+SUMIFS('Doc Há Pagar | Rodopar 1015'!$J:$J,'Doc Há Pagar | Rodopar 1015'!$A:$A,$B68&$E68&$F68,'Doc Há Pagar | Rodopar 1015'!$B:$B,T$1) -> 38471.3 | U68: =SUMIFS('Doc''s Pagos | Rodopar 108'!$J:$J,'Doc''s Pagos | Rodopar 108'!$A:$A,$B68&$E68&$F68&$J68,'Doc''s Pagos | Rodopar 108'!$B:$B,U$1)+SUMIFS('Doc Há Pagar | Rodopar 1015'!$J:$J,'Doc Há Pagar | Rodopar 1015'!$A:$A,$B68&$E68&$F68,'Doc Há Pagar | Rodopar 1015'!$B:$B,U$1) -> 0 | V68: =SUMIFS('Doc''s Pagos | Rodopar 108'!$J:$J,'Doc''s Pagos | Rodopar 108'!$A:$A,$B68&$E68&$F68&$J68,'Doc''s Pagos | Rodopar 108'!$B:$B,V$1)+SUMIFS('Doc Há Pagar | Rodopar 1015'!$J:$J,'Doc Há Pagar | Rodopar 1015'!$A:$A,$B68&$E68&$F68,'Doc Há Pagar | Rodopar 1015'!$B:$B,V$1) -> 0 | W68: =SUMIFS('Doc''s Pagos | Rodopar 108'!$J:$J,'Doc''s Pagos | Rodopar 108'!$A:$A,$B68&$E68&$F68&$J68,'Doc''s Pagos | Rodopar 108'!$B:$B,W$1)+SUMIFS('Doc Há Pagar | Rodopar 1015'!$J:$J,'Doc Há Pagar | Rodopar 1015'!$A:$A,$B68&$E68&$F68,'Doc Há Pagar | Rodopar 1015'!$B:$B,W$1) -> 0 | X68: =SUMIFS('Doc''s Pagos | Rodopar 108'!$J:$J,'Doc''s Pagos | Rodopar 108'!$A:$A,$B68&$E68&$F68&$J68,'Doc''s Pagos | Rodopar 108'!$B:$B,X$1)+SUMIFS('Doc Há Pagar | Rodopar 1015'!$J:$J,'Doc Há Pagar | Rodopar 1015'!$A:$A,$B68&$E68&$F68,'Doc Há Pagar | Rodopar 1015'!$B:$B,X$1) -> 0 | Y68: =SUMIFS('Doc''s Pagos | Rodopar 108'!$J:$J,'Doc''s Pagos | Rodopar 108'!$A:$A,$B68&$E68&$F68&$J68,'Doc''s Pagos | Rodopar 108'!$B:$B,Y$1)+SUMIFS('Doc Há Pagar | Rodopar 1015'!$J:$J,'Doc Há Pagar | Rodopar 1015'!$A:$A,$B68&$E68&$F68,'Doc Há Pagar | Rodopar 1015'!$B:$B,Y$1) -> 0 | Z68: =SUMIFS('Doc''s Pagos | Rodopar 108'!$J:$J,'Doc''s Pagos | Rodopar 108'!$A:$A,$B68&$E68&$F68&$J68,'Doc''s Pagos | Rodopar 108'!$B:$B,Z$1)+SUMIFS('Doc Há Pagar | Rodopar 1015'!$J:$J,'Doc Há Pagar | Rodopar 1015'!$A:$A,$B68&$E68&$F68,'Doc Há Pagar | Rodopar 1015'!$B:$B,Z$1) -> 0 | ... AD68: =SUMIFS('Doc''s Pagos | Rodopar 108'!$J:$J,'Doc''s Pagos | Rodopar 108'!$A:$A,$B68&$E68&$F68&$J68,'Doc''s Pagos | Rodopar 108'!$B:$B,AD$1)+SUMIFS('Doc Há Pagar | Rodopar 1015'!$J:$J,'Doc Há Pagar | Rodopar 1015'!$A:$A,$B68&$E68&$F68,'Doc Há Pagar | Rodopar 1015'!$B:$B,AD$1) -> 0
A69: =VLOOKUP($E69,Fornecedores!$A:$C,3,0) -> Frota | B69: AFMTZ-3076696 | C69: =IFERROR(VLOOKUP($E69,Fornecedores!$A:$E,4,0),"") -> OPE Merchandising | D69: =IFERROR(VLOOKUP($E69,Fornecedores!$A:$E,5,0),"") -> Locação | E69: LOCALIZA FLEET S/A | F69: FT | G69: 02.286.479/0001-08 | H69: 87 | I69: 5151 | J69: 46066 | K69: 46072 | L69: BELO HORIZONTE | M69: MG | N69: 1556 | O69: GABRIEL.ALBINO | Q69: =SUM(R69:AD69)-I69 -> 0 | S69: =SUMIFS('Doc''s Pagos | Rodopar 108'!$J:$J,'Doc''s Pagos | Rodopar 108'!$A:$A,$B69&$E69&$F69&$J69,'Doc''s Pagos | Rodopar 108'!$B:$B,S$1)+SUMIFS('Doc Há Pagar | Rodopar 1015'!$J:$J,'Doc Há Pagar | Rodopar 1015'!$A:$A,$B69&$E69&$F69,'Doc Há Pagar | Rodopar 1015'!$B:$B,S$1) -> 0 | T69: =SUMIFS('Doc''s Pagos | Rodopar 108'!$J:$J,'Doc''s Pagos | Rodopar 108'!$A:$A,$B69&$E69&$F69&$J69,'Doc''s Pagos | Rodopar 108'!$B:$B,T$1)+SUMIFS('Doc Há Pagar | Rodopar 1015'!$J:$J,'Doc Há Pagar | Rodopar 1015'!$A:$A,$B69&$E69&$F69,'Doc Há Pagar | Rodopar 1015'!$B:$B,T$1) -> 5151 | U69: =SUMIFS('Doc''s Pagos | Rodopar 108'!$J:$J,'Doc''s Pagos | Rodopar 108'!$A:$A,$B69&$E69&$F69&$J69,'Doc''s Pagos | Rodopar 108'!$B:$B,U$1)+SUMIFS('Doc Há Pagar | Rodopar 1015'!$J:$J,'Doc Há Pagar | Rodopar 1015'!$A:$A,$B69&$E69&$F69,'Doc Há Pagar | Rodopar 1015'!$B:$B,U$1) -> 0 | V69: =SUMIFS('Doc''s Pagos | Rodopar 108'!$J:$J,'Doc''s Pagos | Rodopar 108'!$A:$A,$B69&$E69&$F69&$J69,'Doc''s Pagos | Rodopar 108'!$B:$B,V$1)+SUMIFS('Doc Há Pagar | Rodopar 1015'!$J:$J,'Doc Há Pagar | Rodopar 1015'!$A:$A,$B69&$E69&$F69,'Doc Há Pagar | Rodopar 1015'!$B:$B,V$1) -> 0 | W69: =SUMIFS('Doc''s Pagos | Rodopar 108'!$J:$J,'Doc''s Pagos | Rodopar 108'!$A:$A,$B69&$E69&$F69&$J69,'Doc''s Pagos | Rodopar 108'!$B:$B,W$1)+SUMIFS('Doc Há Pagar | Rodopar 1015'!$J:$J,'Doc Há Pagar | Rodopar 1015'!$A:$A,$B69&$E69&$F69,'Doc Há Pagar | Rodopar 1015'!$B:$B,W$1) -> 0 | X69: =SUMIFS('Doc''s Pagos | Rodopar 108'!$J:$J,'Doc''s Pagos | Rodopar 108'!$A:$A,$B69&$E69&$F69&$J69,'Doc''s Pagos | Rodopar 108'!$B:$B,X$1)+SUMIFS('Doc Há Pagar | Rodopar 1015'!$J:$J,'Doc Há Pagar | Rodopar 1015'!$A:$A,$B69&$E69&$F69,'Doc Há Pagar | Rodopar 1015'!$B:$B,X$1) -> 0 | Y69: =SUMIFS('Doc''s Pagos | Rodopar 108'!$J:$J,'Doc''s Pagos | Rodopar 108'!$A:$A,$B69&$E69&$F69&$J69,'Doc''s Pagos | Rodopar 108'!$B:$B,Y$1)+SUMIFS('Doc Há Pagar | Rodopar 1015'!$J:$J,'Doc Há Pagar | Rodopar 1015'!$A:$A,$B69&$E69&$F69,'Doc Há Pagar | Rodopar 1015'!$B:$B,Y$1) -> 0 | Z69: =SUMIFS('Doc''s Pagos | Rodopar 108'!$J:$J,'Doc''s Pagos | Rodopar 108'!$A:$A,$B69&$E69&$F69&$J69,'Doc''s Pagos | Rodopar 108'!$B:$B,Z$1)+SUMIFS('Doc Há Pagar | Rodopar 1015'!$J:$J,'Doc Há Pagar | Rodopar 1015'!$A:$A,$B69&$E69&$F69,'Doc Há Pagar | Rodopar 1015'!$B:$B,Z$1) -> 0 | ... AD69: =SUMIFS('Doc''s Pagos | Rodopar 108'!$J:$J,'Doc''s Pagos | Rodopar 108'!$A:$A,$B69&$E69&$F69&$J69,'Doc''s Pagos | Rodopar 108'!$B:$B,AD$1)+SUMIFS('Doc Há Pagar | Rodopar 1015'!$J:$J,'Doc Há Pagar | Rodopar 1015'!$A:$A,$B69&$E69&$F69,'Doc Há Pagar | Rodopar 1015'!$B:$B,AD$1) -> 0
A70: =VLOOKUP($E70,Fornecedores!$A:$C,3,0) -> Frota | B70: AGMTZ-3004225 | C70: =IFERROR(VLOOKUP($E70,Fornecedores!$A:$E,4,0),"") -> OPE Merchandising | D70: =IFERROR(VLOOKUP($E70,Fornecedores!$A:$E,5,0),"") -> Locação | E70: LOCALIZA FLEET S/A | F70: FT | G70: 02.286.479/0001-08 | H70: 87 | I70: 191.18 | J70: 46066 | K70: 46072 | L70: BELO HORIZONTE | M70: MG | N70: 1556 | O70: GABRIEL.ALBINO | Q70: =SUM(R70:AD70)-I70 -> 0 | S70: =SUMIFS('Doc''s Pagos | Rodopar 108'!$J:$J,'Doc''s Pagos | Rodopar 108'!$A:$A,$B70&$E70&$F70&$J70,'Doc''s Pagos | Rodopar 108'!$B:$B,S$1)+SUMIFS('Doc Há Pagar | Rodopar 1015'!$J:$J,'Doc Há Pagar | Rodopar 1015'!$A:$A,$B70&$E70&$F70,'Doc Há Pagar | Rodopar 1015'!$B:$B,S$1) -> 0 | T70: =SUMIFS('Doc''s Pagos | Rodopar 108'!$J:$J,'Doc''s Pagos | Rodopar 108'!$A:$A,$B70&$E70&$F70&$J70,'Doc''s Pagos | Rodopar 108'!$B:$B,T$1)+SUMIFS('Doc Há Pagar | Rodopar 1015'!$J:$J,'Doc Há Pagar | Rodopar 1015'!$A:$A,$B70&$E70&$F70,'Doc Há Pagar | Rodopar 1015'!$B:$B,T$1) -> 0 | U70: =SUMIFS('Doc''s Pagos | Rodopar 108'!$J:$J,'Doc''s Pagos | Rodopar 108'!$A:$A,$B70&$E70&$F70&$J70,'Doc''s Pagos | Rodopar 108'!$B:$B,U$1)+SUMIFS('Doc Há Pagar | Rodopar 1015'!$J:$J,'Doc Há Pagar | Rodopar 1015'!$A:$A,$B70&$E70&$F70,'Doc Há Pagar | Rodopar 1015'!$B:$B,U$1) -> 191.18 | V70: =SUMIFS('Doc''s Pagos | Rodopar 108'!$J:$J,'Doc''s Pagos | Rodopar 108'!$A:$A,$B70&$E70&$F70&$J70,'Doc''s Pagos | Rodopar 108'!$B:$B,V$1)+SUMIFS('Doc Há Pagar | Rodopar 1015'!$J:$J,'Doc Há Pagar | Rodopar 1015'!$A:$A,$B70&$E70&$F70,'Doc Há Pagar | Rodopar 1015'!$B:$B,V$1) -> 0 | W70: =SUMIFS('Doc''s Pagos | Rodopar 108'!$J:$J,'Doc''s Pagos | Rodopar 108'!$A:$A,$B70&$E70&$F70&$J70,'Doc''s Pagos | Rodopar 108'!$B:$B,W$1)+SUMIFS('Doc Há Pagar | Rodopar 1015'!$J:$J,'Doc Há Pagar | Rodopar 1015'!$A:$A,$B70&$E70&$F70,'Doc Há Pagar | Rodopar 1015'!$B:$B,W$1) -> 0 | X70: =SUMIFS('Doc''s Pagos | Rodopar 108'!$J:$J,'Doc''s Pagos | Rodopar 108'!$A:$A,$B70&$E70&$F70&$J70,'Doc''s Pagos | Rodopar 108'!$B:$B,X$1)+SUMIFS('Doc Há Pagar | Rodopar 1015'!$J:$J,'Doc Há Pagar | Rodopar 1015'!$A:$A,$B70&$E70&$F70,'Doc Há Pagar | Rodopar 1015'!$B:$B,X$1) -> 0 | Y70: =SUMIFS('Doc''s Pagos | Rodopar 108'!$J:$J,'Doc''s Pagos | Rodopar 108'!$A:$A,$B70&$E70&$F70&$J70,'Doc''s Pagos | Rodopar 108'!$B:$B,Y$1)+SUMIFS('Doc Há Pagar | Rodopar 1015'!$J:$J,'Doc Há Pagar | Rodopar 1015'!$A:$A,$B70&$E70&$F70,'Doc Há Pagar | Rodopar 1015'!$B:$B,Y$1) -> 0 | Z70: =SUMIFS('Doc''s Pagos | Rodopar 108'!$J:$J,'Doc''s Pagos | Rodopar 108'!$A:$A,$B70&$E70&$F70&$J70,'Doc''s Pagos | Rodopar 108'!$B:$B,Z$1)+SUMIFS('Doc Há Pagar | Rodopar 1015'!$J:$J,'Doc Há Pagar | Rodopar 1015'!$A:$A,$B70&$E70&$F70,'Doc Há Pagar | Rodopar 1015'!$B:$B,Z$1) -> 0 | ... AD70: =SUMIFS('Doc''s Pagos | Rodopar 108'!$J:$J,'Doc''s Pagos | Rodopar 108'!$A:$A,$B70&$E70&$F70&$J70,'Doc''s Pagos | Rodopar 108'!$B:$B,AD$1)+SUMIFS('Doc Há Pagar | Rodopar 1015'!$J:$J,'Doc Há Pagar | Rodopar 1015'!$A:$A,$B70&$E70&$F70,'Doc Há Pagar | Rodopar 1015'!$B:$B,AD$1) -> 0
A71: =VLOOKUP($E71,Fornecedores!$A:$C,3,0) -> Frota | B71: AGMTZ-3006710 | C71: =IFERROR(VLOOKUP($E71,Fornecedores!$A:$E,4,0),"") -> OPE Merchandising | D71: =IFERROR(VLOOKUP($E71,Fornecedores!$A:$E,5,0),"") -> Locação | E71: LOCALIZA FLEET S/A | F71: FT | G71: 02.286.479/0001-08 | H71: 87 | I71: 1047.5 | J71: 46066 | K71: 46072 | L71: BELO HORIZONTE | M71: MG | N71: 1556 | O71: GABRIEL.ALBINO | Q71: =SUM(R71:AD71)-I71 -> 0 | S71: =SUMIFS('Doc''s Pagos | Rodopar 108'!$J:$J,'Doc''s Pagos | Rodopar 108'!$A:$A,$B71&$E71&$F71&$J71,'Doc''s Pagos | Rodopar 108'!$B:$B,S$1)+SUMIFS('Doc Há Pagar | Rodopar 1015'!$J:$J,'Doc Há Pagar | Rodopar 1015'!$A:$A,$B71&$E71&$F71,'Doc Há Pagar | Rodopar 1015'!$B:$B,S$1) -> 0 | T71: =SUMIFS('Doc''s Pagos | Rodopar 108'!$J:$J,'Doc''s Pagos | Rodopar 108'!$A:$A,$B71&$E71&$F71&$J71,'Doc''s Pagos | Rodopar 108'!$B:$B,T$1)+SUMIFS('Doc Há Pagar | Rodopar 1015'!$J:$J,'Doc Há Pagar | Rodopar 1015'!$A:$A,$B71&$E71&$F71,'Doc Há Pagar | Rodopar 1015'!$B:$B,T$1) -> 0 | U71: =SUMIFS('Doc''s Pagos | Rodopar 108'!$J:$J,'Doc''s Pagos | Rodopar 108'!$A:$A,$B71&$E71&$F71&$J71,'Doc''s Pagos | Rodopar 108'!$B:$B,U$1)+SUMIFS('Doc Há Pagar | Rodopar 1015'!$J:$J,'Doc Há Pagar | Rodopar 1015'!$A:$A,$B71&$E71&$F71,'Doc Há Pagar | Rodopar 1015'!$B:$B,U$1) -> 1047.5 | V71: =SUMIFS('Doc''s Pagos | Rodopar 108'!$J:$J,'Doc''s Pagos | Rodopar 108'!$A:$A,$B71&$E71&$F71&$J71,'Doc''s Pagos | Rodopar 108'!$B:$B,V$1)+SUMIFS('Doc Há Pagar | Rodopar 1015'!$J:$J,'Doc Há Pagar | Rodopar 1015'!$A:$A,$B71&$E71&$F71,'Doc Há Pagar | Rodopar 1015'!$B:$B,V$1) -> 0 | W71: =SUMIFS('Doc''s Pagos | Rodopar 108'!$J:$J,'Doc''s Pagos | Rodopar 108'!$A:$A,$B71&$E71&$F71&$J71,'Doc''s Pagos | Rodopar 108'!$B:$B,W$1)+SUMIFS('Doc Há Pagar | Rodopar 1015'!$J:$J,'Doc Há Pagar | Rodopar 1015'!$A:$A,$B71&$E71&$F71,'Doc Há Pagar | Rodopar 1015'!$B:$B,W$1) -> 0 | X71: =SUMIFS('Doc''s Pagos | Rodopar 108'!$J:$J,'Doc''s Pagos | Rodopar 108'!$A:$A,$B71&$E71&$F71&$J71,'Doc''s Pagos | Rodopar 108'!$B:$B,X$1)+SUMIFS('Doc Há Pagar | Rodopar 1015'!$J:$J,'Doc Há Pagar | Rodopar 1015'!$A:$A,$B71&$E71&$F71,'Doc Há Pagar | Rodopar 1015'!$B:$B,X$1) -> 0 | Y71: =SUMIFS('Doc''s Pagos | Rodopar 108'!$J:$J,'Doc''s Pagos | Rodopar 108'!$A:$A,$B71&$E71&$F71&$J71,'Doc''s Pagos | Rodopar 108'!$B:$B,Y$1)+SUMIFS('Doc Há Pagar | Rodopar 1015'!$J:$J,'Doc Há Pagar | Rodopar 1015'!$A:$A,$B71&$E71&$F71,'Doc Há Pagar | Rodopar 1015'!$B:$B,Y$1) -> 0 | Z71: =SUMIFS('Doc''s Pagos | Rodopar 108'!$J:$J,'Doc''s Pagos | Rodopar 108'!$A:$A,$B71&$E71&$F71&$J71,'Doc''s Pagos | Rodopar 108'!$B:$B,Z$1)+SUMIFS('Doc Há Pagar | Rodopar 1015'!$J:$J,'Doc Há Pagar | Rodopar 1015'!$A:$A,$B71&$E71&$F71,'Doc Há Pagar | Rodopar 1015'!$B:$B,Z$1) -> 0 | ... AD71: =SUMIFS('Doc''s Pagos | Rodopar 108'!$J:$J,'Doc''s Pagos | Rodopar 108'!$A:$A,$B71&$E71&$F71&$J71,'Doc''s Pagos | Rodopar 108'!$B:$B,AD$1)+SUMIFS('Doc Há Pagar | Rodopar 1015'!$J:$J,'Doc Há Pagar | Rodopar 1015'!$A:$A,$B71&$E71&$F71,'Doc Há Pagar | Rodopar 1015'!$B:$B,AD$1) -> 0
A72: =VLOOKUP($E72,Fornecedores!$A:$C,3,0) -> Frota | B72: 108 | C72: =IFERROR(VLOOKUP($E72,Fornecedores!$A:$E,4,0),"") -> Manutenção | D72: =IFERROR(VLOOKUP($E72,Fornecedores!$A:$E,5,0),"") -> Peças E Serviços | E72: ZAMBALDI AUTO CENTER LTDA | F72: NFE | G72: 55.012.105/0001-52 | H72: 87 | I72: 2909 | J72: 46066 | K72: 46067 | L72: CONTAGEM | M72: MG | N72: 1556 | O72: GABRIEL.ALBINO | Q72: =SUM(R72:AD72)-I72 -> 0 | S72: =SUMIFS('Doc''s Pagos | Rodopar 108'!$J:$J,'Doc''s Pagos | Rodopar 108'!$A:$A,$B72&$E72&$F72&$J72,'Doc''s Pagos | Rodopar 108'!$B:$B,S$1)+SUMIFS('Doc Há Pagar | Rodopar 1015'!$J:$J,'Doc Há Pagar | Rodopar 1015'!$A:$A,$B72&$E72&$F72,'Doc Há Pagar | Rodopar 1015'!$B:$B,S$1) -> 0 | T72: =SUMIFS('Doc''s Pagos | Rodopar 108'!$J:$J,'Doc''s Pagos | Rodopar 108'!$A:$A,$B72&$E72&$F72&$J72,'Doc''s Pagos | Rodopar 108'!$B:$B,T$1)+SUMIFS('Doc Há Pagar | Rodopar 1015'!$J:$J,'Doc Há Pagar | Rodopar 1015'!$A:$A,$B72&$E72&$F72,'Doc Há Pagar | Rodopar 1015'!$B:$B,T$1) -> 0 | U72: =SUMIFS('Doc''s Pagos | Rodopar 108'!$J:$J,'Doc''s Pagos | Rodopar 108'!$A:$A,$B72&$E72&$F72&$J72,'Doc''s Pagos | Rodopar 108'!$B:$B,U$1)+SUMIFS('Doc Há Pagar | Rodopar 1015'!$J:$J,'Doc Há Pagar | Rodopar 1015'!$A:$A,$B72&$E72&$F72,'Doc Há Pagar | Rodopar 1015'!$B:$B,U$1) -> 2909 | V72: =SUMIFS('Doc''s Pagos | Rodopar 108'!$J:$J,'Doc''s Pagos | Rodopar 108'!$A:$A,$B72&$E72&$F72&$J72,'Doc''s Pagos | Rodopar 108'!$B:$B,V$1)+SUMIFS('Doc Há Pagar | Rodopar 1015'!$J:$J,'Doc Há Pagar | Rodopar 1015'!$A:$A,$B72&$E72&$F72,'Doc Há Pagar | Rodopar 1015'!$B:$B,V$1) -> 0 | W72: =SUMIFS('Doc''s Pagos | Rodopar 108'!$J:$J,'Doc''s Pagos | Rodopar 108'!$A:$A,$B72&$E72&$F72&$J72,'Doc''s Pagos | Rodopar 108'!$B:$B,W$1)+SUMIFS('Doc Há Pagar | Rodopar 1015'!$J:$J,'Doc Há Pagar | Rodopar 1015'!$A:$A,$B72&$E72&$F72,'Doc Há Pagar | Rodopar 1015'!$B:$B,W$1) -> 0 | X72: =SUMIFS('Doc''s Pagos | Rodopar 108'!$J:$J,'Doc''s Pagos | Rodopar 108'!$A:$A,$B72&$E72&$F72&$J72,'Doc''s Pagos | Rodopar 108'!$B:$B,X$1)+SUMIFS('Doc Há Pagar | Rodopar 1015'!$J:$J,'Doc Há Pagar | Rodopar 1015'!$A:$A,$B72&$E72&$F72,'Doc Há Pagar | Rodopar 1015'!$B:$B,X$1) -> 0 | Y72: =SUMIFS('Doc''s Pagos | Rodopar 108'!$J:$J,'Doc''s Pagos | Rodopar 108'!$A:$A,$B72&$E72&$F72&$J72,'Doc''s Pagos | Rodopar 108'!$B:$B,Y$1)+SUMIFS('Doc Há Pagar | Rodopar 1015'!$J:$J,'Doc Há Pagar | Rodopar 1015'!$A:$A,$B72&$E72&$F72,'Doc Há Pagar | Rodopar 1015'!$B:$B,Y$1) -> 0 | Z72: =SUMIFS('Doc''s Pagos | Rodopar 108'!$J:$J,'Doc''s Pagos | Rodopar 108'!$A:$A,$B72&$E72&$F72&$J72,'Doc''s Pagos | Rodopar 108'!$B:$B,Z$1)+SUMIFS('Doc Há Pagar | Rodopar 1015'!$J:$J,'Doc Há Pagar | Rodopar 1015'!$A:$A,$B72&$E72&$F72,'Doc Há Pagar | Rodopar 1015'!$B:$B,Z$1) -> 0 | ... AD72: =SUMIFS('Doc''s Pagos | Rodopar 108'!$J:$J,'Doc''s Pagos | Rodopar 108'!$A:$A,$B72&$E72&$F72&$J72,'Doc''s Pagos | Rodopar 108'!$B:$B,AD$1)+SUMIFS('Doc Há Pagar | Rodopar 1015'!$J:$J,'Doc Há Pagar | Rodopar 1015'!$A:$A,$B72&$E72&$F72,'Doc Há Pagar | Rodopar 1015'!$B:$B,AD$1) -> 0
A73: =VLOOKUP($E73,Fornecedores!$A:$C,3,0) -> Frota | B73: 1486122 | C73: =IFERROR(VLOOKUP($E73,Fornecedores!$A:$E,4,0),"") -> MTSR | D73: =IFERROR(VLOOKUP($E73,Fornecedores!$A:$E,5,0),"") -> Tecnologia | E73: TRUCKS COM. E TEC. DE RASTREAD. COMUNICAÇÕES LTDA | F73: NSE | G73: 27.755.427/0007-41 | H73: 87 | I73: 1477.83 | J73: 46066 | K73: 46066 | L73: IBIPORA | M73: PR | N73: 2556 | O73: GABRIEL.ALBINO | Q73: =SUM(R73:AD73)-I73 -> 0 | S73: =SUMIFS('Doc''s Pagos | Rodopar 108'!$J:$J,'Doc''s Pagos | Rodopar 108'!$A:$A,$B73&$E73&$F73&$J73,'Doc''s Pagos | Rodopar 108'!$B:$B,S$1)+SUMIFS('Doc Há Pagar | Rodopar 1015'!$J:$J,'Doc Há Pagar | Rodopar 1015'!$A:$A,$B73&$E73&$F73,'Doc Há Pagar | Rodopar 1015'!$B:$B,S$1) -> 0 | T73: =SUMIFS('Doc''s Pagos | Rodopar 108'!$J:$J,'Doc''s Pagos | Rodopar 108'!$A:$A,$B73&$E73&$F73&$J73,'Doc''s Pagos | Rodopar 108'!$B:$B,T$1)+SUMIFS('Doc Há Pagar | Rodopar 1015'!$J:$J,'Doc Há Pagar | Rodopar 1015'!$A:$A,$B73&$E73&$F73,'Doc Há Pagar | Rodopar 1015'!$B:$B,T$1) -> 0 | U73: =SUMIFS('Doc''s Pagos | Rodopar 108'!$J:$J,'Doc''s Pagos | Rodopar 108'!$A:$A,$B73&$E73&$F73&$J73,'Doc''s Pagos | Rodopar 108'!$B:$B,U$1)+SUMIFS('Doc Há Pagar | Rodopar 1015'!$J:$J,'Doc Há Pagar | Rodopar 1015'!$A:$A,$B73&$E73&$F73,'Doc Há Pagar | Rodopar 1015'!$B:$B,U$1) -> 1477.83 | V73: =SUMIFS('Doc''s Pagos | Rodopar 108'!$J:$J,'Doc''s Pagos | Rodopar 108'!$A:$A,$B73&$E73&$F73&$J73,'Doc''s Pagos | Rodopar 108'!$B:$B,V$1)+SUMIFS('Doc Há Pagar | Rodopar 1015'!$J:$J,'Doc Há Pagar | Rodopar 1015'!$A:$A,$B73&$E73&$F73,'Doc Há Pagar | Rodopar 1015'!$B:$B,V$1) -> 0 | W73: =SUMIFS('Doc''s Pagos | Rodopar 108'!$J:$J,'Doc''s Pagos | Rodopar 108'!$A:$A,$B73&$E73&$F73&$J73,'Doc''s Pagos | Rodopar 108'!$B:$B,W$1)+SUMIFS('Doc Há Pagar | Rodopar 1015'!$J:$J,'Doc Há Pagar | Rodopar 1015'!$A:$A,$B73&$E73&$F73,'Doc Há Pagar | Rodopar 1015'!$B:$B,W$1) -> 0 | X73: =SUMIFS('Doc''s Pagos | Rodopar 108'!$J:$J,'Doc''s Pagos | Rodopar 108'!$A:$A,$B73&$E73&$F73&$J73,'Doc''s Pagos | Rodopar 108'!$B:$B,X$1)+SUMIFS('Doc Há Pagar | Rodopar 1015'!$J:$J,'Doc Há Pagar | Rodopar 1015'!$A:$A,$B73&$E73&$F73,'Doc Há Pagar | Rodopar 1015'!$B:$B,X$1) -> 0 | Y73: =SUMIFS('Doc''s Pagos | Rodopar 108'!$J:$J,'Doc''s Pagos | Rodopar 108'!$A:$A,$B73&$E73&$F73&$J73,'Doc''s Pagos | Rodopar 108'!$B:$B,Y$1)+SUMIFS('Doc Há Pagar | Rodopar 1015'!$J:$J,'Doc Há Pagar | Rodopar 1015'!$A:$A,$B73&$E73&$F73,'Doc Há Pagar | Rodopar 1015'!$B:$B,Y$1) -> 0 | Z73: =SUMIFS('Doc''s Pagos | Rodopar 108'!$J:$J,'Doc''s Pagos | Rodopar 108'!$A:$A,$B73&$E73&$F73&$J73,'Doc''s Pagos | Rodopar 108'!$B:$B,Z$1)+SUMIFS('Doc Há Pagar | Rodopar 1015'!$J:$J,'Doc Há Pagar | Rodopar 1015'!$A:$A,$B73&$E73&$F73,'Doc Há Pagar | Rodopar 1015'!$B:$B,Z$1) -> 0 | ... AD73: =SUMIFS('Doc''s Pagos | Rodopar 108'!$J:$J,'Doc''s Pagos | Rodopar 108'!$A:$A,$B73&$E73&$F73&$J73,'Doc''s Pagos | Rodopar 108'!$B:$B,AD$1)+SUMIFS('Doc Há Pagar | Rodopar 1015'!$J:$J,'Doc Há Pagar | Rodopar 1015'!$A:$A,$B73&$E73&$F73,'Doc Há Pagar | Rodopar 1015'!$B:$B,AD$1) -> 0
A74: =VLOOKUP($E74,Fornecedores!$A:$C,3,0) -> Frota | B74: 3168757 | C74: =IFERROR(VLOOKUP($E74,Fornecedores!$A:$E,4,0),"") -> MTSR | D74: =IFERROR(VLOOKUP($E74,Fornecedores!$A:$E,5,0),"") -> Tecnologia | E74: TRUCKS CONTROL - SERVIÇOS DE LOGISTICA LTDA | F74: NSE | G74: 09.110.913/0027-74 | H74: 87 | I74: 8365.89 | J74: 46066 | K74: 46066 | L74: IBIPORA | M74: PR | N74: 2556 | O74: GABRIEL.ALBINO | Q74: =SUM(R74:AD74)-I74 -> 0 | S74: =SUMIFS('Doc''s Pagos | Rodopar 108'!$J:$J,'Doc''s Pagos | Rodopar 108'!$A:$A,$B74&$E74&$F74&$J74,'Doc''s Pagos | Rodopar 108'!$B:$B,S$1)+SUMIFS('Doc Há Pagar | Rodopar 1015'!$J:$J,'Doc Há Pagar | Rodopar 1015'!$A:$A,$B74&$E74&$F74,'Doc Há Pagar | Rodopar 1015'!$B:$B,S$1) -> 0 | T74: =SUMIFS('Doc''s Pagos | Rodopar 108'!$J:$J,'Doc''s Pagos | Rodopar 108'!$A:$A,$B74&$E74&$F74&$J74,'Doc''s Pagos | Rodopar 108'!$B:$B,T$1)+SUMIFS('Doc Há Pagar | Rodopar 1015'!$J:$J,'Doc Há Pagar | Rodopar 1015'!$A:$A,$B74&$E74&$F74,'Doc Há Pagar | Rodopar 1015'!$B:$B,T$1) -> 0 | U74: =SUMIFS('Doc''s Pagos | Rodopar 108'!$J:$J,'Doc''s Pagos | Rodopar 108'!$A:$A,$B74&$E74&$F74&$J74,'Doc''s Pagos | Rodopar 108'!$B:$B,U$1)+SUMIFS('Doc Há Pagar | Rodopar 1015'!$J:$J,'Doc Há Pagar | Rodopar 1015'!$A:$A,$B74&$E74&$F74,'Doc Há Pagar | Rodopar 1015'!$B:$B,U$1) -> 8365.89 | V74: =SUMIFS('Doc''s Pagos | Rodopar 108'!$J:$J,'Doc''s Pagos | Rodopar 108'!$A:$A,$B74&$E74&$F74&$J74,'Doc''s Pagos | Rodopar 108'!$B:$B,V$1)+SUMIFS('Doc Há Pagar | Rodopar 1015'!$J:$J,'Doc Há Pagar | Rodopar 1015'!$A:$A,$B74&$E74&$F74,'Doc Há Pagar | Rodopar 1015'!$B:$B,V$1) -> 0 | W74: =SUMIFS('Doc''s Pagos | Rodopar 108'!$J:$J,'Doc''s Pagos | Rodopar 108'!$A:$A,$B74&$E74&$F74&$J74,'Doc''s Pagos | Rodopar 108'!$B:$B,W$1)+SUMIFS('Doc Há Pagar | Rodopar 1015'!$J:$J,'Doc Há Pagar | Rodopar 1015'!$A:$A,$B74&$E74&$F74,'Doc Há Pagar | Rodopar 1015'!$B:$B,W$1) -> 0 | X74: =SUMIFS('Doc''s Pagos | Rodopar 108'!$J:$J,'Doc''s Pagos | Rodopar 108'!$A:$A,$B74&$E74&$F74&$J74,'Doc''s Pagos | Rodopar 108'!$B:$B,X$1)+SUMIFS('Doc Há Pagar | Rodopar 1015'!$J:$J,'Doc Há Pagar | Rodopar 1015'!$A:$A,$B74&$E74&$F74,'Doc Há Pagar | Rodopar 1015'!$B:$B,X$1) -> 0 | Y74: =SUMIFS('Doc''s Pagos | Rodopar 108'!$J:$J,'Doc''s Pagos | Rodopar 108'!$A:$A,$B74&$E74&$F74&$J74,'Doc''s Pagos | Rodopar 108'!$B:$B,Y$1)+SUMIFS('Doc Há Pagar | Rodopar 1015'!$J:$J,'Doc Há Pagar | Rodopar 1015'!$A:$A,$B74&$E74&$F74,'Doc Há Pagar | Rodopar 1015'!$B:$B,Y$1) -> 0 | Z74: =SUMIFS('Doc''s Pagos | Rodopar 108'!$J:$J,'Doc''s Pagos | Rodopar 108'!$A:$A,$B74&$E74&$F74&$J74,'Doc''s Pagos | Rodopar 108'!$B:$B,Z$1)+SUMIFS('Doc Há Pagar | Rodopar 1015'!$J:$J,'Doc Há Pagar | Rodopar 1015'!$A:$A,$B74&$E74&$F74,'Doc Há Pagar | Rodopar 1015'!$B:$B,Z$1) -> 0 | ... AD74: =SUMIFS('Doc''s Pagos | Rodopar 108'!$J:$J,'Doc''s Pagos | Rodopar 108'!$A:$A,$B74&$E74&$F74&$J74,'Doc''s Pagos | Rodopar 108'!$B:$B,AD$1)+SUMIFS('Doc Há Pagar | Rodopar 1015'!$J:$J,'Doc Há Pagar | Rodopar 1015'!$A:$A,$B74&$E74&$F74,'Doc Há Pagar | Rodopar 1015'!$B:$B,AD$1) -> 0
A75: =VLOOKUP($E75,Fornecedores!$A:$C,3,0) -> Frota | B75: 39 | C75: =IFERROR(VLOOKUP($E75,Fornecedores!$A:$E,4,0),"") -> Manutenção | D75: =IFERROR(VLOOKUP($E75,Fornecedores!$A:$E,5,0),"") -> Peças E Serviços | E75: ZAMBALDI AUTO CENTER LTDA | F75: NSE | G75: 55.012.105/0001-52 | H75: 87 | I75: 750 | J75: 46066 | K75: 46067 | L75: CONTAGEM | M75: MG | N75: 1556 | O75: GABRIEL.ALBINO | Q75: =SUM(R75:AD75)-I75 -> 0 | S75: =SUMIFS('Doc''s Pagos | Rodopar 108'!$J:$J,'Doc''s Pagos | Rodopar 108'!$A:$A,$B75&$E75&$F75&$J75,'Doc''s Pagos | Rodopar 108'!$B:$B,S$1)+SUMIFS('Doc Há Pagar | Rodopar 1015'!$J:$J,'Doc Há Pagar | Rodopar 1015'!$A:$A,$B75&$E75&$F75,'Doc Há Pagar | Rodopar 1015'!$B:$B,S$1) -> 0 | T75: =SUMIFS('Doc''s Pagos | Rodopar 108'!$J:$J,'Doc''s Pagos | Rodopar 108'!$A:$A,$B75&$E75&$F75&$J75,'Doc''s Pagos | Rodopar 108'!$B:$B,T$1)+SUMIFS('Doc Há Pagar | Rodopar 1015'!$J:$J,'Doc Há Pagar | Rodopar 1015'!$A:$A,$B75&$E75&$F75,'Doc Há Pagar | Rodopar 1015'!$B:$B,T$1) -> 0 | U75: =SUMIFS('Doc''s Pagos | Rodopar 108'!$J:$J,'Doc''s Pagos | Rodopar 108'!$A:$A,$B75&$E75&$F75&$J75,'Doc''s Pagos | Rodopar 108'!$B:$B,U$1)+SUMIFS('Doc Há Pagar | Rodopar 1015'!$J:$J,'Doc Há Pagar | Rodopar 1015'!$A:$A,$B75&$E75&$F75,'Doc Há Pagar | Rodopar 1015'!$B:$B,U$1) -> 750 | V75: =SUMIFS('Doc''s Pagos | Rodopar 108'!$J:$J,'Doc''s Pagos | Rodopar 108'!$A:$A,$B75&$E75&$F75&$J75,'Doc''s Pagos | Rodopar 108'!$B:$B,V$1)+SUMIFS('Doc Há Pagar | Rodopar 1015'!$J:$J,'Doc Há Pagar | Rodopar 1015'!$A:$A,$B75&$E75&$F75,'Doc Há Pagar | Rodopar 1015'!$B:$B,V$1) -> 0 | W75: =SUMIFS('Doc''s Pagos | Rodopar 108'!$J:$J,'Doc''s Pagos | Rodopar 108'!$A:$A,$B75&$E75&$F75&$J75,'Doc''s Pagos | Rodopar 108'!$B:$B,W$1)+SUMIFS('Doc Há Pagar | Rodopar 1015'!$J:$J,'Doc Há Pagar | Rodopar 1015'!$A:$A,$B75&$E75&$F75,'Doc Há Pagar | Rodopar 1015'!$B:$B,W$1) -> 0 | X75: =SUMIFS('Doc''s Pagos | Rodopar 108'!$J:$J,'Doc''s Pagos | Rodopar 108'!$A:$A,$B75&$E75&$F75&$J75,'Doc''s Pagos | Rodopar 108'!$B:$B,X$1)+SUMIFS('Doc Há Pagar | Rodopar 1015'!$J:$J,'Doc Há Pagar | Rodopar 1015'!$A:$A,$B75&$E75&$F75,'Doc Há Pagar | Rodopar 1015'!$B:$B,X$1) -> 0 | Y75: =SUMIFS('Doc''s Pagos | Rodopar 108'!$J:$J,'Doc''s Pagos | Rodopar 108'!$A:$A,$B75&$E75&$F75&$J75,'Doc''s Pagos | Rodopar 108'!$B:$B,Y$1)+SUMIFS('Doc Há Pagar | Rodopar 1015'!$J:$J,'Doc Há Pagar | Rodopar 1015'!$A:$A,$B75&$E75&$F75,'Doc Há Pagar | Rodopar 1015'!$B:$B,Y$1) -> 0 | Z75: =SUMIFS('Doc''s Pagos | Rodopar 108'!$J:$J,'Doc''s Pagos | Rodopar 108'!$A:$A,$B75&$E75&$F75&$J75,'Doc''s Pagos | Rodopar 108'!$B:$B,Z$1)+SUMIFS('Doc Há Pagar | Rodopar 1015'!$J:$J,'Doc Há Pagar | Rodopar 1015'!$A:$A,$B75&$E75&$F75,'Doc Há Pagar | Rodopar 1015'!$B:$B,Z$1) -> 0 | ... AD75: =SUMIFS('Doc''s Pagos | Rodopar 108'!$J:$J,'Doc''s Pagos | Rodopar 108'!$A:$A,$B75&$E75&$F75&$J75,'Doc''s Pagos | Rodopar 108'!$B:$B,AD$1)+SUMIFS('Doc Há Pagar | Rodopar 1015'!$J:$J,'Doc Há Pagar | Rodopar 1015'!$A:$A,$B75&$E75&$F75,'Doc Há Pagar | Rodopar 1015'!$B:$B,AD$1) -> 0
A76: =VLOOKUP($E76,Fornecedores!$A:$C,3,0) -> Frota | B76: 40 | C76: =IFERROR(VLOOKUP($E76,Fornecedores!$A:$E,4,0),"") -> Manutenção | D76: =IFERROR(VLOOKUP($E76,Fornecedores!$A:$E,5,0),"") -> Peças E Serviços | E76: ZAMBALDI AUTO CENTER LTDA | F76: NSE | G76: 55.012.105/0001-52 | H76: 87 | I76: 180 | J76: 46066 | K76: 46067 | L76: CONTAGEM | M76: MG | N76: 1556 | O76: GABRIEL.ALBINO | Q76: =SUM(R76:AD76)-I76 -> 0 | S76: =SUMIFS('Doc''s Pagos | Rodopar 108'!$J:$J,'Doc''s Pagos | Rodopar 108'!$A:$A,$B76&$E76&$F76&$J76,'Doc''s Pagos | Rodopar 108'!$B:$B,S$1)+SUMIFS('Doc Há Pagar | Rodopar 1015'!$J:$J,'Doc Há Pagar | Rodopar 1015'!$A:$A,$B76&$E76&$F76,'Doc Há Pagar | Rodopar 1015'!$B:$B,S$1) -> 0 | T76: =SUMIFS('Doc''s Pagos | Rodopar 108'!$J:$J,'Doc''s Pagos | Rodopar 108'!$A:$A,$B76&$E76&$F76&$J76,'Doc''s Pagos | Rodopar 108'!$B:$B,T$1)+SUMIFS('Doc Há Pagar | Rodopar 1015'!$J:$J,'Doc Há Pagar | Rodopar 1015'!$A:$A,$B76&$E76&$F76,'Doc Há Pagar | Rodopar 1015'!$B:$B,T$1) -> 0 | U76: =SUMIFS('Doc''s Pagos | Rodopar 108'!$J:$J,'Doc''s Pagos | Rodopar 108'!$A:$A,$B76&$E76&$F76&$J76,'Doc''s Pagos | Rodopar 108'!$B:$B,U$1)+SUMIFS('Doc Há Pagar | Rodopar 1015'!$J:$J,'Doc Há Pagar | Rodopar 1015'!$A:$A,$B76&$E76&$F76,'Doc Há Pagar | Rodopar 1015'!$B:$B,U$1) -> 180 | V76: =SUMIFS('Doc''s Pagos | Rodopar 108'!$J:$J,'Doc''s Pagos | Rodopar 108'!$A:$A,$B76&$E76&$F76&$J76,'Doc''s Pagos | Rodopar 108'!$B:$B,V$1)+SUMIFS('Doc Há Pagar | Rodopar 1015'!$J:$J,'Doc Há Pagar | Rodopar 1015'!$A:$A,$B76&$E76&$F76,'Doc Há Pagar | Rodopar 1015'!$B:$B,V$1) -> 0 | W76: =SUMIFS('Doc''s Pagos | Rodopar 108'!$J:$J,'Doc''s Pagos | Rodopar 108'!$A:$A,$B76&$E76&$F76&$J76,'Doc''s Pagos | Rodopar 108'!$B:$B,W$1)+SUMIFS('Doc Há Pagar | Rodopar 1015'!$J:$J,'Doc Há Pagar | Rodopar 1015'!$A:$A,$B76&$E76&$F76,'Doc Há Pagar | Rodopar 1015'!$B:$B,W$1) -> 0 | X76: =SUMIFS('Doc''s Pagos | Rodopar 108'!$J:$J,'Doc''s Pagos | Rodopar 108'!$A:$A,$B76&$E76&$F76&$J76,'Doc''s Pagos | Rodopar 108'!$B:$B,X$1)+SUMIFS('Doc Há Pagar | Rodopar 1015'!$J:$J,'Doc Há Pagar | Rodopar 1015'!$A:$A,$B76&$E76&$F76,'Doc Há Pagar | Rodopar 1015'!$B:$B,X$1) -> 0 | Y76: =SUMIFS('Doc''s Pagos | Rodopar 108'!$J:$J,'Doc''s Pagos | Rodopar 108'!$A:$A,$B76&$E76&$F76&$J76,'Doc''s Pagos | Rodopar 108'!$B:$B,Y$1)+SUMIFS('Doc Há Pagar | Rodopar 1015'!$J:$J,'Doc Há Pagar | Rodopar 1015'!$A:$A,$B76&$E76&$F76,'Doc Há Pagar | Rodopar 1015'!$B:$B,Y$1) -> 0 | Z76: =SUMIFS('Doc''s Pagos | Rodopar 108'!$J:$J,'Doc''s Pagos | Rodopar 108'!$A:$A,$B76&$E76&$F76&$J76,'Doc''s Pagos | Rodopar 108'!$B:$B,Z$1)+SUMIFS('Doc Há Pagar | Rodopar 1015'!$J:$J,'Doc Há Pagar | Rodopar 1015'!$A:$A,$B76&$E76&$F76,'Doc Há Pagar | Rodopar 1015'!$B:$B,Z$1) -> 0 | ... AD76: =SUMIFS('Doc''s Pagos | Rodopar 108'!$J:$J,'Doc''s Pagos | Rodopar 108'!$A:$A,$B76&$E76&$F76&$J76,'Doc''s Pagos | Rodopar 108'!$B:$B,AD$1)+SUMIFS('Doc Há Pagar | Rodopar 1015'!$J:$J,'Doc Há Pagar | Rodopar 1015'!$A:$A,$B76&$E76&$F76,'Doc Há Pagar | Rodopar 1015'!$B:$B,AD$1) -> 0
A77: =VLOOKUP($E77,Fornecedores!$A:$C,3,0) -> Frota | B77: 142 | C77: =IFERROR(VLOOKUP($E77,Fornecedores!$A:$E,4,0),"") -> Sinistro | D77: =IFERROR(VLOOKUP($E77,Fornecedores!$A:$E,5,0),"") -> Guincho | E77: HAMILTON AUTO SOCORRO LTDA | F77: NSE | G77: 53.633.121/0001-37 | H77: 87 | I77: 1150 | J77: 46069 | K77: 46071 | L77: UBERLANDIA | M77: MG | N77: 1556 | O77: GABRIEL.ALBINO | Q77: =SUM(R77:AD77)-I77 -> 0 | S77: =SUMIFS('Doc''s Pagos | Rodopar 108'!$J:$J,'Doc''s Pagos | Rodopar 108'!$A:$A,$B77&$E77&$F77&$J77,'Doc''s Pagos | Rodopar 108'!$B:$B,S$1)+SUMIFS('Doc Há Pagar | Rodopar 1015'!$J:$J,'Doc Há Pagar | Rodopar 1015'!$A:$A,$B77&$E77&$F77,'Doc Há Pagar | Rodopar 1015'!$B:$B,S$1) -> 0 | T77: =SUMIFS('Doc''s Pagos | Rodopar 108'!$J:$J,'Doc''s Pagos | Rodopar 108'!$A:$A,$B77&$E77&$F77&$J77,'Doc''s Pagos | Rodopar 108'!$B:$B,T$1)+SUMIFS('Doc Há Pagar | Rodopar 1015'!$J:$J,'Doc Há Pagar | Rodopar 1015'!$A:$A,$B77&$E77&$F77,'Doc Há Pagar | Rodopar 1015'!$B:$B,T$1) -> 1150 | U77: =SUMIFS('Doc''s Pagos | Rodopar 108'!$J:$J,'Doc''s Pagos | Rodopar 108'!$A:$A,$B77&$E77&$F77&$J77,'Doc''s Pagos | Rodopar 108'!$B:$B,U$1)+SUMIFS('Doc Há Pagar | Rodopar 1015'!$J:$J,'Doc Há Pagar | Rodopar 1015'!$A:$A,$B77&$E77&$F77,'Doc Há Pagar | Rodopar 1015'!$B:$B,U$1) -> 0 | V77: =SUMIFS('Doc''s Pagos | Rodopar 108'!$J:$J,'Doc''s Pagos | Rodopar 108'!$A:$A,$B77&$E77&$F77&$J77,'Doc''s Pagos | Rodopar 108'!$B:$B,V$1)+SUMIFS('Doc Há Pagar | Rodopar 1015'!$J:$J,'Doc Há Pagar | Rodopar 1015'!$A:$A,$B77&$E77&$F77,'Doc Há Pagar | Rodopar 1015'!$B:$B,V$1) -> 0 | W77: =SUMIFS('Doc''s Pagos | Rodopar 108'!$J:$J,'Doc''s Pagos | Rodopar 108'!$A:$A,$B77&$E77&$F77&$J77,'Doc''s Pagos | Rodopar 108'!$B:$B,W$1)+SUMIFS('Doc Há Pagar | Rodopar 1015'!$J:$J,'Doc Há Pagar | Rodopar 1015'!$A:$A,$B77&$E77&$F77,'Doc Há Pagar | Rodopar 1015'!$B:$B,W$1) -> 0 | X77: =SUMIFS('Doc''s Pagos | Rodopar 108'!$J:$J,'Doc''s Pagos | Rodopar 108'!$A:$A,$B77&$E77&$F77&$J77,'Doc''s Pagos | Rodopar 108'!$B:$B,X$1)+SUMIFS('Doc Há Pagar | Rodopar 1015'!$J:$J,'Doc Há Pagar | Rodopar 1015'!$A:$A,$B77&$E77&$F77,'Doc Há Pagar | Rodopar 1015'!$B:$B,X$1) -> 0 | Y77: =SUMIFS('Doc''s Pagos | Rodopar 108'!$J:$J,'Doc''s Pagos | Rodopar 108'!$A:$A,$B77&$E77&$F77&$J77,'Doc''s Pagos | Rodopar 108'!$B:$B,Y$1)+SUMIFS('Doc Há Pagar | Rodopar 1015'!$J:$J,'Doc Há Pagar | Rodopar 1015'!$A:$A,$B77&$E77&$F77,'Doc Há Pagar | Rodopar 1015'!$B:$B,Y$1) -> 0 | Z77: =SUMIFS('Doc''s Pagos | Rodopar 108'!$J:$J,'Doc''s Pagos | Rodopar 108'!$A:$A,$B77&$E77&$F77&$J77,'Doc''s Pagos | Rodopar 108'!$B:$B,Z$1)+SUMIFS('Doc Há Pagar | Rodopar 1015'!$J:$J,'Doc Há Pagar | Rodopar 1015'!$A:$A,$B77&$E77&$F77,'Doc Há Pagar | Rodopar 1015'!$B:$B,Z$1) -> 0 | ... AD77: =SUMIFS('Doc''s Pagos | Rodopar 108'!$J:$J,'Doc''s Pagos | Rodopar 108'!$A:$A,$B77&$E77&$F77&$J77,'Doc''s Pagos | Rodopar 108'!$B:$B,AD$1)+SUMIFS('Doc Há Pagar | Rodopar 1015'!$J:$J,'Doc Há Pagar | Rodopar 1015'!$A:$A,$B77&$E77&$F77,'Doc Há Pagar | Rodopar 1015'!$B:$B,AD$1) -> 0
A78: =VLOOKUP($E78,Fornecedores!$A:$C,3,0) -> Frota | B78: 2707 | C78: =IFERROR(VLOOKUP($E78,Fornecedores!$A:$E,4,0),"") -> Manutenção | D78: =IFERROR(VLOOKUP($E78,Fornecedores!$A:$E,5,0),"") -> Frota Leve OPE | E78: MECANICA CRISTO REI LTDA | F78: NFE | G78: 71.299.614/0001-64 | H78: 87 | I78: 386 | J78: 46071 | K78: 46079 | L78: CONTAGEM | M78: MG | N78: 1556 | O78: GABRIEL.ALBINO | Q78: =SUM(R78:AD78)-I78 -> 0 | S78: =SUMIFS('Doc''s Pagos | Rodopar 108'!$J:$J,'Doc''s Pagos | Rodopar 108'!$A:$A,$B78&$E78&$F78&$J78,'Doc''s Pagos | Rodopar 108'!$B:$B,S$1)+SUMIFS('Doc Há Pagar | Rodopar 1015'!$J:$J,'Doc Há Pagar | Rodopar 1015'!$A:$A,$B78&$E78&$F78,'Doc Há Pagar | Rodopar 1015'!$B:$B,S$1) -> 0 | T78: =SUMIFS('Doc''s Pagos | Rodopar 108'!$J:$J,'Doc''s Pagos | Rodopar 108'!$A:$A,$B78&$E78&$F78&$J78,'Doc''s Pagos | Rodopar 108'!$B:$B,T$1)+SUMIFS('Doc Há Pagar | Rodopar 1015'!$J:$J,'Doc Há Pagar | Rodopar 1015'!$A:$A,$B78&$E78&$F78,'Doc Há Pagar | Rodopar 1015'!$B:$B,T$1) -> 0 | U78: =SUMIFS('Doc''s Pagos | Rodopar 108'!$J:$J,'Doc''s Pagos | Rodopar 108'!$A:$A,$B78&$E78&$F78&$J78,'Doc''s Pagos | Rodopar 108'!$B:$B,U$1)+SUMIFS('Doc Há Pagar | Rodopar 1015'!$J:$J,'Doc Há Pagar | Rodopar 1015'!$A:$A,$B78&$E78&$F78,'Doc Há Pagar | Rodopar 1015'!$B:$B,U$1) -> 386 | V78: =SUMIFS('Doc''s Pagos | Rodopar 108'!$J:$J,'Doc''s Pagos | Rodopar 108'!$A:$A,$B78&$E78&$F78&$J78,'Doc''s Pagos | Rodopar 108'!$B:$B,V$1)+SUMIFS('Doc Há Pagar | Rodopar 1015'!$J:$J,'Doc Há Pagar | Rodopar 1015'!$A:$A,$B78&$E78&$F78,'Doc Há Pagar | Rodopar 1015'!$B:$B,V$1) -> 0 | W78: =SUMIFS('Doc''s Pagos | Rodopar 108'!$J:$J,'Doc''s Pagos | Rodopar 108'!$A:$A,$B78&$E78&$F78&$J78,'Doc''s Pagos | Rodopar 108'!$B:$B,W$1)+SUMIFS('Doc Há Pagar | Rodopar 1015'!$J:$J,'Doc Há Pagar | Rodopar 1015'!$A:$A,$B78&$E78&$F78,'Doc Há Pagar | Rodopar 1015'!$B:$B,W$1) -> 0 | X78: =SUMIFS('Doc''s Pagos | Rodopar 108'!$J:$J,'Doc''s Pagos | Rodopar 108'!$A:$A,$B78&$E78&$F78&$J78,'Doc''s Pagos | Rodopar 108'!$B:$B,X$1)+SUMIFS('Doc Há Pagar | Rodopar 1015'!$J:$J,'Doc Há Pagar | Rodopar 1015'!$A:$A,$B78&$E78&$F78,'Doc Há Pagar | Rodopar 1015'!$B:$B,X$1) -> 0 | Y78: =SUMIFS('Doc''s Pagos | Rodopar 108'!$J:$J,'Doc''s Pagos | Rodopar 108'!$A:$A,$B78&$E78&$F78&$J78,'Doc''s Pagos | Rodopar 108'!$B:$B,Y$1)+SUMIFS('Doc Há Pagar | Rodopar 1015'!$J:$J,'Doc Há Pagar | Rodopar 1015'!$A:$A,$B78&$E78&$F78,'Doc Há Pagar | Rodopar 1015'!$B:$B,Y$1) -> 0 | Z78: =SUMIFS('Doc''s Pagos | Rodopar 108'!$J:$J,'Doc''s Pagos | Rodopar 108'!$A:$A,$B78&$E78&$F78&$J78,'Doc''s Pagos | Rodopar 108'!$B:$B,Z$1)+SUMIFS('Doc Há Pagar | Rodopar 1015'!$J:$J,'Doc Há Pagar | Rodopar 1015'!$A:$A,$B78&$E78&$F78,'Doc Há Pagar | Rodopar 1015'!$B:$B,Z$1) -> 0 | ... AD78: =SUMIFS('Doc''s Pagos | Rodopar 108'!$J:$J,'Doc''s Pagos | Rodopar 108'!$A:$A,$B78&$E78&$F78&$J78,'Doc''s Pagos | Rodopar 108'!$B:$B,AD$1)+SUMIFS('Doc Há Pagar | Rodopar 1015'!$J:$J,'Doc Há Pagar | Rodopar 1015'!$A:$A,$B78&$E78&$F78,'Doc Há Pagar | Rodopar 1015'!$B:$B,AD$1) -> 0
A79: =VLOOKUP($E79,Fornecedores!$A:$C,3,0) -> Frota | B79: 2708 | C79: =IFERROR(VLOOKUP($E79,Fornecedores!$A:$E,4,0),"") -> Manutenção | D79: =IFERROR(VLOOKUP($E79,Fornecedores!$A:$E,5,0),"") -> Frota Leve OPE | E79: MECANICA CRISTO REI LTDA | F79: NFE | G79: 71.299.614/0001-64 | H79: 87 | I79: 386 | J79: 46071 | K79: 46079 | L79: CONTAGEM | M79: MG | N79: 1556 | O79: GABRIEL.ALBINO | Q79: =SUM(R79:AD79)-I79 -> 0 | S79: =SUMIFS('Doc''s Pagos | Rodopar 108'!$J:$J,'Doc''s Pagos | Rodopar 108'!$A:$A,$B79&$E79&$F79&$J79,'Doc''s Pagos | Rodopar 108'!$B:$B,S$1)+SUMIFS('Doc Há Pagar | Rodopar 1015'!$J:$J,'Doc Há Pagar | Rodopar 1015'!$A:$A,$B79&$E79&$F79,'Doc Há Pagar | Rodopar 1015'!$B:$B,S$1) -> 0 | T79: =SUMIFS('Doc''s Pagos | Rodopar 108'!$J:$J,'Doc''s Pagos | Rodopar 108'!$A:$A,$B79&$E79&$F79&$J79,'Doc''s Pagos | Rodopar 108'!$B:$B,T$1)+SUMIFS('Doc Há Pagar | Rodopar 1015'!$J:$J,'Doc Há Pagar | Rodopar 1015'!$A:$A,$B79&$E79&$F79,'Doc Há Pagar | Rodopar 1015'!$B:$B,T$1) -> 0 | U79: =SUMIFS('Doc''s Pagos | Rodopar 108'!$J:$J,'Doc''s Pagos | Rodopar 108'!$A:$A,$B79&$E79&$F79&$J79,'Doc''s Pagos | Rodopar 108'!$B:$B,U$1)+SUMIFS('Doc Há Pagar | Rodopar 1015'!$J:$J,'Doc Há Pagar | Rodopar 1015'!$A:$A,$B79&$E79&$F79,'Doc Há Pagar | Rodopar 1015'!$B:$B,U$1) -> 386 | V79: =SUMIFS('Doc''s Pagos | Rodopar 108'!$J:$J,'Doc''s Pagos | Rodopar 108'!$A:$A,$B79&$E79&$F79&$J79,'Doc''s Pagos | Rodopar 108'!$B:$B,V$1)+SUMIFS('Doc Há Pagar | Rodopar 1015'!$J:$J,'Doc Há Pagar | Rodopar 1015'!$A:$A,$B79&$E79&$F79,'Doc Há Pagar | Rodopar 1015'!$B:$B,V$1) -> 0 | W79: =SUMIFS('Doc''s Pagos | Rodopar 108'!$J:$J,'Doc''s Pagos | Rodopar 108'!$A:$A,$B79&$E79&$F79&$J79,'Doc''s Pagos | Rodopar 108'!$B:$B,W$1)+SUMIFS('Doc Há Pagar | Rodopar 1015'!$J:$J,'Doc Há Pagar | Rodopar 1015'!$A:$A,$B79&$E79&$F79,'Doc Há Pagar | Rodopar 1015'!$B:$B,W$1) -> 0 | X79: =SUMIFS('Doc''s Pagos | Rodopar 108'!$J:$J,'Doc''s Pagos | Rodopar 108'!$A:$A,$B79&$E79&$F79&$J79,'Doc''s Pagos | Rodopar 108'!$B:$B,X$1)+SUMIFS('Doc Há Pagar | Rodopar 1015'!$J:$J,'Doc Há Pagar | Rodopar 1015'!$A:$A,$B79&$E79&$F79,'Doc Há Pagar | Rodopar 1015'!$B:$B,X$1) -> 0 | Y79: =SUMIFS('Doc''s Pagos | Rodopar 108'!$J:$J,'Doc''s Pagos | Rodopar 108'!$A:$A,$B79&$E79&$F79&$J79,'Doc''s Pagos | Rodopar 108'!$B:$B,Y$1)+SUMIFS('Doc Há Pagar | Rodopar 1015'!$J:$J,'Doc Há Pagar | Rodopar 1015'!$A:$A,$B79&$E79&$F79,'Doc Há Pagar | Rodopar 1015'!$B:$B,Y$1) -> 0 | Z79: =SUMIFS('Doc''s Pagos | Rodopar 108'!$J:$J,'Doc''s Pagos | Rodopar 108'!$A:$A,$B79&$E79&$F79&$J79,'Doc''s Pagos | Rodopar 108'!$B:$B,Z$1)+SUMIFS('Doc Há Pagar | Rodopar 1015'!$J:$J,'Doc Há Pagar | Rodopar 1015'!$A:$A,$B79&$E79&$F79,'Doc Há Pagar | Rodopar 1015'!$B:$B,Z$1) -> 0 | ... AD79: =SUMIFS('Doc''s Pagos | Rodopar 108'!$J:$J,'Doc''s Pagos | Rodopar 108'!$A:$A,$B79&$E79&$F79&$J79,'Doc''s Pagos | Rodopar 108'!$B:$B,AD$1)+SUMIFS('Doc Há Pagar | Rodopar 1015'!$J:$J,'Doc Há Pagar | Rodopar 1015'!$A:$A,$B79&$E79&$F79,'Doc Há Pagar | Rodopar 1015'!$B:$B,AD$1) -> 0
A80: =VLOOKUP($E80,Fornecedores!$A:$C,3,0) -> Frota | B80: 16 | C80: =IFERROR(VLOOKUP($E80,Fornecedores!$A:$E,4,0),"") -> Manutenção | D80: =IFERROR(VLOOKUP($E80,Fornecedores!$A:$E,5,0),"") -> Frota Leve OPE | E80: MECANICA CRISTO REI LTDA | F80: NSE | G80: 71.299.614/0001-64 | H80: 87 | I80: 280 | J80: 46071 | K80: 46079 | L80: CONTAGEM | M80: MG | N80: 1556 | O80: GABRIEL.ALBINO | Q80: =SUM(R80:AD80)-I80 -> 0 | S80: =SUMIFS('Doc''s Pagos | Rodopar 108'!$J:$J,'Doc''s Pagos | Rodopar 108'!$A:$A,$B80&$E80&$F80&$J80,'Doc''s Pagos | Rodopar 108'!$B:$B,S$1)+SUMIFS('Doc Há Pagar | Rodopar 1015'!$J:$J,'Doc Há Pagar | Rodopar 1015'!$A:$A,$B80&$E80&$F80,'Doc Há Pagar | Rodopar 1015'!$B:$B,S$1) -> 0 | T80: =SUMIFS('Doc''s Pagos | Rodopar 108'!$J:$J,'Doc''s Pagos | Rodopar 108'!$A:$A,$B80&$E80&$F80&$J80,'Doc''s Pagos | Rodopar 108'!$B:$B,T$1)+SUMIFS('Doc Há Pagar | Rodopar 1015'!$J:$J,'Doc Há Pagar | Rodopar 1015'!$A:$A,$B80&$E80&$F80,'Doc Há Pagar | Rodopar 1015'!$B:$B,T$1) -> 0 | U80: =SUMIFS('Doc''s Pagos | Rodopar 108'!$J:$J,'Doc''s Pagos | Rodopar 108'!$A:$A,$B80&$E80&$F80&$J80,'Doc''s Pagos | Rodopar 108'!$B:$B,U$1)+SUMIFS('Doc Há Pagar | Rodopar 1015'!$J:$J,'Doc Há Pagar | Rodopar 1015'!$A:$A,$B80&$E80&$F80,'Doc Há Pagar | Rodopar 1015'!$B:$B,U$1) -> 280 | V80: =SUMIFS('Doc''s Pagos | Rodopar 108'!$J:$J,'Doc''s Pagos | Rodopar 108'!$A:$A,$B80&$E80&$F80&$J80,'Doc''s Pagos | Rodopar 108'!$B:$B,V$1)+SUMIFS('Doc Há Pagar | Rodopar 1015'!$J:$J,'Doc Há Pagar | Rodopar 1015'!$A:$A,$B80&$E80&$F80,'Doc Há Pagar | Rodopar 1015'!$B:$B,V$1) -> 0 | W80: =SUMIFS('Doc''s Pagos | Rodopar 108'!$J:$J,'Doc''s Pagos | Rodopar 108'!$A:$A,$B80&$E80&$F80&$J80,'Doc''s Pagos | Rodopar 108'!$B:$B,W$1)+SUMIFS('Doc Há Pagar | Rodopar 1015'!$J:$J,'Doc Há Pagar | Rodopar 1015'!$A:$A,$B80&$E80&$F80,'Doc Há Pagar | Rodopar 1015'!$B:$B,W$1) -> 0 | X80: =SUMIFS('Doc''s Pagos | Rodopar 108'!$J:$J,'Doc''s Pagos | Rodopar 108'!$A:$A,$B80&$E80&$F80&$J80,'Doc''s Pagos | Rodopar 108'!$B:$B,X$1)+SUMIFS('Doc Há Pagar | Rodopar 1015'!$J:$J,'Doc Há Pagar | Rodopar 1015'!$A:$A,$B80&$E80&$F80,'Doc Há Pagar | Rodopar 1015'!$B:$B,X$1) -> 0 | Y80: =SUMIFS('Doc''s Pagos | Rodopar 108'!$J:$J,'Doc''s Pagos | Rodopar 108'!$A:$A,$B80&$E80&$F80&$J80,'Doc''s Pagos | Rodopar 108'!$B:$B,Y$1)+SUMIFS('Doc Há Pagar | Rodopar 1015'!$J:$J,'Doc Há Pagar | Rodopar 1015'!$A:$A,$B80&$E80&$F80,'Doc Há Pagar | Rodopar 1015'!$B:$B,Y$1) -> 0 | Z80: =SUMIFS('Doc''s Pagos | Rodopar 108'!$J:$J,'Doc''s Pagos | Rodopar 108'!$A:$A,$B80&$E80&$F80&$J80,'Doc''s Pagos | Rodopar 108'!$B:$B,Z$1)+SUMIFS('Doc Há Pagar | Rodopar 1015'!$J:$J,'Doc Há Pagar | Rodopar 1015'!$A:$A,$B80&$E80&$F80,'Doc Há Pagar | Rodopar 1015'!$B:$B,Z$1) -> 0 | ... AD80: =SUMIFS('Doc''s Pagos | Rodopar 108'!$J:$J,'Doc''s Pagos | Rodopar 108'!$A:$A,$B80&$E80&$F80&$J80,'Doc''s Pagos | Rodopar 108'!$B:$B,AD$1)+SUMIFS('Doc Há Pagar | Rodopar 1015'!$J:$J,'Doc Há Pagar | Rodopar 1015'!$A:$A,$B80&$E80&$F80,'Doc Há Pagar | Rodopar 1015'!$B:$B,AD$1) -> 0
A81: =VLOOKUP($E81,Fornecedores!$A:$C,3,0) -> Frota | B81: 403 | C81: =IFERROR(VLOOKUP($E81,Fornecedores!$A:$E,4,0),"") -> Manutenção | D81: =IFERROR(VLOOKUP($E81,Fornecedores!$A:$E,5,0),"") -> Vans | E81: INGA VEICULOS LTDA - UBERLANDIA | F81: NSE | G81: 01.994.951/0019-15 | H81: 87 | I81: 924 | J81: 46076 | K81: 46076 | L81: UBERLANDIA | M81: MG | N81: 1556 | O81: GABRIEL.ALBINO | Q81: =SUM(R81:AD81)-I81 -> 0 | S81: =SUMIFS('Doc''s Pagos | Rodopar 108'!$J:$J,'Doc''s Pagos | Rodopar 108'!$A:$A,$B81&$E81&$F81&$J81,'Doc''s Pagos | Rodopar 108'!$B:$B,S$1)+SUMIFS('Doc Há Pagar | Rodopar 1015'!$J:$J,'Doc Há Pagar | Rodopar 1015'!$A:$A,$B81&$E81&$F81,'Doc Há Pagar | Rodopar 1015'!$B:$B,S$1) -> 0 | T81: =SUMIFS('Doc''s Pagos | Rodopar 108'!$J:$J,'Doc''s Pagos | Rodopar 108'!$A:$A,$B81&$E81&$F81&$J81,'Doc''s Pagos | Rodopar 108'!$B:$B,T$1)+SUMIFS('Doc Há Pagar | Rodopar 1015'!$J:$J,'Doc Há Pagar | Rodopar 1015'!$A:$A,$B81&$E81&$F81,'Doc Há Pagar | Rodopar 1015'!$B:$B,T$1) -> 924 | U81: =SUMIFS('Doc''s Pagos | Rodopar 108'!$J:$J,'Doc''s Pagos | Rodopar 108'!$A:$A,$B81&$E81&$F81&$J81,'Doc''s Pagos | Rodopar 108'!$B:$B,U$1)+SUMIFS('Doc Há Pagar | Rodopar 1015'!$J:$J,'Doc Há Pagar | Rodopar 1015'!$A:$A,$B81&$E81&$F81,'Doc Há Pagar | Rodopar 1015'!$B:$B,U$1) -> 0 | V81: =SUMIFS('Doc''s Pagos | Rodopar 108'!$J:$J,'Doc''s Pagos | Rodopar 108'!$A:$A,$B81&$E81&$F81&$J81,'Doc''s Pagos | Rodopar 108'!$B:$B,V$1)+SUMIFS('Doc Há Pagar | Rodopar 1015'!$J:$J,'Doc Há Pagar | Rodopar 1015'!$A:$A,$B81&$E81&$F81,'Doc Há Pagar | Rodopar 1015'!$B:$B,V$1) -> 0 | W81: =SUMIFS('Doc''s Pagos | Rodopar 108'!$J:$J,'Doc''s Pagos | Rodopar 108'!$A:$A,$B81&$E81&$F81&$J81,'Doc''s Pagos | Rodopar 108'!$B:$B,W$1)+SUMIFS('Doc Há Pagar | Rodopar 1015'!$J:$J,'Doc Há Pagar | Rodopar 1015'!$A:$A,$B81&$E81&$F81,'Doc Há Pagar | Rodopar 1015'!$B:$B,W$1) -> 0 | X81: =SUMIFS('Doc''s Pagos | Rodopar 108'!$J:$J,'Doc''s Pagos | Rodopar 108'!$A:$A,$B81&$E81&$F81&$J81,'Doc''s Pagos | Rodopar 108'!$B:$B,X$1)+SUMIFS('Doc Há Pagar | Rodopar 1015'!$J:$J,'Doc Há Pagar | Rodopar 1015'!$A:$A,$B81&$E81&$F81,'Doc Há Pagar | Rodopar 1015'!$B:$B,X$1) -> 0 | Y81: =SUMIFS('Doc''s Pagos | Rodopar 108'!$J:$J,'Doc''s Pagos | Rodopar 108'!$A:$A,$B81&$E81&$F81&$J81,'Doc''s Pagos | Rodopar 108'!$B:$B,Y$1)+SUMIFS('Doc Há Pagar | Rodopar 1015'!$J:$J,'Doc Há Pagar | Rodopar 1015'!$A:$A,$B81&$E81&$F81,'Doc Há Pagar | Rodopar 1015'!$B:$B,Y$1) -> 0 | Z81: =SUMIFS('Doc''s Pagos | Rodopar 108'!$J:$J,'Doc''s Pagos | Rodopar 108'!$A:$A,$B81&$E81&$F81&$J81,'Doc''s Pagos | Rodopar 108'!$B:$B,Z$1)+SUMIFS('Doc Há Pagar | Rodopar 1015'!$J:$J,'Doc Há Pagar | Rodopar 1015'!$A:$A,$B81&$E81&$F81,'Doc Há Pagar | Rodopar 1015'!$B:$B,Z$1) -> 0 | ... AD81: =SUMIFS('Doc''s Pagos | Rodopar 108'!$J:$J,'Doc''s Pagos | Rodopar 108'!$A:$A,$B81&$E81&$F81&$J81,'Doc''s Pagos | Rodopar 108'!$B:$B,AD$1)+SUMIFS('Doc Há Pagar | Rodopar 1015'!$J:$J,'Doc Há Pagar | Rodopar 1015'!$A:$A,$B81&$E81&$F81,'Doc Há Pagar | Rodopar 1015'!$B:$B,AD$1) -> 0
A82: =VLOOKUP($E82,Fornecedores!$A:$C,3,0) -> Frota | B82: 120 | C82: =IFERROR(VLOOKUP($E82,Fornecedores!$A:$E,4,0),"") -> Documentação | D82: =IFERROR(VLOOKUP($E82,Fornecedores!$A:$E,5,0),"") -> Vistoria Inmetro | E82: CERTIFICAR INSPECAO VEICULAR LTDA | F82: NSE | G82: 65.306.599/0001-31 | H82: 87 | I82: 4480 | J82: 46078 | K82: 46079 | L82: BELO HORIZONTE | M82: MG | N82: 1556 | O82: GABRIEL.ALBINO | Q82: =SUM(R82:AD82)-I82 -> 0 | S82: =SUMIFS('Doc''s Pagos | Rodopar 108'!$J:$J,'Doc''s Pagos | Rodopar 108'!$A:$A,$B82&$E82&$F82&$J82,'Doc''s Pagos | Rodopar 108'!$B:$B,S$1)+SUMIFS('Doc Há Pagar | Rodopar 1015'!$J:$J,'Doc Há Pagar | Rodopar 1015'!$A:$A,$B82&$E82&$F82,'Doc Há Pagar | Rodopar 1015'!$B:$B,S$1) -> 0 | T82: =SUMIFS('Doc''s Pagos | Rodopar 108'!$J:$J,'Doc''s Pagos | Rodopar 108'!$A:$A,$B82&$E82&$F82&$J82,'Doc''s Pagos | Rodopar 108'!$B:$B,T$1)+SUMIFS('Doc Há Pagar | Rodopar 1015'!$J:$J,'Doc Há Pagar | Rodopar 1015'!$A:$A,$B82&$E82&$F82,'Doc Há Pagar | Rodopar 1015'!$B:$B,T$1) -> 4480 | U82: =SUMIFS('Doc''s Pagos | Rodopar 108'!$J:$J,'Doc''s Pagos | Rodopar 108'!$A:$A,$B82&$E82&$F82&$J82,'Doc''s Pagos | Rodopar 108'!$B:$B,U$1)+SUMIFS('Doc Há Pagar | Rodopar 1015'!$J:$J,'Doc Há Pagar | Rodopar 1015'!$A:$A,$B82&$E82&$F82,'Doc Há Pagar | Rodopar 1015'!$B:$B,U$1) -> 0 | V82: =SUMIFS('Doc''s Pagos | Rodopar 108'!$J:$J,'Doc''s Pagos | Rodopar 108'!$A:$A,$B82&$E82&$F82&$J82,'Doc''s Pagos | Rodopar 108'!$B:$B,V$1)+SUMIFS('Doc Há Pagar | Rodopar 1015'!$J:$J,'Doc Há Pagar | Rodopar 1015'!$A:$A,$B82&$E82&$F82,'Doc Há Pagar | Rodopar 1015'!$B:$B,V$1) -> 0 | W82: =SUMIFS('Doc''s Pagos | Rodopar 108'!$J:$J,'Doc''s Pagos | Rodopar 108'!$A:$A,$B82&$E82&$F82&$J82,'Doc''s Pagos | Rodopar 108'!$B:$B,W$1)+SUMIFS('Doc Há Pagar | Rodopar 1015'!$J:$J,'Doc Há Pagar | Rodopar 1015'!$A:$A,$B82&$E82&$F82,'Doc Há Pagar | Rodopar 1015'!$B:$B,W$1) -> 0 | X82: =SUMIFS('Doc''s Pagos | Rodopar 108'!$J:$J,'Doc''s Pagos | Rodopar 108'!$A:$A,$B82&$E82&$F82&$J82,'Doc''s Pagos | Rodopar 108'!$B:$B,X$1)+SUMIFS('Doc Há Pagar | Rodopar 1015'!$J:$J,'Doc Há Pagar | Rodopar 1015'!$A:$A,$B82&$E82&$F82,'Doc Há Pagar | Rodopar 1015'!$B:$B,X$1) -> 0 | Y82: =SUMIFS('Doc''s Pagos | Rodopar 108'!$J:$J,'Doc''s Pagos | Rodopar 108'!$A:$A,$B82&$E82&$F82&$J82,'Doc''s Pagos | Rodopar 108'!$B:$B,Y$1)+SUMIFS('Doc Há Pagar | Rodopar 1015'!$J:$J,'Doc Há Pagar | Rodopar 1015'!$A:$A,$B82&$E82&$F82,'Doc Há Pagar | Rodopar 1015'!$B:$B,Y$1) -> 0 | Z82: =SUMIFS('Doc''s Pagos | Rodopar 108'!$J:$J,'Doc''s Pagos | Rodopar 108'!$A:$A,$B82&$E82&$F82&$J82,'Doc''s Pagos | Rodopar 108'!$B:$B,Z$1)+SUMIFS('Doc Há Pagar | Rodopar 1015'!$J:$J,'Doc Há Pagar | Rodopar 1015'!$A:$A,$B82&$E82&$F82,'Doc Há Pagar | Rodopar 1015'!$B:$B,Z$1) -> 0 | ... AD82: =SUMIFS('Doc''s Pagos | Rodopar 108'!$J:$J,'Doc''s Pagos | Rodopar 108'!$A:$A,$B82&$E82&$F82&$J82,'Doc''s Pagos | Rodopar 108'!$B:$B,AD$1)+SUMIFS('Doc Há Pagar | Rodopar 1015'!$J:$J,'Doc Há Pagar | Rodopar 1015'!$A:$A,$B82&$E82&$F82,'Doc Há Pagar | Rodopar 1015'!$B:$B,AD$1) -> 0
A83: =VLOOKUP($E83,Fornecedores!$A:$C,3,0) -> Frota | B83: 34646 | C83: =IFERROR(VLOOKUP($E83,Fornecedores!$A:$E,4,0),"") -> Manutenção | D83: =IFERROR(VLOOKUP($E83,Fornecedores!$A:$E,5,0),"") -> Vans | E83: MINAS MAQUINAS SA | NOVA LIMA | F83: NFE | G83: 17.161.241/0014-30 | H83: 87 | I83: 4190.67 | J83: 46079 | K83: 46081 | L83: NOVA LIMA | M83: MG | N83: 1556 | O83: GABRIEL.ALBINO | Q83: =SUM(R83:AD83)-I83 -> 0 | S83: =SUMIFS('Doc''s Pagos | Rodopar 108'!$J:$J,'Doc''s Pagos | Rodopar 108'!$A:$A,$B83&$E83&$F83&$J83,'Doc''s Pagos | Rodopar 108'!$B:$B,S$1)+SUMIFS('Doc Há Pagar | Rodopar 1015'!$J:$J,'Doc Há Pagar | Rodopar 1015'!$A:$A,$B83&$E83&$F83,'Doc Há Pagar | Rodopar 1015'!$B:$B,S$1) -> 0 | T83: =SUMIFS('Doc''s Pagos | Rodopar 108'!$J:$J,'Doc''s Pagos | Rodopar 108'!$A:$A,$B83&$E83&$F83&$J83,'Doc''s Pagos | Rodopar 108'!$B:$B,T$1)+SUMIFS('Doc Há Pagar | Rodopar 1015'!$J:$J,'Doc Há Pagar | Rodopar 1015'!$A:$A,$B83&$E83&$F83,'Doc Há Pagar | Rodopar 1015'!$B:$B,T$1) -> 0 | U83: =SUMIFS('Doc''s Pagos | Rodopar 108'!$J:$J,'Doc''s Pagos | Rodopar 108'!$A:$A,$B83&$E83&$F83&$J83,'Doc''s Pagos | Rodopar 108'!$B:$B,U$1)+SUMIFS('Doc Há Pagar | Rodopar 1015'!$J:$J,'Doc Há Pagar | Rodopar 1015'!$A:$A,$B83&$E83&$F83,'Doc Há Pagar | Rodopar 1015'!$B:$B,U$1) -> 4190.67 | V83: =SUMIFS('Doc''s Pagos | Rodopar 108'!$J:$J,'Doc''s Pagos | Rodopar 108'!$A:$A,$B83&$E83&$F83&$J83,'Doc''s Pagos | Rodopar 108'!$B:$B,V$1)+SUMIFS('Doc Há Pagar | Rodopar 1015'!$J:$J,'Doc Há Pagar | Rodopar 1015'!$A:$A,$B83&$E83&$F83,'Doc Há Pagar | Rodopar 1015'!$B:$B,V$1) -> 0 | W83: =SUMIFS('Doc''s Pagos | Rodopar 108'!$J:$J,'Doc''s Pagos | Rodopar 108'!$A:$A,$B83&$E83&$F83&$J83,'Doc''s Pagos | Rodopar 108'!$B:$B,W$1)+SUMIFS('Doc Há Pagar | Rodopar 1015'!$J:$J,'Doc Há Pagar | Rodopar 1015'!$A:$A,$B83&$E83&$F83,'Doc Há Pagar | Rodopar 1015'!$B:$B,W$1) -> 0 | X83: =SUMIFS('Doc''s Pagos | Rodopar 108'!$J:$J,'Doc''s Pagos | Rodopar 108'!$A:$A,$B83&$E83&$F83&$J83,'Doc''s Pagos | Rodopar 108'!$B:$B,X$1)+SUMIFS('Doc Há Pagar | Rodopar 1015'!$J:$J,'Doc Há Pagar | Rodopar 1015'!$A:$A,$B83&$E83&$F83,'Doc Há Pagar | Rodopar 1015'!$B:$B,X$1) -> 0 | Y83: =SUMIFS('Doc''s Pagos | Rodopar 108'!$J:$J,'Doc''s Pagos | Rodopar 108'!$A:$A,$B83&$E83&$F83&$J83,'Doc''s Pagos | Rodopar 108'!$B:$B,Y$1)+SUMIFS('Doc Há Pagar | Rodopar 1015'!$J:$J,'Doc Há Pagar | Rodopar 1015'!$A:$A,$B83&$E83&$F83,'Doc Há Pagar | Rodopar 1015'!$B:$B,Y$1) -> 0 | Z83: =SUMIFS('Doc''s Pagos | Rodopar 108'!$J:$J,'Doc''s Pagos | Rodopar 108'!$A:$A,$B83&$E83&$F83&$J83,'Doc''s Pagos | Rodopar 108'!$B:$B,Z$1)+SUMIFS('Doc Há Pagar | Rodopar 1015'!$J:$J,'Doc Há Pagar | Rodopar 1015'!$A:$A,$B83&$E83&$F83,'Doc Há Pagar | Rodopar 1015'!$B:$B,Z$1) -> 0 | ... AD83: =SUMIFS('Doc''s Pagos | Rodopar 108'!$J:$J,'Doc''s Pagos | Rodopar 108'!$A:$A,$B83&$E83&$F83&$J83,'Doc''s Pagos | Rodopar 108'!$B:$B,AD$1)+SUMIFS('Doc Há Pagar | Rodopar 1015'!$J:$J,'Doc Há Pagar | Rodopar 1015'!$A:$A,$B83&$E83&$F83,'Doc Há Pagar | Rodopar 1015'!$B:$B,AD$1) -> 0
... A107: =VLOOKUP($E107,Fornecedores!$A:$C,3,0) -> Frota | B107: 590 | C107: =IFERROR(VLOOKUP($E107,Fornecedores!$A:$E,4,0),"") -> Manutenção | D107: =IFERROR(VLOOKUP($E107,Fornecedores!$A:$E,5,0),"") -> Vans | E107: MINAS MAQUINAS SA | NOVA LIMA | F107: NSE | G107: 17.161.241/0014-30 | H107: 87 | I107: 927 | J107: 46094 | K107: 46100 | L107: NOVA LIMA | M107: MG | N107: 1556 | O107: GABRIEL.ALBINO | Q107: =SUM(R107:AD107)-I107 -> 0 | S107: =SUMIFS('Doc''s Pagos | Rodopar 108'!$J:$J,'Doc''s Pagos | Rodopar 108'!$A:$A,$B107&$E107&$F107&$J107,'Doc''s Pagos | Rodopar 108'!$B:$B,S$1)+SUMIFS('Doc Há Pagar | Rodopar 1015'!$J:$J,'Doc Há Pagar | Rodopar 1015'!$A:$A,$B107&$E107&$F107,'Doc Há Pagar | Rodopar 1015'!$B:$B,S$1) -> 0 | T107: =SUMIFS('Doc''s Pagos | Rodopar 108'!$J:$J,'Doc''s Pagos | Rodopar 108'!$A:$A,$B107&$E107&$F107&$J107,'Doc''s Pagos | Rodopar 108'!$B:$B,T$1)+SUMIFS('Doc Há Pagar | Rodopar 1015'!$J:$J,'Doc Há Pagar | Rodopar 1015'!$A:$A,$B107&$E107&$F107,'Doc Há Pagar | Rodopar 1015'!$B:$B,T$1) -> 0 | U107: =SUMIFS('Doc''s Pagos | Rodopar 108'!$J:$J,'Doc''s Pagos | Rodopar 108'!$A:$A,$B107&$E107&$F107&$J107,'Doc''s Pagos | Rodopar 108'!$B:$B,U$1)+SUMIFS('Doc Há Pagar | Rodopar 1015'!$J:$J,'Doc Há Pagar | Rodopar 1015'!$A:$A,$B107&$E107&$F107,'Doc Há Pagar | Rodopar 1015'!$B:$B,U$1) -> 0 | V107: =SUMIFS('Doc''s Pagos | Rodopar 108'!$J:$J,'Doc''s Pagos | Rodopar 108'!$A:$A,$B107&$E107&$F107&$J107,'Doc''s Pagos | Rodopar 108'!$B:$B,V$1)+SUMIFS('Doc Há Pagar | Rodopar 1015'!$J:$J,'Doc Há Pagar | Rodopar 1015'!$A:$A,$B107&$E107&$F107,'Doc Há Pagar | Rodopar 1015'!$B:$B,V$1) -> 927 | W107: =SUMIFS('Doc''s Pagos | Rodopar 108'!$J:$J,'Doc''s Pagos | Rodopar 108'!$A:$A,$B107&$E107&$F107&$J107,'Doc''s Pagos | Rodopar 108'!$B:$B,W$1)+SUMIFS('Doc Há Pagar | Rodopar 1015'!$J:$J,'Doc Há Pagar | Rodopar 1015'!$A:$A,$B107&$E107&$F107,'Doc Há Pagar | Rodopar 1015'!$B:$B,W$1) -> 0 | X107: =SUMIFS('Doc''s Pagos | Rodopar 108'!$J:$J,'Doc''s Pagos | Rodopar 108'!$A:$A,$B107&$E107&$F107&$J107,'Doc''s Pagos | Rodopar 108'!$B:$B,X$1)+SUMIFS('Doc Há Pagar | Rodopar 1015'!$J:$J,'Doc Há Pagar | Rodopar 1015'!$A:$A,$B107&$E107&$F107,'Doc Há Pagar | Rodopar 1015'!$B:$B,X$1) -> 0 | Y107: =SUMIFS('Doc''s Pagos | Rodopar 108'!$J:$J,'Doc''s Pagos | Rodopar 108'!$A:$A,$B107&$E107&$F107&$J107,'Doc''s Pagos | Rodopar 108'!$B:$B,Y$1)+SUMIFS('Doc Há Pagar | Rodopar 1015'!$J:$J,'Doc Há Pagar | Rodopar 1015'!$A:$A,$B107&$E107&$F107,'Doc Há Pagar | Rodopar 1015'!$B:$B,Y$1) -> 0 | Z107: =SUMIFS('Doc''s Pagos | Rodopar 108'!$J:$J,'Doc''s Pagos | Rodopar 108'!$A:$A,$B107&$E107&$F107&$J107,'Doc''s Pagos | Rodopar 108'!$B:$B,Z$1)+SUMIFS('Doc Há Pagar | Rodopar 1015'!$J:$J,'Doc Há Pagar | Rodopar 1015'!$A:$A,$B107&$E107&$F107,'Doc Há Pagar | Rodopar 1015'!$B:$B,Z$1) -> 0 | ... AD107: =SUMIFS('Doc''s Pagos | Rodopar 108'!$J:$J,'Doc''s Pagos | Rodopar 108'!$A:$A,$B107&$E107&$F107&$J107,'Doc''s Pagos | Rodopar 108'!$B:$B,AD$1)+SUMIFS('Doc Há Pagar | Rodopar 1015'!$J:$J,'Doc Há Pagar | Rodopar 1015'!$A:$A,$B107&$E107&$F107,'Doc Há Pagar | Rodopar 1015'!$B:$B,AD$1) -> 0
A108: =VLOOKUP($E108,Fornecedores!$A:$C,3,0) -> Frota | B108: AFMTZ-3157195 | C108: =IFERROR(VLOOKUP($E108,Fornecedores!$A:$E,4,0),"") -> OPE Merchandising | D108: =IFERROR(VLOOKUP($E108,Fornecedores!$A:$E,5,0),"") -> Locação | E108: LOCALIZA FLEET S/A | F108: FT | G108: 02.286.479/0001-08 | H108: 87 | I108: 38471.3 | J108: 46097 | K108: 46105 | L108: BELO HORIZONTE | M108: MG | N108: 1556 | O108: GABRIEL.ALBINO | Q108: =SUM(R108:AD108)-I108 -> 0 | S108: =SUMIFS('Doc''s Pagos | Rodopar 108'!$J:$J,'Doc''s Pagos | Rodopar 108'!$A:$A,$B108&$E108&$F108&$J108,'Doc''s Pagos | Rodopar 108'!$B:$B,S$1)+SUMIFS('Doc Há Pagar | Rodopar 1015'!$J:$J,'Doc Há Pagar | Rodopar 1015'!$A:$A,$B108&$E108&$F108,'Doc Há Pagar | Rodopar 1015'!$B:$B,S$1) -> 0 | T108: =SUMIFS('Doc''s Pagos | Rodopar 108'!$J:$J,'Doc''s Pagos | Rodopar 108'!$A:$A,$B108&$E108&$F108&$J108,'Doc''s Pagos | Rodopar 108'!$B:$B,T$1)+SUMIFS('Doc Há Pagar | Rodopar 1015'!$J:$J,'Doc Há Pagar | Rodopar 1015'!$A:$A,$B108&$E108&$F108,'Doc Há Pagar | Rodopar 1015'!$B:$B,T$1) -> 0 | U108: =SUMIFS('Doc''s Pagos | Rodopar 108'!$J:$J,'Doc''s Pagos | Rodopar 108'!$A:$A,$B108&$E108&$F108&$J108,'Doc''s Pagos | Rodopar 108'!$B:$B,U$1)+SUMIFS('Doc Há Pagar | Rodopar 1015'!$J:$J,'Doc Há Pagar | Rodopar 1015'!$A:$A,$B108&$E108&$F108,'Doc Há Pagar | Rodopar 1015'!$B:$B,U$1) -> 38471.3 | V108: =SUMIFS('Doc''s Pagos | Rodopar 108'!$J:$J,'Doc''s Pagos | Rodopar 108'!$A:$A,$B108&$E108&$F108&$J108,'Doc''s Pagos | Rodopar 108'!$B:$B,V$1)+SUMIFS('Doc Há Pagar | Rodopar 1015'!$J:$J,'Doc Há Pagar | Rodopar 1015'!$A:$A,$B108&$E108&$F108,'Doc Há Pagar | Rodopar 1015'!$B:$B,V$1) -> 0 | W108: =SUMIFS('Doc''s Pagos | Rodopar 108'!$J:$J,'Doc''s Pagos | Rodopar 108'!$A:$A,$B108&$E108&$F108&$J108,'Doc''s Pagos | Rodopar 108'!$B:$B,W$1)+SUMIFS('Doc Há Pagar | Rodopar 1015'!$J:$J,'Doc Há Pagar | Rodopar 1015'!$A:$A,$B108&$E108&$F108,'Doc Há Pagar | Rodopar 1015'!$B:$B,W$1) -> 0 | X108: =SUMIFS('Doc''s Pagos | Rodopar 108'!$J:$J,'Doc''s Pagos | Rodopar 108'!$A:$A,$B108&$E108&$F108&$J108,'Doc''s Pagos | Rodopar 108'!$B:$B,X$1)+SUMIFS('Doc Há Pagar | Rodopar 1015'!$J:$J,'Doc Há Pagar | Rodopar 1015'!$A:$A,$B108&$E108&$F108,'Doc Há Pagar | Rodopar 1015'!$B:$B,X$1) -> 0 | Y108: =SUMIFS('Doc''s Pagos | Rodopar 108'!$J:$J,'Doc''s Pagos | Rodopar 108'!$A:$A,$B108&$E108&$F108&$J108,'Doc''s Pagos | Rodopar 108'!$B:$B,Y$1)+SUMIFS('Doc Há Pagar | Rodopar 1015'!$J:$J,'Doc Há Pagar | Rodopar 1015'!$A:$A,$B108&$E108&$F108,'Doc Há Pagar | Rodopar 1015'!$B:$B,Y$1) -> 0 | Z108: =SUMIFS('Doc''s Pagos | Rodopar 108'!$J:$J,'Doc''s Pagos | Rodopar 108'!$A:$A,$B108&$E108&$F108&$J108,'Doc''s Pagos | Rodopar 108'!$B:$B,Z$1)+SUMIFS('Doc Há Pagar | Rodopar 1015'!$J:$J,'Doc Há Pagar | Rodopar 1015'!$A:$A,$B108&$E108&$F108,'Doc Há Pagar | Rodopar 1015'!$B:$B,Z$1) -> 0 | ... AD108: =SUMIFS('Doc''s Pagos | Rodopar 108'!$J:$J,'Doc''s Pagos | Rodopar 108'!$A:$A,$B108&$E108&$F108&$J108,'Doc''s Pagos | Rodopar 108'!$B:$B,AD$1)+SUMIFS('Doc Há Pagar | Rodopar 1015'!$J:$J,'Doc Há Pagar | Rodopar 1015'!$A:$A,$B108&$E108&$F108,'Doc Há Pagar | Rodopar 1015'!$B:$B,AD$1) -> 0
A109: =VLOOKUP($E109,Fornecedores!$A:$C,3,0) -> Frota | B109: AGMTZ-3060870 | C109: =IFERROR(VLOOKUP($E109,Fornecedores!$A:$E,4,0),"") -> OPE Merchandising | D109: =IFERROR(VLOOKUP($E109,Fornecedores!$A:$E,5,0),"") -> Locação | E109: LOCALIZA FLEET S/A | F109: FT | G109: 02.286.479/0001-08 | H109: 87 | I109: 410 | J109: 46097 | K109: 46105 | L109: BELO HORIZONTE | M109: MG | N109: 1556 | O109: GABRIEL.ALBINO | Q109: =SUM(R109:AD109)-I109 -> 0 | S109: =SUMIFS('Doc''s Pagos | Rodopar 108'!$J:$J,'Doc''s Pagos | Rodopar 108'!$A:$A,$B109&$E109&$F109&$J109,'Doc''s Pagos | Rodopar 108'!$B:$B,S$1)+SUMIFS('Doc Há Pagar | Rodopar 1015'!$J:$J,'Doc Há Pagar | Rodopar 1015'!$A:$A,$B109&$E109&$F109,'Doc Há Pagar | Rodopar 1015'!$B:$B,S$1) -> 0 | T109: =SUMIFS('Doc''s Pagos | Rodopar 108'!$J:$J,'Doc''s Pagos | Rodopar 108'!$A:$A,$B109&$E109&$F109&$J109,'Doc''s Pagos | Rodopar 108'!$B:$B,T$1)+SUMIFS('Doc Há Pagar | Rodopar 1015'!$J:$J,'Doc Há Pagar | Rodopar 1015'!$A:$A,$B109&$E109&$F109,'Doc Há Pagar | Rodopar 1015'!$B:$B,T$1) -> 0 | U109: =SUMIFS('Doc''s Pagos | Rodopar 108'!$J:$J,'Doc''s Pagos | Rodopar 108'!$A:$A,$B109&$E109&$F109&$J109,'Doc''s Pagos | Rodopar 108'!$B:$B,U$1)+SUMIFS('Doc Há Pagar | Rodopar 1015'!$J:$J,'Doc Há Pagar | Rodopar 1015'!$A:$A,$B109&$E109&$F109,'Doc Há Pagar | Rodopar 1015'!$B:$B,U$1) -> 0 | V109: =SUMIFS('Doc''s Pagos | Rodopar 108'!$J:$J,'Doc''s Pagos | Rodopar 108'!$A:$A,$B109&$E109&$F109&$J109,'Doc''s Pagos | Rodopar 108'!$B:$B,V$1)+SUMIFS('Doc Há Pagar | Rodopar 1015'!$J:$J,'Doc Há Pagar | Rodopar 1015'!$A:$A,$B109&$E109&$F109,'Doc Há Pagar | Rodopar 1015'!$B:$B,V$1) -> 410 | W109: =SUMIFS('Doc''s Pagos | Rodopar 108'!$J:$J,'Doc''s Pagos | Rodopar 108'!$A:$A,$B109&$E109&$F109&$J109,'Doc''s Pagos | Rodopar 108'!$B:$B,W$1)+SUMIFS('Doc Há Pagar | Rodopar 1015'!$J:$J,'Doc Há Pagar | Rodopar 1015'!$A:$A,$B109&$E109&$F109,'Doc Há Pagar | Rodopar 1015'!$B:$B,W$1) -> 0 | X109: =SUMIFS('Doc''s Pagos | Rodopar 108'!$J:$J,'Doc''s Pagos | Rodopar 108'!$A:$A,$B109&$E109&$F109&$J109,'Doc''s Pagos | Rodopar 108'!$B:$B,X$1)+SUMIFS('Doc Há Pagar | Rodopar 1015'!$J:$J,'Doc Há Pagar | Rodopar 1015'!$A:$A,$B109&$E109&$F109,'Doc Há Pagar | Rodopar 1015'!$B:$B,X$1) -> 0 | Y109: =SUMIFS('Doc''s Pagos | Rodopar 108'!$J:$J,'Doc''s Pagos | Rodopar 108'!$A:$A,$B109&$E109&$F109&$J109,'Doc''s Pagos | Rodopar 108'!$B:$B,Y$1)+SUMIFS('Doc Há Pagar | Rodopar 1015'!$J:$J,'Doc Há Pagar | Rodopar 1015'!$A:$A,$B109&$E109&$F109,'Doc Há Pagar | Rodopar 1015'!$B:$B,Y$1) -> 0 | Z109: =SUMIFS('Doc''s Pagos | Rodopar 108'!$J:$J,'Doc''s Pagos | Rodopar 108'!$A:$A,$B109&$E109&$F109&$J109,'Doc''s Pagos | Rodopar 108'!$B:$B,Z$1)+SUMIFS('Doc Há Pagar | Rodopar 1015'!$J:$J,'Doc Há Pagar | Rodopar 1015'!$A:$A,$B109&$E109&$F109,'Doc Há Pagar | Rodopar 1015'!$B:$B,Z$1) -> 0 | ... AD109: =SUMIFS('Doc''s Pagos | Rodopar 108'!$J:$J,'Doc''s Pagos | Rodopar 108'!$A:$A,$B109&$E109&$F109&$J109,'Doc''s Pagos | Rodopar 108'!$B:$B,AD$1)+SUMIFS('Doc Há Pagar | Rodopar 1015'!$J:$J,'Doc Há Pagar | Rodopar 1015'!$A:$A,$B109&$E109&$F109,'Doc Há Pagar | Rodopar 1015'!$B:$B,AD$1) -> 0
A110: =VLOOKUP($E110,Fornecedores!$A:$C,3,0) -> Frota | B110: AGMTZ-3060911 | C110: =IFERROR(VLOOKUP($E110,Fornecedores!$A:$E,4,0),"") -> OPE Merchandising | D110: =IFERROR(VLOOKUP($E110,Fornecedores!$A:$E,5,0),"") -> Locação | E110: LOCALIZA FLEET S/A | F110: FT | G110: 02.286.479/0001-08 | H110: 87 | I110: 139.13 | J110: 46097 | K110: 46112 | L110: BELO HORIZONTE | M110: MG | N110: 1556 | O110: GABRIEL.ALBINO | Q110: =SUM(R110:AD110)-I110 -> 0 | S110: =SUMIFS('Doc''s Pagos | Rodopar 108'!$J:$J,'Doc''s Pagos | Rodopar 108'!$A:$A,$B110&$E110&$F110&$J110,'Doc''s Pagos | Rodopar 108'!$B:$B,S$1)+SUMIFS('Doc Há Pagar | Rodopar 1015'!$J:$J,'Doc Há Pagar | Rodopar 1015'!$A:$A,$B110&$E110&$F110,'Doc Há Pagar | Rodopar 1015'!$B:$B,S$1) -> 0 | T110: =SUMIFS('Doc''s Pagos | Rodopar 108'!$J:$J,'Doc''s Pagos | Rodopar 108'!$A:$A,$B110&$E110&$F110&$J110,'Doc''s Pagos | Rodopar 108'!$B:$B,T$1)+SUMIFS('Doc Há Pagar | Rodopar 1015'!$J:$J,'Doc Há Pagar | Rodopar 1015'!$A:$A,$B110&$E110&$F110,'Doc Há Pagar | Rodopar 1015'!$B:$B,T$1) -> 0 | U110: =SUMIFS('Doc''s Pagos | Rodopar 108'!$J:$J,'Doc''s Pagos | Rodopar 108'!$A:$A,$B110&$E110&$F110&$J110,'Doc''s Pagos | Rodopar 108'!$B:$B,U$1)+SUMIFS('Doc Há Pagar | Rodopar 1015'!$J:$J,'Doc Há Pagar | Rodopar 1015'!$A:$A,$B110&$E110&$F110,'Doc Há Pagar | Rodopar 1015'!$B:$B,U$1) -> 0 | V110: =SUMIFS('Doc''s Pagos | Rodopar 108'!$J:$J,'Doc''s Pagos | Rodopar 108'!$A:$A,$B110&$E110&$F110&$J110,'Doc''s Pagos | Rodopar 108'!$B:$B,V$1)+SUMIFS('Doc Há Pagar | Rodopar 1015'!$J:$J,'Doc Há Pagar | Rodopar 1015'!$A:$A,$B110&$E110&$F110,'Doc Há Pagar | Rodopar 1015'!$B:$B,V$1) -> 139.13 | W110: =SUMIFS('Doc''s Pagos | Rodopar 108'!$J:$J,'Doc''s Pagos | Rodopar 108'!$A:$A,$B110&$E110&$F110&$J110,'Doc''s Pagos | Rodopar 108'!$B:$B,W$1)+SUMIFS('Doc Há Pagar | Rodopar 1015'!$J:$J,'Doc Há Pagar | Rodopar 1015'!$A:$A,$B110&$E110&$F110,'Doc Há Pagar | Rodopar 1015'!$B:$B,W$1) -> 0 | X110: =SUMIFS('Doc''s Pagos | Rodopar 108'!$J:$J,'Doc''s Pagos | Rodopar 108'!$A:$A,$B110&$E110&$F110&$J110,'Doc''s Pagos | Rodopar 108'!$B:$B,X$1)+SUMIFS('Doc Há Pagar | Rodopar 1015'!$J:$J,'Doc Há Pagar | Rodopar 1015'!$A:$A,$B110&$E110&$F110,'Doc Há Pagar | Rodopar 1015'!$B:$B,X$1) -> 0 | Y110: =SUMIFS('Doc''s Pagos | Rodopar 108'!$J:$J,'Doc''s Pagos | Rodopar 108'!$A:$A,$B110&$E110&$F110&$J110,'Doc''s Pagos | Rodopar 108'!$B:$B,Y$1)+SUMIFS('Doc Há Pagar | Rodopar 1015'!$J:$J,'Doc Há Pagar | Rodopar 1015'!$A:$A,$B110&$E110&$F110,'Doc Há Pagar | Rodopar 1015'!$B:$B,Y$1) -> 0 | Z110: =SUMIFS('Doc''s Pagos | Rodopar 108'!$J:$J,'Doc''s Pagos | Rodopar 108'!$A:$A,$B110&$E110&$F110&$J110,'Doc''s Pagos | Rodopar 108'!$B:$B,Z$1)+SUMIFS('Doc Há Pagar | Rodopar 1015'!$J:$J,'Doc Há Pagar | Rodopar 1015'!$A:$A,$B110&$E110&$F110,'Doc Há Pagar | Rodopar 1015'!$B:$B,Z$1) -> 0 | ... AD110: =SUMIFS('Doc''s Pagos | Rodopar 108'!$J:$J,'Doc''s Pagos | Rodopar 108'!$A:$A,$B110&$E110&$F110&$J110,'Doc''s Pagos | Rodopar 108'!$B:$B,AD$1)+SUMIFS('Doc Há Pagar | Rodopar 1015'!$J:$J,'Doc Há Pagar | Rodopar 1015'!$A:$A,$B110&$E110&$F110,'Doc Há Pagar | Rodopar 1015'!$B:$B,AD$1) -> 0
A111: =VLOOKUP($E111,Fornecedores!$A:$C,3,0) -> Frota | B111: AMGTZ-3060899 | C111: =IFERROR(VLOOKUP($E111,Fornecedores!$A:$E,4,0),"") -> OPE Merchandising | D111: =IFERROR(VLOOKUP($E111,Fornecedores!$A:$E,5,0),"") -> Locação | E111: LOCALIZA FLEET S/A | F111: FT | G111: 02.286.479/0001-08 | H111: 87 | I111: 139.13 | J111: 46097 | K111: 46112 | L111: BELO HORIZONTE | M111: MG | N111: 1556 | O111: GABRIEL.ALBINO | Q111: =SUM(R111:AD111)-I111 -> 0 | S111: =SUMIFS('Doc''s Pagos | Rodopar 108'!$J:$J,'Doc''s Pagos | Rodopar 108'!$A:$A,$B111&$E111&$F111&$J111,'Doc''s Pagos | Rodopar 108'!$B:$B,S$1)+SUMIFS('Doc Há Pagar | Rodopar 1015'!$J:$J,'Doc Há Pagar | Rodopar 1015'!$A:$A,$B111&$E111&$F111,'Doc Há Pagar | Rodopar 1015'!$B:$B,S$1) -> 0 | T111: =SUMIFS('Doc''s Pagos | Rodopar 108'!$J:$J,'Doc''s Pagos | Rodopar 108'!$A:$A,$B111&$E111&$F111&$J111,'Doc''s Pagos | Rodopar 108'!$B:$B,T$1)+SUMIFS('Doc Há Pagar | Rodopar 1015'!$J:$J,'Doc Há Pagar | Rodopar 1015'!$A:$A,$B111&$E111&$F111,'Doc Há Pagar | Rodopar 1015'!$B:$B,T$1) -> 0 | U111: =SUMIFS('Doc''s Pagos | Rodopar 108'!$J:$J,'Doc''s Pagos | Rodopar 108'!$A:$A,$B111&$E111&$F111&$J111,'Doc''s Pagos | Rodopar 108'!$B:$B,U$1)+SUMIFS('Doc Há Pagar | Rodopar 1015'!$J:$J,'Doc Há Pagar | Rodopar 1015'!$A:$A,$B111&$E111&$F111,'Doc Há Pagar | Rodopar 1015'!$B:$B,U$1) -> 0 | V111: =SUMIFS('Doc''s Pagos | Rodopar 108'!$J:$J,'Doc''s Pagos | Rodopar 108'!$A:$A,$B111&$E111&$F111&$J111,'Doc''s Pagos | Rodopar 108'!$B:$B,V$1)+SUMIFS('Doc Há Pagar | Rodopar 1015'!$J:$J,'Doc Há Pagar | Rodopar 1015'!$A:$A,$B111&$E111&$F111,'Doc Há Pagar | Rodopar 1015'!$B:$B,V$1) -> 139.13 | W111: =SUMIFS('Doc''s Pagos | Rodopar 108'!$J:$J,'Doc''s Pagos | Rodopar 108'!$A:$A,$B111&$E111&$F111&$J111,'Doc''s Pagos | Rodopar 108'!$B:$B,W$1)+SUMIFS('Doc Há Pagar | Rodopar 1015'!$J:$J,'Doc Há Pagar | Rodopar 1015'!$A:$A,$B111&$E111&$F111,'Doc Há Pagar | Rodopar 1015'!$B:$B,W$1) -> 0 | X111: =SUMIFS('Doc''s Pagos | Rodopar 108'!$J:$J,'Doc''s Pagos | Rodopar 108'!$A:$A,$B111&$E111&$F111&$J111,'Doc''s Pagos | Rodopar 108'!$B:$B,X$1)+SUMIFS('Doc Há Pagar | Rodopar 1015'!$J:$J,'Doc Há Pagar | Rodopar 1015'!$A:$A,$B111&$E111&$F111,'Doc Há Pagar | Rodopar 1015'!$B:$B,X$1) -> 0 | Y111: =SUMIFS('Doc''s Pagos | Rodopar 108'!$J:$J,'Doc''s Pagos | Rodopar 108'!$A:$A,$B111&$E111&$F111&$J111,'Doc''s Pagos | Rodopar 108'!$B:$B,Y$1)+SUMIFS('Doc Há Pagar | Rodopar 1015'!$J:$J,'Doc Há Pagar | Rodopar 1015'!$A:$A,$B111&$E111&$F111,'Doc Há Pagar | Rodopar 1015'!$B:$B,Y$1) -> 0 | Z111: =SUMIFS('Doc''s Pagos | Rodopar 108'!$J:$J,'Doc''s Pagos | Rodopar 108'!$A:$A,$B111&$E111&$F111&$J111,'Doc''s Pagos | Rodopar 108'!$B:$B,Z$1)+SUMIFS('Doc Há Pagar | Rodopar 1015'!$J:$J,'Doc Há Pagar | Rodopar 1015'!$A:$A,$B111&$E111&$F111,'Doc Há Pagar | Rodopar 1015'!$B:$B,Z$1) -> 0 | ... AD111: =SUMIFS('Doc''s Pagos | Rodopar 108'!$J:$J,'Doc''s Pagos | Rodopar 108'!$A:$A,$B111&$E111&$F111&$J111,'Doc''s Pagos | Rodopar 108'!$B:$B,AD$1)+SUMIFS('Doc Há Pagar | Rodopar 1015'!$J:$J,'Doc Há Pagar | Rodopar 1015'!$A:$A,$B111&$E111&$F111,'Doc Há Pagar | Rodopar 1015'!$B:$B,AD$1) -> 0
A112: =VLOOKUP($E112,Fornecedores!$A:$C,3,0) -> Frota | B112: 136211 | C112: =IFERROR(VLOOKUP($E112,Fornecedores!$A:$E,4,0),"") -> Pneus | D112: =IFERROR(VLOOKUP($E112,Fornecedores!$A:$E,5,0),"") -> Compra | E112: GW PNEUS LTDA | F112: NFE | G112: 64.419.393/0008-21 | H112: 87 | I112: 12270 | J112: 46097 | K112: 46100 | L112: BETIM | M112: MG | N112: 1556 | O112: GABRIEL.ALBINO | Q112: =SUM(R112:AD112)-I112 -> 0 | S112: =SUMIFS('Doc''s Pagos | Rodopar 108'!$J:$J,'Doc''s Pagos | Rodopar 108'!$A:$A,$B112&$E112&$F112&$J112,'Doc''s Pagos | Rodopar 108'!$B:$B,S$1)+SUMIFS('Doc Há Pagar | Rodopar 1015'!$J:$J,'Doc Há Pagar | Rodopar 1015'!$A:$A,$B112&$E112&$F112,'Doc Há Pagar | Rodopar 1015'!$B:$B,S$1) -> 0 | T112: =SUMIFS('Doc''s Pagos | Rodopar 108'!$J:$J,'Doc''s Pagos | Rodopar 108'!$A:$A,$B112&$E112&$F112&$J112,'Doc''s Pagos | Rodopar 108'!$B:$B,T$1)+SUMIFS('Doc Há Pagar | Rodopar 1015'!$J:$J,'Doc Há Pagar | Rodopar 1015'!$A:$A,$B112&$E112&$F112,'Doc Há Pagar | Rodopar 1015'!$B:$B,T$1) -> 0 | U112: =SUMIFS('Doc''s Pagos | Rodopar 108'!$J:$J,'Doc''s Pagos | Rodopar 108'!$A:$A,$B112&$E112&$F112&$J112,'Doc''s Pagos | Rodopar 108'!$B:$B,U$1)+SUMIFS('Doc Há Pagar | Rodopar 1015'!$J:$J,'Doc Há Pagar | Rodopar 1015'!$A:$A,$B112&$E112&$F112,'Doc Há Pagar | Rodopar 1015'!$B:$B,U$1) -> 0 | V112: =SUMIFS('Doc''s Pagos | Rodopar 108'!$J:$J,'Doc''s Pagos | Rodopar 108'!$A:$A,$B112&$E112&$F112&$J112,'Doc''s Pagos | Rodopar 108'!$B:$B,V$1)+SUMIFS('Doc Há Pagar | Rodopar 1015'!$J:$J,'Doc Há Pagar | Rodopar 1015'!$A:$A,$B112&$E112&$F112,'Doc Há Pagar | Rodopar 1015'!$B:$B,V$1) -> 0 | W112: =SUMIFS('Doc''s Pagos | Rodopar 108'!$J:$J,'Doc''s Pagos | Rodopar 108'!$A:$A,$B112&$E112&$F112&$J112,'Doc''s Pagos | Rodopar 108'!$B:$B,W$1)+SUMIFS('Doc Há Pagar | Rodopar 1015'!$J:$J,'Doc Há Pagar | Rodopar 1015'!$A:$A,$B112&$E112&$F112,'Doc Há Pagar | Rodopar 1015'!$B:$B,W$1) -> 4090 | X112: =SUMIFS('Doc''s Pagos | Rodopar 108'!$J:$J,'Doc''s Pagos | Rodopar 108'!$A:$A,$B112&$E112&$F112&$J112,'Doc''s Pagos | Rodopar 108'!$B:$B,X$1)+SUMIFS('Doc Há Pagar | Rodopar 1015'!$J:$J,'Doc Há Pagar | Rodopar 1015'!$A:$A,$B112&$E112&$F112,'Doc Há Pagar | Rodopar 1015'!$B:$B,X$1) -> 4090 | Y112: =SUMIFS('Doc''s Pagos | Rodopar 108'!$J:$J,'Doc''s Pagos | Rodopar 108'!$A:$A,$B112&$E112&$F112&$J112,'Doc''s Pagos | Rodopar 108'!$B:$B,Y$1)+SUMIFS('Doc Há Pagar | Rodopar 1015'!$J:$J,'Doc Há Pagar | Rodopar 1015'!$A:$A,$B112&$E112&$F112,'Doc Há Pagar | Rodopar 1015'!$B:$B,Y$1) -> 4090 | Z112: =SUMIFS('Doc''s Pagos | Rodopar 108'!$J:$J,'Doc''s Pagos | Rodopar 108'!$A:$A,$B112&$E112&$F112&$J112,'Doc''s Pagos | Rodopar 108'!$B:$B,Z$1)+SUMIFS('Doc Há Pagar | Rodopar 1015'!$J:$J,'Doc Há Pagar | Rodopar 1015'!$A:$A,$B112&$E112&$F112,'Doc Há Pagar | Rodopar 1015'!$B:$B,Z$1) -> 0 | ... AD112: =SUMIFS('Doc''s Pagos | Rodopar 108'!$J:$J,'Doc''s Pagos | Rodopar 108'!$A:$A,$B112&$E112&$F112&$J112,'Doc''s Pagos | Rodopar 108'!$B:$B,AD$1)+SUMIFS('Doc Há Pagar | Rodopar 1015'!$J:$J,'Doc Há Pagar | Rodopar 1015'!$A:$A,$B112&$E112&$F112,'Doc Há Pagar | Rodopar 1015'!$B:$B,AD$1) -> 0
A113: =VLOOKUP($E113,Fornecedores!$A:$C,3,0) -> Frota | B113: 1004593 | C113: =IFERROR(VLOOKUP($E113,Fornecedores!$A:$E,4,0),"") -> Manutenção | D113: =IFERROR(VLOOKUP($E113,Fornecedores!$A:$E,5,0),"") -> Caminhão | E113: TREVISO BETIM VEICULOS LTDA | F113: NFE | G113: 21.014.220/0001-44 | H113: 87 | I113: 1981.04 | J113: 46098 | K113: 46100 | L113: BETIM | M113: MG | N113: 1556 | O113: GABRIEL.ALBINO | Q113: =SUM(R113:AD113)-I113 -> 0 | S113: =SUMIFS('Doc''s Pagos | Rodopar 108'!$J:$J,'Doc''s Pagos | Rodopar 108'!$A:$A,$B113&$E113&$F113&$J113,'Doc''s Pagos | Rodopar 108'!$B:$B,S$1)+SUMIFS('Doc Há Pagar | Rodopar 1015'!$J:$J,'Doc Há Pagar | Rodopar 1015'!$A:$A,$B113&$E113&$F113,'Doc Há Pagar | Rodopar 1015'!$B:$B,S$1) -> 0 | T113: =SUMIFS('Doc''s Pagos | Rodopar 108'!$J:$J,'Doc''s Pagos | Rodopar 108'!$A:$A,$B113&$E113&$F113&$J113,'Doc''s Pagos | Rodopar 108'!$B:$B,T$1)+SUMIFS('Doc Há Pagar | Rodopar 1015'!$J:$J,'Doc Há Pagar | Rodopar 1015'!$A:$A,$B113&$E113&$F113,'Doc Há Pagar | Rodopar 1015'!$B:$B,T$1) -> 0 | U113: =SUMIFS('Doc''s Pagos | Rodopar 108'!$J:$J,'Doc''s Pagos | Rodopar 108'!$A:$A,$B113&$E113&$F113&$J113,'Doc''s Pagos | Rodopar 108'!$B:$B,U$1)+SUMIFS('Doc Há Pagar | Rodopar 1015'!$J:$J,'Doc Há Pagar | Rodopar 1015'!$A:$A,$B113&$E113&$F113,'Doc Há Pagar | Rodopar 1015'!$B:$B,U$1) -> 0 | V113: =SUMIFS('Doc''s Pagos | Rodopar 108'!$J:$J,'Doc''s Pagos | Rodopar 108'!$A:$A,$B113&$E113&$F113&$J113,'Doc''s Pagos | Rodopar 108'!$B:$B,V$1)+SUMIFS('Doc Há Pagar | Rodopar 1015'!$J:$J,'Doc Há Pagar | Rodopar 1015'!$A:$A,$B113&$E113&$F113,'Doc Há Pagar | Rodopar 1015'!$B:$B,V$1) -> 1981.04 | W113: =SUMIFS('Doc''s Pagos | Rodopar 108'!$J:$J,'Doc''s Pagos | Rodopar 108'!$A:$A,$B113&$E113&$F113&$J113,'Doc''s Pagos | Rodopar 108'!$B:$B,W$1)+SUMIFS('Doc Há Pagar | Rodopar 1015'!$J:$J,'Doc Há Pagar | Rodopar 1015'!$A:$A,$B113&$E113&$F113,'Doc Há Pagar | Rodopar 1015'!$B:$B,W$1) -> 0 | X113: =SUMIFS('Doc''s Pagos | Rodopar 108'!$J:$J,'Doc''s Pagos | Rodopar 108'!$A:$A,$B113&$E113&$F113&$J113,'Doc''s Pagos | Rodopar 108'!$B:$B,X$1)+SUMIFS('Doc Há Pagar | Rodopar 1015'!$J:$J,'Doc Há Pagar | Rodopar 1015'!$A:$A,$B113&$E113&$F113,'Doc Há Pagar | Rodopar 1015'!$B:$B,X$1) -> 0 | Y113: =SUMIFS('Doc''s Pagos | Rodopar 108'!$J:$J,'Doc''s Pagos | Rodopar 108'!$A:$A,$B113&$E113&$F113&$J113,'Doc''s Pagos | Rodopar 108'!$B:$B,Y$1)+SUMIFS('Doc Há Pagar | Rodopar 1015'!$J:$J,'Doc Há Pagar | Rodopar 1015'!$A:$A,$B113&$E113&$F113,'Doc Há Pagar | Rodopar 1015'!$B:$B,Y$1) -> 0 | Z113: =SUMIFS('Doc''s Pagos | Rodopar 108'!$J:$J,'Doc''s Pagos | Rodopar 108'!$A:$A,$B113&$E113&$F113&$J113,'Doc''s Pagos | Rodopar 108'!$B:$B,Z$1)+SUMIFS('Doc Há Pagar | Rodopar 1015'!$J:$J,'Doc Há Pagar | Rodopar 1015'!$A:$A,$B113&$E113&$F113,'Doc Há Pagar | Rodopar 1015'!$B:$B,Z$1) -> 0 | ... AD113: =SUMIFS('Doc''s Pagos | Rodopar 108'!$J:$J,'Doc''s Pagos | Rodopar 108'!$A:$A,$B113&$E113&$F113&$J113,'Doc''s Pagos | Rodopar 108'!$B:$B,AD$1)+SUMIFS('Doc Há Pagar | Rodopar 1015'!$J:$J,'Doc Há Pagar | Rodopar 1015'!$A:$A,$B113&$E113&$F113,'Doc Há Pagar | Rodopar 1015'!$B:$B,AD$1) -> 0
A114: =VLOOKUP($E114,Fornecedores!$A:$C,3,0) -> Frota | B114: 3009 | C114: =IFERROR(VLOOKUP($E114,Fornecedores!$A:$E,4,0),"") -> Pneus | D114: =IFERROR(VLOOKUP($E114,Fornecedores!$A:$E,5,0),"") -> Ressolagem | E114: RECAPAGEM RECATEC LTDA. | F114: NSE | G114: 42.993.214/0001-56 | H114: 87 | I114: 210 | J114: 46098 | K114: 46100 | L114: BETIM | M114: MG | N114: 1556 | O114: GABRIEL.ALBINO | Q114: =SUM(R114:AD114)-I114 -> 0 | S114: =SUMIFS('Doc''s Pagos | Rodopar 108'!$J:$J,'Doc''s Pagos | Rodopar 108'!$A:$A,$B114&$E114&$F114&$J114,'Doc''s Pagos | Rodopar 108'!$B:$B,S$1)+SUMIFS('Doc Há Pagar | Rodopar 1015'!$J:$J,'Doc Há Pagar | Rodopar 1015'!$A:$A,$B114&$E114&$F114,'Doc Há Pagar | Rodopar 1015'!$B:$B,S$1) -> 0 | T114: =SUMIFS('Doc''s Pagos | Rodopar 108'!$J:$J,'Doc''s Pagos | Rodopar 108'!$A:$A,$B114&$E114&$F114&$J114,'Doc''s Pagos | Rodopar 108'!$B:$B,T$1)+SUMIFS('Doc Há Pagar | Rodopar 1015'!$J:$J,'Doc Há Pagar | Rodopar 1015'!$A:$A,$B114&$E114&$F114,'Doc Há Pagar | Rodopar 1015'!$B:$B,T$1) -> 0 | U114: =SUMIFS('Doc''s Pagos | Rodopar 108'!$J:$J,'Doc''s Pagos | Rodopar 108'!$A:$A,$B114&$E114&$F114&$J114,'Doc''s Pagos | Rodopar 108'!$B:$B,U$1)+SUMIFS('Doc Há Pagar | Rodopar 1015'!$J:$J,'Doc Há Pagar | Rodopar 1015'!$A:$A,$B114&$E114&$F114,'Doc Há Pagar | Rodopar 1015'!$B:$B,U$1) -> 0 | V114: =SUMIFS('Doc''s Pagos | Rodopar 108'!$J:$J,'Doc''s Pagos | Rodopar 108'!$A:$A,$B114&$E114&$F114&$J114,'Doc''s Pagos | Rodopar 108'!$B:$B,V$1)+SUMIFS('Doc Há Pagar | Rodopar 1015'!$J:$J,'Doc Há Pagar | Rodopar 1015'!$A:$A,$B114&$E114&$F114,'Doc Há Pagar | Rodopar 1015'!$B:$B,V$1) -> 210 | W114: =SUMIFS('Doc''s Pagos | Rodopar 108'!$J:$J,'Doc''s Pagos | Rodopar 108'!$A:$A,$B114&$E114&$F114&$J114,'Doc''s Pagos | Rodopar 108'!$B:$B,W$1)+SUMIFS('Doc Há Pagar | Rodopar 1015'!$J:$J,'Doc Há Pagar | Rodopar 1015'!$A:$A,$B114&$E114&$F114,'Doc Há Pagar | Rodopar 1015'!$B:$B,W$1) -> 0 | X114: =SUMIFS('Doc''s Pagos | Rodopar 108'!$J:$J,'Doc''s Pagos | Rodopar 108'!$A:$A,$B114&$E114&$F114&$J114,'Doc''s Pagos | Rodopar 108'!$B:$B,X$1)+SUMIFS('Doc Há Pagar | Rodopar 1015'!$J:$J,'Doc Há Pagar | Rodopar 1015'!$A:$A,$B114&$E114&$F114,'Doc Há Pagar | Rodopar 1015'!$B:$B,X$1) -> 0 | Y114: =SUMIFS('Doc''s Pagos | Rodopar 108'!$J:$J,'Doc''s Pagos | Rodopar 108'!$A:$A,$B114&$E114&$F114&$J114,'Doc''s Pagos | Rodopar 108'!$B:$B,Y$1)+SUMIFS('Doc Há Pagar | Rodopar 1015'!$J:$J,'Doc Há Pagar | Rodopar 1015'!$A:$A,$B114&$E114&$F114,'Doc Há Pagar | Rodopar 1015'!$B:$B,Y$1) -> 0 | Z114: =SUMIFS('Doc''s Pagos | Rodopar 108'!$J:$J,'Doc''s Pagos | Rodopar 108'!$A:$A,$B114&$E114&$F114&$J114,'Doc''s Pagos | Rodopar 108'!$B:$B,Z$1)+SUMIFS('Doc Há Pagar | Rodopar 1015'!$J:$J,'Doc Há Pagar | Rodopar 1015'!$A:$A,$B114&$E114&$F114,'Doc Há Pagar | Rodopar 1015'!$B:$B,Z$1) -> 0 | ... AD114: =SUMIFS('Doc''s Pagos | Rodopar 108'!$J:$J,'Doc''s Pagos | Rodopar 108'!$A:$A,$B114&$E114&$F114&$J114,'Doc''s Pagos | Rodopar 108'!$B:$B,AD$1)+SUMIFS('Doc Há Pagar | Rodopar 1015'!$J:$J,'Doc Há Pagar | Rodopar 1015'!$A:$A,$B114&$E114&$F114,'Doc Há Pagar | Rodopar 1015'!$B:$B,AD$1) -> 0
A115: =VLOOKUP($E115,Fornecedores!$A:$C,3,0) -> Frota | B115: 7084 | C115: =IFERROR(VLOOKUP($E115,Fornecedores!$A:$E,4,0),"") -> Manutenção | D115: =IFERROR(VLOOKUP($E115,Fornecedores!$A:$E,5,0),"") -> Caminhão | E115: TREVISO BETIM VEICULOS LTDA | F115: NSE | G115: 21.014.220/0001-44 | H115: 87 | I115: 1231.99 | J115: 46098 | K115: 46100 | L115: BETIM | M115: MG | N115: 1556 | O115: GABRIEL.ALBINO | Q115: =SUM(R115:AD115)-I115 -> 0 | S115: =SUMIFS('Doc''s Pagos | Rodopar 108'!$J:$J,'Doc''s Pagos | Rodopar 108'!$A:$A,$B115&$E115&$F115&$J115,'Doc''s Pagos | Rodopar 108'!$B:$B,S$1)+SUMIFS('Doc Há Pagar | Rodopar 1015'!$J:$J,'Doc Há Pagar | Rodopar 1015'!$A:$A,$B115&$E115&$F115,'Doc Há Pagar | Rodopar 1015'!$B:$B,S$1) -> 0 | T115: =SUMIFS('Doc''s Pagos | Rodopar 108'!$J:$J,'Doc''s Pagos | Rodopar 108'!$A:$A,$B115&$E115&$F115&$J115,'Doc''s Pagos | Rodopar 108'!$B:$B,T$1)+SUMIFS('Doc Há Pagar | Rodopar 1015'!$J:$J,'Doc Há Pagar | Rodopar 1015'!$A:$A,$B115&$E115&$F115,'Doc Há Pagar | Rodopar 1015'!$B:$B,T$1) -> 0 | U115: =SUMIFS('Doc''s Pagos | Rodopar 108'!$J:$J,'Doc''s Pagos | Rodopar 108'!$A:$A,$B115&$E115&$F115&$J115,'Doc''s Pagos | Rodopar 108'!$B:$B,U$1)+SUMIFS('Doc Há Pagar | Rodopar 1015'!$J:$J,'Doc Há Pagar | Rodopar 1015'!$A:$A,$B115&$E115&$F115,'Doc Há Pagar | Rodopar 1015'!$B:$B,U$1) -> 0 | V115: =SUMIFS('Doc''s Pagos | Rodopar 108'!$J:$J,'Doc''s Pagos | Rodopar 108'!$A:$A,$B115&$E115&$F115&$J115,'Doc''s Pagos | Rodopar 108'!$B:$B,V$1)+SUMIFS('Doc Há Pagar | Rodopar 1015'!$J:$J,'Doc Há Pagar | Rodopar 1015'!$A:$A,$B115&$E115&$F115,'Doc Há Pagar | Rodopar 1015'!$B:$B,V$1) -> 1231.99 | W115: =SUMIFS('Doc''s Pagos | Rodopar 108'!$J:$J,'Doc''s Pagos | Rodopar 108'!$A:$A,$B115&$E115&$F115&$J115,'Doc''s Pagos | Rodopar 108'!$B:$B,W$1)+SUMIFS('Doc Há Pagar | Rodopar 1015'!$J:$J,'Doc Há Pagar | Rodopar 1015'!$A:$A,$B115&$E115&$F115,'Doc Há Pagar | Rodopar 1015'!$B:$B,W$1) -> 0 | X115: =SUMIFS('Doc''s Pagos | Rodopar 108'!$J:$J,'Doc''s Pagos | Rodopar 108'!$A:$A,$B115&$E115&$F115&$J115,'Doc''s Pagos | Rodopar 108'!$B:$B,X$1)+SUMIFS('Doc Há Pagar | Rodopar 1015'!$J:$J,'Doc Há Pagar | Rodopar 1015'!$A:$A,$B115&$E115&$F115,'Doc Há Pagar | Rodopar 1015'!$B:$B,X$1) -> 0 | Y115: =SUMIFS('Doc''s Pagos | Rodopar 108'!$J:$J,'Doc''s Pagos | Rodopar 108'!$A:$A,$B115&$E115&$F115&$J115,'Doc''s Pagos | Rodopar 108'!$B:$B,Y$1)+SUMIFS('Doc Há Pagar | Rodopar 1015'!$J:$J,'Doc Há Pagar | Rodopar 1015'!$A:$A,$B115&$E115&$F115,'Doc Há Pagar | Rodopar 1015'!$B:$B,Y$1) -> 0 | Z115: =SUMIFS('Doc''s Pagos | Rodopar 108'!$J:$J,'Doc''s Pagos | Rodopar 108'!$A:$A,$B115&$E115&$F115&$J115,'Doc''s Pagos | Rodopar 108'!$B:$B,Z$1)+SUMIFS('Doc Há Pagar | Rodopar 1015'!$J:$J,'Doc Há Pagar | Rodopar 1015'!$A:$A,$B115&$E115&$F115,'Doc Há Pagar | Rodopar 1015'!$B:$B,Z$1) -> 0 | ... AD115: =SUMIFS('Doc''s Pagos | Rodopar 108'!$J:$J,'Doc''s Pagos | Rodopar 108'!$A:$A,$B115&$E115&$F115&$J115,'Doc''s Pagos | Rodopar 108'!$B:$B,AD$1)+SUMIFS('Doc Há Pagar | Rodopar 1015'!$J:$J,'Doc Há Pagar | Rodopar 1015'!$A:$A,$B115&$E115&$F115,'Doc Há Pagar | Rodopar 1015'!$B:$B,AD$1) -> 0
A116: =VLOOKUP($E116,Fornecedores!$A:$C,3,0) -> Frota | B116: 7814 | C116: =IFERROR(VLOOKUP($E116,Fornecedores!$A:$E,4,0),"") -> Manutenção | D116: =IFERROR(VLOOKUP($E116,Fornecedores!$A:$E,5,0),"") -> Peças E Serviços | E116: DISTRIBUIDORA IDEAL PECAS LTDA | F116: NFE | G116: 53.649.555/0001-25 | H116: 87 | I116: 4000 | J116: 46099 | K116: 46108 | L116: BELO HORIZONTE | M116: MG | N116: 1556 | O116: GABRIEL.ALBINO | Q116: =SUM(R116:AD116)-I116 -> 0 | S116: =SUMIFS('Doc''s Pagos | Rodopar 108'!$J:$J,'Doc''s Pagos | Rodopar 108'!$A:$A,$B116&$E116&$F116&$J116,'Doc''s Pagos | Rodopar 108'!$B:$B,S$1)+SUMIFS('Doc Há Pagar | Rodopar 1015'!$J:$J,'Doc Há Pagar | Rodopar 1015'!$A:$A,$B116&$E116&$F116,'Doc Há Pagar | Rodopar 1015'!$B:$B,S$1) -> 0 | T116: =SUMIFS('Doc''s Pagos | Rodopar 108'!$J:$J,'Doc''s Pagos | Rodopar 108'!$A:$A,$B116&$E116&$F116&$J116,'Doc''s Pagos | Rodopar 108'!$B:$B,T$1)+SUMIFS('Doc Há Pagar | Rodopar 1015'!$J:$J,'Doc Há Pagar | Rodopar 1015'!$A:$A,$B116&$E116&$F116,'Doc Há Pagar | Rodopar 1015'!$B:$B,T$1) -> 0 | U116: =SUMIFS('Doc''s Pagos | Rodopar 108'!$J:$J,'Doc''s Pagos | Rodopar 108'!$A:$A,$B116&$E116&$F116&$J116,'Doc''s Pagos | Rodopar 108'!$B:$B,U$1)+SUMIFS('Doc Há Pagar | Rodopar 1015'!$J:$J,'Doc Há Pagar | Rodopar 1015'!$A:$A,$B116&$E116&$F116,'Doc Há Pagar | Rodopar 1015'!$B:$B,U$1) -> 0 | V116: =SUMIFS('Doc''s Pagos | Rodopar 108'!$J:$J,'Doc''s Pagos | Rodopar 108'!$A:$A,$B116&$E116&$F116&$J116,'Doc''s Pagos | Rodopar 108'!$B:$B,V$1)+SUMIFS('Doc Há Pagar | Rodopar 1015'!$J:$J,'Doc Há Pagar | Rodopar 1015'!$A:$A,$B116&$E116&$F116,'Doc Há Pagar | Rodopar 1015'!$B:$B,V$1) -> 2000 | W116: =SUMIFS('Doc''s Pagos | Rodopar 108'!$J:$J,'Doc''s Pagos | Rodopar 108'!$A:$A,$B116&$E116&$F116&$J116,'Doc''s Pagos | Rodopar 108'!$B:$B,W$1)+SUMIFS('Doc Há Pagar | Rodopar 1015'!$J:$J,'Doc Há Pagar | Rodopar 1015'!$A:$A,$B116&$E116&$F116,'Doc Há Pagar | Rodopar 1015'!$B:$B,W$1) -> 2000 | X116: =SUMIFS('Doc''s Pagos | Rodopar 108'!$J:$J,'Doc''s Pagos | Rodopar 108'!$A:$A,$B116&$E116&$F116&$J116,'Doc''s Pagos | Rodopar 108'!$B:$B,X$1)+SUMIFS('Doc Há Pagar | Rodopar 1015'!$J:$J,'Doc Há Pagar | Rodopar 1015'!$A:$A,$B116&$E116&$F116,'Doc Há Pagar | Rodopar 1015'!$B:$B,X$1) -> 0 | Y116: =SUMIFS('Doc''s Pagos | Rodopar 108'!$J:$J,'Doc''s Pagos | Rodopar 108'!$A:$A,$B116&$E116&$F116&$J116,'Doc''s Pagos | Rodopar 108'!$B:$B,Y$1)+SUMIFS('Doc Há Pagar | Rodopar 1015'!$J:$J,'Doc Há Pagar | Rodopar 1015'!$A:$A,$B116&$E116&$F116,'Doc Há Pagar | Rodopar 1015'!$B:$B,Y$1) -> 0 | Z116: =SUMIFS('Doc''s Pagos | Rodopar 108'!$J:$J,'Doc''s Pagos | Rodopar 108'!$A:$A,$B116&$E116&$F116&$J116,'Doc''s Pagos | Rodopar 108'!$B:$B,Z$1)+SUMIFS('Doc Há Pagar | Rodopar 1015'!$J:$J,'Doc Há Pagar | Rodopar 1015'!$A:$A,$B116&$E116&$F116,'Doc Há Pagar | Rodopar 1015'!$B:$B,Z$1) -> 0 | ... AD116: =SUMIFS('Doc''s Pagos | Rodopar 108'!$J:$J,'Doc''s Pagos | Rodopar 108'!$A:$A,$B116&$E116&$F116&$J116,'Doc''s Pagos | Rodopar 108'!$B:$B,AD$1)+SUMIFS('Doc Há Pagar | Rodopar 1015'!$J:$J,'Doc Há Pagar | Rodopar 1015'!$A:$A,$B116&$E116&$F116,'Doc Há Pagar | Rodopar 1015'!$B:$B,AD$1) -> 0
A117: =VLOOKUP($E117,Fornecedores!$A:$C,3,0) -> Frota | B117: 2729 | C117: =IFERROR(VLOOKUP($E117,Fornecedores!$A:$E,4,0),"") -> Manutenção | D117: =IFERROR(VLOOKUP($E117,Fornecedores!$A:$E,5,0),"") -> Frota Leve OPE | E117: MECANICA CRISTO REI LTDA | F117: NFE | G117: 71.299.614/0001-64 | H117: 87 | I117: 816.5 | J117: 46100 | K117: 46119 | L117: CONTAGEM | M117: MG | N117: 1556 | O117: GABRIEL.ALBINO | Q117: =SUM(R117:AD117)-I117 -> 0 | S117: =SUMIFS('Doc''s Pagos | Rodopar 108'!$J:$J,'Doc''s Pagos | Rodopar 108'!$A:$A,$B117&$E117&$F117&$J117,'Doc''s Pagos | Rodopar 108'!$B:$B,S$1)+SUMIFS('Doc Há Pagar | Rodopar 1015'!$J:$J,'Doc Há Pagar | Rodopar 1015'!$A:$A,$B117&$E117&$F117,'Doc Há Pagar | Rodopar 1015'!$B:$B,S$1) -> 0 | T117: =SUMIFS('Doc''s Pagos | Rodopar 108'!$J:$J,'Doc''s Pagos | Rodopar 108'!$A:$A,$B117&$E117&$F117&$J117,'Doc''s Pagos | Rodopar 108'!$B:$B,T$1)+SUMIFS('Doc Há Pagar | Rodopar 1015'!$J:$J,'Doc Há Pagar | Rodopar 1015'!$A:$A,$B117&$E117&$F117,'Doc Há Pagar | Rodopar 1015'!$B:$B,T$1) -> 0 | U117: =SUMIFS('Doc''s Pagos | Rodopar 108'!$J:$J,'Doc''s Pagos | Rodopar 108'!$A:$A,$B117&$E117&$F117&$J117,'Doc''s Pagos | Rodopar 108'!$B:$B,U$1)+SUMIFS('Doc Há Pagar | Rodopar 1015'!$J:$J,'Doc Há Pagar | Rodopar 1015'!$A:$A,$B117&$E117&$F117,'Doc Há Pagar | Rodopar 1015'!$B:$B,U$1) -> 0 | V117: =SUMIFS('Doc''s Pagos | Rodopar 108'!$J:$J,'Doc''s Pagos | Rodopar 108'!$A:$A,$B117&$E117&$F117&$J117,'Doc''s Pagos | Rodopar 108'!$B:$B,V$1)+SUMIFS('Doc Há Pagar | Rodopar 1015'!$J:$J,'Doc Há Pagar | Rodopar 1015'!$A:$A,$B117&$E117&$F117,'Doc Há Pagar | Rodopar 1015'!$B:$B,V$1) -> 816.5 | W117: =SUMIFS('Doc''s Pagos | Rodopar 108'!$J:$J,'Doc''s Pagos | Rodopar 108'!$A:$A,$B117&$E117&$F117&$J117,'Doc''s Pagos | Rodopar 108'!$B:$B,W$1)+SUMIFS('Doc Há Pagar | Rodopar 1015'!$J:$J,'Doc Há Pagar | Rodopar 1015'!$A:$A,$B117&$E117&$F117,'Doc Há Pagar | Rodopar 1015'!$B:$B,W$1) -> 0 | X117: =SUMIFS('Doc''s Pagos | Rodopar 108'!$J:$J,'Doc''s Pagos | Rodopar 108'!$A:$A,$B117&$E117&$F117&$J117,'Doc''s Pagos | Rodopar 108'!$B:$B,X$1)+SUMIFS('Doc Há Pagar | Rodopar 1015'!$J:$J,'Doc Há Pagar | Rodopar 1015'!$A:$A,$B117&$E117&$F117,'Doc Há Pagar | Rodopar 1015'!$B:$B,X$1) -> 0 | Y117: =SUMIFS('Doc''s Pagos | Rodopar 108'!$J:$J,'Doc''s Pagos | Rodopar 108'!$A:$A,$B117&$E117&$F117&$J117,'Doc''s Pagos | Rodopar 108'!$B:$B,Y$1)+SUMIFS('Doc Há Pagar | Rodopar 1015'!$J:$J,'Doc Há Pagar | Rodopar 1015'!$A:$A,$B117&$E117&$F117,'Doc Há Pagar | Rodopar 1015'!$B:$B,Y$1) -> 0 | Z117: =SUMIFS('Doc''s Pagos | Rodopar 108'!$J:$J,'Doc''s Pagos | Rodopar 108'!$A:$A,$B117&$E117&$F117&$J117,'Doc''s Pagos | Rodopar 108'!$B:$B,Z$1)+SUMIFS('Doc Há Pagar | Rodopar 1015'!$J:$J,'Doc Há Pagar | Rodopar 1015'!$A:$A,$B117&$E117&$F117,'Doc Há Pagar | Rodopar 1015'!$B:$B,Z$1) -> 0 | ... AD117: =SUMIFS('Doc''s Pagos | Rodopar 108'!$J:$J,'Doc''s Pagos | Rodopar 108'!$A:$A,$B117&$E117&$F117&$J117,'Doc''s Pagos | Rodopar 108'!$B:$B,AD$1)+SUMIFS('Doc Há Pagar | Rodopar 1015'!$J:$J,'Doc Há Pagar | Rodopar 1015'!$A:$A,$B117&$E117&$F117,'Doc Há Pagar | Rodopar 1015'!$B:$B,AD$1) -> 0
